Workbook
Name Neighborhood_Main: 'Complete List_09252026'!$A$2:$L$309
Name Query_Neighborhood_List_Affiliations: #REF!

Sheet Complete List_09252026
A1: FIRST | B1: LAST | C1: NAME | D1: ORGANIZATION | E1: ADDRESS | F1: CITY | G1: STATE | H1: ZIP | I1: TELEPHONE | J1: EMAIL | K1: NOTIFICATION PREFERENCES | L1: NEIGHBORHOOD OF INTEREST
A2: Aaron | B2: Peskin | C2: =A2&" "&B2 -> Aaron Peskin | D2: - | E2: 470 Columbus Avenue, Ste. 211 | F2: San Francisco | G2: CA | H2: 94133 | I2: 415-986-7014 | J2: aaron.peskin@earthlink.net | K2: Physical | L2: Citywide
A3: Barry | B3: Perkins | C3: =A3&" "&B3 -> Barry Perkins | D3: - | E3: 2140 Pine Street | F3: San Francisco | G3: CA | H3: 94115 | I3: 415-990-0234 | J3: barry_perkins@yahoo.com | K3: Physical | L3: Western Addition
A4: Marianne | B4: Hesse | C4: =A4&" "&B4 -> Marianne Hesse | D4: - | E4: 101 Belvedere Street | F4: San Francisco | G4: CA | H4: 94117 | I4: 415-665-3657 | J4: mhesse@pacbell.net | K4: Physical | L4: Haight Ashbury
A5: James | B5: Fisher | C5: =A5&" "&B5 -> James Fisher | D5: - | E5: 10495 N De Anza Blvd MS 74-2RC | F5: Cupertino | G5: CA | H5: 95014 | I5: 262-352-9498 | J5: j.benjamin.fisher@gmail.com | K5: Physical | L5: Western Addition
A6: Georgia | B6: Schuttish | C6: =A6&" "&B6 -> Georgia Schuttish | D6: - | E6: 460 Duncan Street | F6: San Francisco | G6: CA | H6: 94131 | I6: - | J6: schuttishtr@sbcglobal.net | K6: Physical | L6: Noe Valley
A7: Russel | B7: Morine | C7: =A7&" "&B7 -> Russel Morine | D7: - | E7: 64 Gillette Avenue | F7: San Francisco | G7: CA | H7: 94134 | I7: 415-740-4014 | J7: rmorine@aol.com | K7: Physical | L7: Bayview
A8: Edward | B8: Stiel | C8: =A8&" "&B8 -> Edward Stiel | D8: 2887 Folsom Street Concerned Residents | E8: 2887 Folsom Street | F8: San Francisco | G8: CA | H8: 94110 | I8: 415-282-5393 | J8: eddiestiel@yahoo.com | K8: Electronic | L8: Mission
C9: Michelle Brown | D9: 318 Frederick St. Tenancy In Common Owner's Association and Board | E9: 318 Frederick Street | F9: San Francisco | G9: CA | H9: 94117 | I9: 415-608-3945 | J9: brownmi@stanford.edu | K9: Electronic | L9: Haight Ashbury
A10: Jeffrey | B10: Kwong | C10: =A10&" "&B10 -> Jeffrey Kwong | D10: District 3 Tenants | E10: 1754 Hyde Street | F10: San Francisco | G10: CA | H10: 94106 | I10: 415-290-5595 | J10: cardinalsf@gmail.com | K10: Physical | L10: Chinatown, Downtown Civic Center, Financial District, Nob Hill, North Beach
A11: Sara | B11: Bartholomew | C11: Marilyn Hersh | D11: 19th Street/Oakwood Neighborhood Association | E11: 3696 19th Street | F11: San Francisco | G11: CA | H11: 94110 | I11: - | J11: hershmari@gmail.com | K11: Electronic | L11: Mission
C12: Leslie Chin | D12: 19th Street/Oakwood Neighborhood Association | E12: 41 Oakwood | F12: San Francisco | G12: CA | H12: 94110 | I12: - | J12: lchinflute@gmail.com | K12: Electronic | L12: Mission
A13: ASNA | B13: Board | C13: =A13&" "&B13 -> ASNA Board | D13: Alamo Square Neighborhood Assocation | E13: 530 Divisadero Street #176 | F13: San Francisco | G13: CA | H13: 94117 | I13: 415-271-5691 | J13: board@alamosq.org | K13: Electronic | L13: Western Addition
A14: Michael | B14: Nulty | C14: =A14&" "&B14 -> Michael Nulty | D14: Alliance for a Better District 6 | E14: P.O. Box 420782 | F14: San Francisco | G14: CA | H14: 94142 | I14: 415-339-8779 | J14: sf_district6@yahoo.com | K14: Physical | L14: Downtown/Civic Center, Financial District, Mission, Nob Hill, South of Market, Treasure Island, Western Addition
A15: Laura | B15: Magnani | C15: =A15&" "&B15 -> Laura Magnani | D15: American Friends Service Committee | E15: 65 Ninth Street | F15: San Francisco | G15: CA | H15: 94103 | I15: 415-565-0201 | J15: sfoffice@afsc.org | K15: Physical | L15: South of Market
A16: Linda | B16: Burton | C16: =A16&" "&B16 -> Linda Burton | D16: Anna Waden Library | E16: 5075 3rd Street | F16: San Francisco | G16: CA | H16: 94124 | I16: 415-715-4100 | K16: Physical | L16: Bayview
A17: Al | B17: Sodini | C17: =A17&" "&B17 -> Al Sodini | D17: Anza Vista Civic Improvement Club | E17: 140 Terra Vista Avenue | F17: San Francisco | G17: CA | H17: 94115 | I17: 415-921-5131 | J17: ducha931@aol.com | K17: Physical | L17: Western Addition
C18: =A18&" "&B18 | D18: Asian Pacific American Community Center | E18: 50 Raymond Ave | F18: San Francisco | G18: CA | H18: 94134 | I18: 415-587-2689 | J18: info@apaccsf.org | K18: Physical | L18: Visitacion Valley
A19: Construction | B19: and Engineering | C19: =A19&" "&B19 -> Construction and Engineering | D19: AT&T | E19: 359 Washington Street, Room 205 | F19: Daly City | G19: CA | H19: 94015 | K19: Physical | L19: Citywide
C20: SatKartar Khalsa | D20: Avila Street Corridor | E20: 333 Avila Street | F20: San Francisco | G20: CA | H20: 94123 | I20: 415-810-2246 | J20: avilastreetcorridor@gmail.com | K20: Electronic | L20: Marina
A21: Board | B21: of Directors | C21: =A21&" "&B21 -> Board of Directors | D21: Balboa Terrace Homes Association | E21: P.O. Box 27642 | F21: San Francisco | G21: CA | H21: 94127 | I21: 415-279-9530 | J21: bthaboard@balboaterrace.org | K21: Electronic | L21: West of Twin Peaks
A22: Yuka | B22: Ioroi | C22: =A22&" "&B22 -> Yuka Ioroi | D22: Balboa Village Merchants Association | E22: 3519 Balboa Street | F22: San Francisco | G22: CA | H22: 94121 | I22: 626-419-2190 | J22: yukaioroi@gmail.com | K22: Physical | L22: Outer Richmond
A23: Diana | B23: Taylor | C23: =A23&" "&B23 -> Diana Taylor | D23: Barbary Coast Neighborhood Association | E23: P.O. Box 2045 | F23: San Francisco | G23: CA | H23: 94126 | I23: - | J23: bcna@bcnasf.org | K23: Electronic | L23: Financial District, North Beach
A24: Daniel | B24: Dodt | C24: =A24&" "&B24 -> Daniel Dodt | D24: BayView Community Planning | E24: 2027 Oakdale Avenue | F24: San Francisco | G24: CA | H24: 94124 | I24: 415-730-2071 | J24: bvhpwatch@mac.com | K24: Electronic | L24: Bayview
A25: Board | B25: Secretary | C25: =A25&" "&B25 -> Board Secretary | D25: Bayview Hill Neighborhood Association | J25: bvhna.secretary@gmail.com bayviewhillsf@gmail.com | K25: Electronic | L25: Bayview
A26: Philip | B26: Williams | D26: Bayview Hunters Point Citizens Advisory Committee | E26: 1550 Evans Avenue | F26: San Francisco | G26: CA | H26: 94124 | J26: bayviewcac@sfgov.org | K26: Electronic | L26: Bayview
A27: Sophie | B27: Constantinou | C27: =A27&" "&B27 -> Sophie Constantinou | D27: Bernal Cut Neighborhood Alliace | E27: 22 Richland Avenue | F27: San Francisco | G27: CA | H27: 94110 | I27: 415-378-6085 | J27: bernalcutpath@gmail.com | K27: Electronic | L27: Bernal Heights, Glen Park
A28: Wendy | B28: Cowles | C28: =A28&" "&B28 -> Wendy Cowles | D28: Bernal Heights East Slope Design Review Board | E28: 89 Banks Street | F28: San Francisco | G28: CA | H28: 94110 | J28: bhesdrb@gmail.com | K28: Electronic | L28: Bernal Heights
A29: Rachel | B29: Ebora | C29: =A29&" "&B29 -> Rachel Ebora | D29: Bernal Heights Housing Corporation | E29: 515 Cortland Avenue | F29: San Francisco | G29: CA | H29: 94110 | K29: Physical | L29: Bernal Heights
A30: Barbara | B30: Lopez | C30: Sulaiman Hyatt | D30: Bernal Heights Neighborhood Center | E30: 1591 Treat Avenue | F30: San Francisco | G30: CA | H30: 94110 | I30: 415-206-2140 | J30: shyatt@bhnc.org | K30: Electronic | L30: Bernal Heights
A31: Andre | B31: Rothblatt | C31: =A31&" "&B31 -> Andre Rothblatt | D31: Bernal Heights Preservation | E31: 475 Nevada Street | F31: San Francisco | G31: CA | H31: 94110 | I31: 415-626-5112 | J31: arothblatt@aol.com | K31: Physical | L31: Bernal Heights
A32: Kathy | B32: Angus | C32: =A32&" "&B32 -> Kathy Angus | D32: Bernal Heights South Slope Organization | E32: 99 Banks Street | F32: San Francisco | G32: CA | H32: 94110 | I32: 415-282-9223 | J32: kathyangus@gmail.com | K32: Electronic | L32: Bernal Heights
C33: Josephine Zhao | D33: Better Housing Policies | E33: 945 Taraval Street | F33: San Francisco | G33: CA | H33: 94116 | I33: 415-871-5715 | J33: info@betterhousingpolicies.org | K33: Electronic | L33: Excelsior, Outer Richmond, Outer Sunset, Parkside, Visitacion Valley
A34: Shamann | B34: Walton | C34: =A34&" "&B34 -> Shamann Walton | D34: Board of Supervisors | E34: 1 Dr. Carlton B Goodlett Place, Room #244 | F34: San Francisco | G34: CA | H34: 94102-4689 | I34: - | J34: waltonstaff@sfgov.org; Percy.Burch@sfgov.org; Tracy.Gallardo@sfgov.org; Natalie.Gee@sfgov.org | K34: Both | L34: Bayview, Potrero Hill, Visitacion Valley
A35: Dean | B35: Preston | C35: Bilal Mahmood | D35: Board of Supervisors | E35: 1 Dr. Carlton B Goodlett Place, Room #244 | F35: San Francisco | G35: CA | H35: 94102-4689 | I35: - | J35: MahmoodStaff@sfgov.org; Raynell.Cooper@sfgov.org | K35: Both | L35: Downtown/Civic Center, Haight Ashbury, Western Addition
A36: Aaron | B36: Peskin | C36: Danny Sauter | D36: Board of Supervisors | E36: 1 Dr. Carlton B Goodlett Place, Room #244 | F36: San Francisco | G36: CA | H36: 94102-4689 | I36: - | J36: SauterStaff@sfgov.org; Michelle.Andrews@sfgov.org; Amy.Lee5@sfgov.org; tita.bell@sfgov.org; tomio.nagano@sfgov.org | K36: Both | L36: Chinatown, Financial District, Nob Hill, North Beach, Russian Hill
A37: Ahsha | B37: Safai | C37: Chyanne Chen | D37: Board of Supervisors | E37: 1 Dr. Carlton B Goodlett Place, Room #244 | F37: San Francisco | G37: CA | H37: 94102-4689 | I37: - | J37: ChenStaff@sfgov.org; Charlie.Sciammas@sfgov.org | K37: Both | L37: Crocker Amazon, Excelsior, Outer Mission, Visitacion Valley
A38: Rafael | B38: Mandelman | C38: =A38&" "&B38 -> Rafael Mandelman | D38: Board of Supervisors | E38: 1 Dr. Carlton B Goodlett Place, Room #244 | F38: San Francisco | G38: CA | H38: 94102-4689 | I38: - | J38: Rafael.Mandelman@sfgov.org; Kyle.Smeallie@sfgov.org; Tom.Temprano@sfgov.org; jacob.bintliff@sfgov.org; mandelmanstaff@sfgov.org | K38: Both | L38: Castro/Upper Market, Diamond Heights, Glen Park, Noe Valley, Twin Peaks
A39: Connie | B39: Chan | C39: =A39&" "&B39 -> Connie Chan | D39: Board of Supervisors | E39: 1 Dr. Carlton B Goodlett Place, Room #244 | F39: San Francisco | G39: CA | H39: 94102-4689 | I39: - | J39: connie.chan@sfgov.org; ian.fregosi@sfgov.org; frances.hsieh@sfgov.org; kelly.groth@sfgov.org; angelina.yu@sfgov.org; ChanStaff@sfgov.org | K39: Both | L39: Inner Richmond, Outer Richmond, Seacliff
A40: Myrna | B40: Melgar | C40: =A40&" "&B40 -> Myrna Melgar | D40: Board of Supervisors | E40: 1 Dr. Carlton B Goodlett Place, Room #244 | F40: San Francisco | G40: CA | H40: 94102-4689 | I40: - | J40: myrna.melgar@sfgov.org; Jennifer.Fieber@sfgov.org; Megan.Imperial@sfgov.org; Lila.Carrillo@sfgov.org; Jen.Low@sfgov.org; melgarstaff@sfgov.org | K40: Both | L40: Inner Sunset, Lakeshore, Ocean View, Parkside, Twin Peaks, West of Twin Peaks
A41: Catherine | B41: Stefani | C41: Stephen Sherrill | D41: Board of Supervisors | E41: 1 Dr. Carlton B Goodlett Place, Room #244 | F41: San Francisco | G41: CA | H41: 94102-4689 | I41: - | J41: SherrillStaff@sfgov.org; Lorenzo.Rosas@sfgov.org | K41: Both | L41: Marina, Pacific Heights, Presidio, Presidio Heights, Russian Hill, Seacliff, Western Addition
A42: Gordon | B42: Mar | C42: Alan Wong | D42: Board of Supervisors | E42: 1 Dr. Carlton B Goodlett Place, Room #244 | F42: San Francisco | G42: CA | H42: 94102-4689 | I42: - | J42: Tiff.Lee@sfgov.org; Jessica.Cen@sfgov.org; Andrew.Sinn@sfgov.org; Derek.Lee@sfgov.org; WongStaff@sfgov.org | K42: Both | L42: Lakeshore, Outer Sunset, Parkside
A43: Matt | B43: Haney | C43: Matt Dorsey | D43: Board of Supervisors | E43: 1 Dr. Carlton B Goodlett Place, Room #244 | F43: San Francisco | G43: CA | H43: 94102-4689 | I43: - | J43: DorseyStaff@sfgov.org; Madison.R.Tam@sfgov.org; Bryan.Dahl@sfgov.org; Leo.Alfaro@sfgov.org | K43: Both | L43: Downtown/Civic Center, South of Market, Treasure Island/YBI
C44: Jackie Fielder | D44: Board of Supervisors | E44: 1 Dr. Carlton B Goodlett Place, Room #244 | F44: San Francisco | G44: CA | H44: 94102-4689 | I44: - | J44: FielderStaff@sfgov.org; Ana.Herrera@sfgov.org; Preston.Kilgore@sfgov.org | K44: Both | L44: Bernal Heights, Excelsior, Mission, Visitacion Valley
C45: Jon Henry | D45: Both Sides of the Conversation | E45: P.O. Box 347518 | F45: San Francisco | G45: CA | H45: 94134 | I45: 415-913-9034 | J45: jonhenry@bsotc.org | K45: Electronic | L45: Bayview, Bernal Heights, Crocker Amazon, Downtown/Civic Center, Excelsior, Glen Park, Haight Ashbury, Potrero Hill, South of Market, Treasure Island, Visitacion Valley, West of Twin Peaks, Western Addition
C46: Dr. Jacques Benghiat | D46: Brannan Google Group | E46: 219 Brannan Street, Unit 12D | F46: San Francisco | G46: CA | H46: 94107 | I46: 408-221-0796 | J46: brannanowner@yahoo.com | K46: Electronic | L46: South of Market
C47: Rasheq Zarif | D47: Buena Vista Neighborhood Association | E47: 1388 Haight Street #1236 | F47: San Francisco | G47: CA | H47: 94117 | I47: 415-371-9307 | J47: info@bvnasf.org | K47: Electronic | L47: Castro/Upper Market
A48: John | B48: Hou | C48: =A48&" "&B48 -> John Hou | D48: Cabrillo Alley Neighbors Association | E48: 742 4th Avenue | F48: San Francisco | G48: CA | H48: 94118 | I48: 415-480-0369 | J48: cabrillo-alley-neighbors-association@googlegroups.com | K48: Physical | L48: Inner Richmond
A49: Alex | B49: Thompson | C49: =A49&" "&B49 -> Alex Thompson | D49: California-Locust Block Neighbors Group | E49: 433 Locust St. | F49: San Francisco | G49: CA | H49: 94118 | I49: 415-407-2775 | J49: alexwt@me.com | K49: Electronic | L49: Presidio Heights
A50: Erick | B50: Arguello | C50: =A50&" "&B50 -> Erick Arguello | D50: Calle 24 Latino Cultural District | E50: 1065 A Hampshire Street | F50: San Francisco | G50: CA | H50: 94110 | I50: 415-323-8939 | J50: eriq94110@aol.com | K50: Physical | L50: Mission
A51: Leonard | B51: Basoco | C51: =A51&" "&B51 -> Leonard Basoco | D51: Carpenters Local 22 | E51: 2085 Third Street | F51: San Francisco | G51: CA | H51: 94107 | I51: 415-355-1322 | J51: ASimi@nccrc.org | K51: Physical | L51: Citywide
A52: Joe | B52: Curtin | C52: =A52&" "&B52 -> Joe Curtin | D52: Castro Area Planning + Action | E52: 584 Castro Street, Suite 169 | F52: San Francisco | G52: CA | H52: 94114 | I52: 415-621-0120 | K52: Physical | L52: Castro/Upper Market
C53: Jesse Sanford & Stephen Torres | D53: Castro LGBTQ Cultural District | E53: 1800 Market Street | F53: San Francisco | G53: CA | H53: 94102 | I53: 415-489-8761 | J53: landuse@castrolgbtq.org | K53: Electronic | L53: Bernal Heights, Castro/Upper Market, Downtown/Civic Center, Mission, Noe Valley, South of Market
A54: Nikolas | B54: Blanchet | C54: =A54&" "&B54 -> Nikolas Blanchet | D54: Castro Merchants | E54: 584 Castro Street #333 | F54: San Francisco | G54: CA | H54: 94114 | I54: 415-431-2359 | J54: info@castromerchants.com | K54: Electronic | L54: Castro/Upper Market
A55: Andrea | B55: Aiello | C55: =A55&" "&B55 -> Andrea Aiello | D55: Castro Upper Market Community Benefit District | E55: 693 14th Street | F55: San Francisco | G55: CA | H55: 94114 | I55: 415-500-1181 | J55: ExecDirector@CastroCBD.org | K55: Electronic | L55: Castro/Upper Market, Haight Ashbury, Noe Valley
A56: Marlayne | B56: Morgan | C56: =A56&" "&B56 -> Marlayne Morgan | D56: Cathedral Hill Neighbors Association | E56: 1200 Gough Street, #17A | F56: San Francisco | G56: CA | H56: 94109 | I56: 415-572-8093 | J56: marlayne16@gmail.com | K56: Electronic | L56: Downtown/Civic Center, Western Addition
A57: CNIA | B57: President | C57: =A57&" "&B57 -> CNIA President | D57: Cayuga Improvement Association | E57: 311 Foote Ave | F57: San Francisco | G57: CA | H57: 94112 | I57: 415-585-7021 | J57: cayugaimprovement@gmail.com | K57: Electronic | L57: Excelsior, Outer Mission
A58: Zoee | B58: Astrachan | C58: =A58&" "&B58 -> Zoee Astrachan | D58: Central 26th Street Neighborhood Coalition | E58: 3441 26th Street | F58: San Francisco | G58: CA | H58: 94114 | I58: 415-285-3960 | J58: za@intersticearchitects.com | K58: Electronic | L58: Mission
A59: Malcom | B59: Yeung | C59: =A59&" "&B59 -> Malcom Yeung | D59: Chinatown Community Development Center (CCDC) | E59: 615 Grant Avenue | F59: San Francisco | G59: CA | H59: 94133 | I59: 415-984-1462 | J59: myeung@chinatowncdc.org; matthias.mormino@chinatowncdc.org; sharon.ng@chinatowncdc.org; tandchow@gmail.com; | K59: Electronic | L59: Chinatown, Financial District, Nob Hill, North Beach, Russian Hill
C60: =A60&" "&B60 | D60: Chinese Chamber of Commerce | E60: 730 Sacramento Street | F60: San Francisco | G60: CA | H60: 94108 | I60: 415-982-3000 | K60: Physical | L60: Chinatown
A61: George | B61: Chan | C61: =A61&" "&B61 -> George Chan | D61: Chinese Newcomers Service Center | E61: 777 Stockton Street #104 | F61: San Francisco | G61: CA | H61: 94108 | I61: 415-421-2111 | J61: georgechan@chinesenewcomers.org | K61: Electronic | L61: Chinatown
A62: Tracy | B62: Everwine | C62: =A62&" "&B62 -> Tracy Everwine | D62: Civic Center Community Benefit District | E62: 234 Van Ness Avenue | F62: San Francisco | G62: CA | H62: 94102 | I62: 415-658-7979 | J62: info@sfciviccenter.org | K62: Physical | L62: Downtown/Civic Center
A63: James | B63: Haas | C63: =A63&" "&B63 -> James Haas | D63: Civic Center Stakeholder Group | E63: 100 Van Ness Avenue Apt 1906 | F63: San Francisco | G63: CA | H63: 94102 | I63: 415-285-5048 | J63: JWHaasESQ@AOL.com | K63: Electronic | L63: Downtown/Civic Center
A64: Cynthia | B64: Huie | C64: =A64&" "&B64 -> Cynthia Huie | D64: Clement Street Merchants Association | E64: 219 Clement St. | F64: San Francisco | G64: CA | H64: 94118 | I64: 415-751-7505 | J64: hello@clementstreetsf.com | K64: Electronic | L64: Outer Richmond
A65: Mary | B65: Miles | C65: =A65&" "&B65 -> Mary Miles | D65: Coalition for Adequate Review | E65: 364 Page Street, #36 | F65: San Francisco | G65: CA | H65: 94102 | K65: Physical | L65: Citywide
A66: George Wooding / | B66: Rose Hillson | C66: =A66&" "&B66 -> George Wooding / Rose Hillson | D66: Coalition for San Francisco Neighborhodos (CSFN) | E66: P.O. Box 156616 | F66: San Francisco | G66: CA | H66: 94115-6616 | I66: 415-695-1393 | J66: CSFNnotices@gmail.com | K66: Physical | L66: Citywide
A67: Jason | B67: Jungreis | C67: =A67&" "&B67 -> Jason Jungreis | D67: Coalition to Save Ocean Beach / Friends of Sutro Park | E67: 527 47th Avenue | F67: San Francisco | G67: CA | H67: 94121 | I67: 415-847-5133 | J67: jasonzjungreis@gmail.com | K67: Electronic | L67: Golden Gate Park, Outer Richmond, Seacliff
A68: Carole | B68: Glosenger | C68: =A68&" "&B68 -> Carole Glosenger | D68: Cole Valley Improvement Association | E68: P.O. Box 170611 | F68: San Francisco | G68: CA | H68: 94117 | I68: 415-431-1414 | J68: cviasf@aol.com | K68: Electronic | L68: Haight Ashbury
A69: Buddy | B69: Choy | C69: =A69&" "&B69 -> Buddy Choy | D69: Coleridge St. Neighbors | E69: 157 Coleridge Street | F69: San Francisco | G69: CA | H69: 94110 | I69: 415-282-2990 | J69: choytate@gmail.com | K69: Physical | L69: Bernal Heights, Mission, Noe Valley
A70: Chuck | B70: Turner | C70: =A70&" "&B70 -> Chuck Turner | D70: Community Design Center | E70: 5 Thomas Mellon Circle, #128 | F70: San Francisco | G70: CA | H70: 94134 | I70: 415-586-1235 | J70: charles.turner@communitydesigncentersf.com | K70: Physical | L70: Citywide
C71: Chandra LaBorde | D71: Comptons Community Land Trust | E71: 80 Turk St | F71: San Franicsco | G71: CA | H71: 94102 | I71: 510-960-9712 | J71: admin@turkxtaylor.net | K71: Both | L71: Downtown / Civic Center
C72: Judi Gorski | D72: Concerned Residents of the Sunset | E72: 2366 48th Avenue | F72: San Francisco | G72: CA | H72: 94116 | I72: 415-716-3004 | J72: judigorski@gmail.com | K72: Electronic | L72: Outer Sunset
A73: William | B73: Holtzman | C73: Maryann Dresner | D73: Corbett Heights Neighbors | E73: P.O. Box 14493 | F73: San Francisco | G73: CA | H73: 94114 | I73: 415-404-9960 | J73: info@corbettneighbors.com | K73: Electronic | L73: Castro/Upper Market, Noe Valley, West of Twin Peaks
A74: Barbara | B74: Heffernan | C74: =A74&" "&B74 -> Barbara Heffernan | D74: Cow Hollow Association | E74: 2423 Green Street | F74: San Francisco | G74: CA | H74: 94123 | J74: bjhassoc@comcast.net | K74: Physical | L74: Marina, Pacific Heights
A75: Anne | B75: Bertrand | C75: =A75&" "&B75 -> Anne Bertrand | D75: Cow Hollow Association | E75: 1592 Union Street #500 | F75: San Francisco | G75: CA | H75: 94123 | J75: bossbien@aol.com | K75: Physical | L75: Marina, Pacific Heights
A76: Brooke | B76: Sampson | C76: =A76&" "&B76 -> Brooke Sampson | D76: Cow Hollow Association | J76: brookesampson@yahoo.com | K76: Electronic | L76: Marina, Pacific Heights
A77: Rick | B77: Hall | C77: =A77&" "&B77 -> Rick Hall | D77: Cultural Action Network | E77: 2940 16th Street, #200-1 | F77: San Francisco | G77: CA | H77: 94103 | I77: 415-967-0795 | J77: rclistad@gmail.com | K77: Physical | L77: Mission
A78: Jeffrey | B78: Rigo | C78: Erica Zweig | D78: D4ward | E78: 3832 Judah St | F78: San Francisco | G78: CA | H78: 94122 | J78: D4ward.info@gmail.com | K78: Electronic | L78: Outer Sunset
A79: Betsy | B79: Eddy | C79: Daniel Schereck | D79: Diamond Heights Community Association | E79: P.O. Box 31529 | F79: San Francisco | G79: CA | H79: 94131 | I79: 415-867-5774 | J79: dhcasf@gmail.com | K79: Electronic | L79: Diamond Heights, Glen Park, Noe Valley
A80: Carey | B80: Rutigliano | C80: =A80&" "&B80 -> Carey Rutigliano | D80: Diamond Heights Homeowners Association (DHHOA) | E80: 108 Everson Street | F80: San Francisco | G80: CA | H80: 94131 | I80: 415-250-9410 | J80: careyruttig@yahoo.com | K80: Electronic | L80: Diamond Heights, Glen Park
A81: Judd | B81: Winick | C81: =A81&" "&B81 -> Judd Winick | D81: Diamond Street Neighborhood Association (DSNA) | E81: 1615 Diamond Street | F81: San Francisco | G81: CA | H81: 94131 | I81: 415-648-4704 | J81: chakabutt@yahoo.com | K81: Physical | L81: Noe Valley
A82: Duncan | B82: Ley | C82: =A82&" "&B82 -> Duncan Ley | D82: Discover Polk Community Benefit District | E82: P.O. Box 642097 | F82: San Francisco | G82: CA | H82: 94164 | I82: 415-481-2845 | J82: duncan@discoverpolk.org ben@discoverpolk.org | K82: Electronic | L82: Nob Hill, Russian Hill
C83: Donovan Lacy | D83: Dogpatch & NW Potrero Hill Green Benefit District | E83: 1459 18th Street #369 | F83: San Francisco | G83: CA | H83: 94107 | I83: - | J83: info@greenbenefit.org; donovan@greenbenefit.org | K83: Electronic | L83: Mission, Potrero Hill
A84: Joel D. | B84: Bean | C84: Michael Berkowitz | D84: Dogpatch Neighborhood Association | E84: 1278 Minnesota Street | F84: San Francisco | G84: CA | H84: 94107 | I84: 917-660-0449 | J84: info@dogpatchna.org; president@dogpatchna.org | K84: Electronic | L84: Bayview, Mission, Potrero Hill, South of Market
C85: Donovan Lacy | D85: Dogpatch Neighborhood Association | E85: 1278 Minnesota Street | F85: San Francisco | G85: CA | H85: 94107 | I85: 206-910-9503 | J85: vp@dogpatchna.org | K85: Electronic | L85: Bayview, Mission, Potrero Hill, South of Market
A86: Planning and Land Use Committee | C86: =A86&" "&B86 -> Planning and Land Use Committee | D86: Dolores Heights Improvement Club-DRC | E86: 4016 20th Street | F86: San Francisco | G86: CA | H86: 94114 | J86: plu@doloresheights.org | K86: Electronic | L86: Castro/Upper Market, Mission, Noe Valley
A87: Kevin | B87: Riley | C87: =A87&" "&B87 -> Kevin Riley | D87: Duboce Triangle Neighborhood Association | E87: 2261 Market Street PMB #301 | F87: San Francisco | G87: CA | H87: 94114 | I87: 415-295-1530 | J87: landuse@dtna.org | K87: Electronic | L87: Castro/Upper Market, Western Addition
A88: Judith | B88: Berkowitz | C88: =A88&" "&B88 -> Judith Berkowitz | D88: East Mission Improvement Association (EMIA) | E88: 2940 16th Street Room 200-1 (second floor) | F88: San Francisco | G88: CA | H88: 94103 | J88: zrants@gmail.com | K88: Electronic | L88: Mission
A89: Earl | B89: Shaddix | C89: =A89&" "&B89 -> Earl Shaddix | D89: Economic Development on Third (EDoT) | E89: 4800 Third Street #404 | F89: San Francisco | G89: CA | H89: 94124 | I89: 415-756-3678 | J89: earl@edotbayview.com | K89: Electronic | L89: Bayview
A90: Alice | B90: Aronow | C90: =A90&" "&B90 -> Alice Aronow | D90: Edgehill Way Association | E90: 100 Edgehill Way | F90: San Francisco | G90: CA | H90: 94127 | I90: 415-242-1454 | J90: alicearonow@gmail.com | K90: Electronic | L90: West of Twin Peaks
A91: Sarah | B91: Jones | C91: =A91&" "&B91 -> Sarah Jones | D91: Edgewood Neighborhood Association | E91: 190 Edgewood Ave | F91: San Francisco | G91: CA | H91: 94117 | I91: (415) 504-7233 | J91: sarahsmithjones@gmail.com | K91: Physical | L91: Inner Sunset
A92: Sue | B92: Mortensen | C92: =A92&" "&B92 -> Sue Mortensen | D92: Esprit Owners Association | E92: 900 Minnesota Street | F92: San Francisco | G92: CA | H92: 94107 | I92: 916-316-3555 | J92: smortens@earthlink.net | K92: Physical | L92: Potrero Hill
A93: Priscilla | B93: Botsford | C93: =A93&" "&B93 -> Priscilla Botsford | D93: Eureka Heights Neighborhood Association | E93: 382 Eureka Street | F93: San Francisco | G93: CA | H93: 94114 | I93: 415-643-4414 | J93: prbotsford@yahoo.com | K93: Physical | L93: Castro/Upper Market
A94: Alex | B94: Lemberg | C94: Jennifer Waggoner | D94: Eureka Valley Neighborhood Association | E94: P.O. Box 14137 | F94: San Francisco | G94: CA | H94: 94114-2827 | J94: president@evna.org | K94: Electronic | L94: Castro/Upper Market
A95: Bruce | B95: Murphy | C95: =A95&" "&B95 -> Bruce Murphy | D95: Eureka Valley Trails/Art Network | E95: 1281 Quesada Ave | F95: San Francisco | G95: CA | H95: 94124-3334 | I95: 415-863-0207 | J95: luckylaowai.sf@gmail.com | K95: Physical | L95: Bayview, Castro/Upper Market
A96: Jack | B96: Keating | C96: =A96&" "&B96 -> Jack Keating | D96: Eureka/17th Street Neighbors | E96: 4134 17th Street | F96: San Francisco | G96: CA | H96: 94114 | I96: 415-431-4551 | J96: jteamj@comcast.net | K96: Physical | L96: Castro/Upper Market
A97: Maribel | B97: Ramirez | C97: =A97&" "&B97 -> Maribel Ramirez | D97: Excelsior Action Group | E97: 35 San Juan Ave | F97: San Francisco | G97: CA | H97: 94112 | I97: 415-585-0110 | J97: maribel@eagsf.org | K97: Electronic | L97: Excelsior
A98: Mel | B98: Flores | C98: =A98&" "&B98 -> Mel Flores | D98: Excelsior District Improvement Association | E98: P.O. Box 12005 | F98: San Francisco | G98: CA | H98: 94112 | I98: 415-760-5151 | J98: melfloressf@gmail.com | K98: Physical | L98: Crocker Amazon, Excelsior, Ocean View, Outer Mission
A99: Jonathan | B99: G | C99: =A99&" "&B99 -> Jonathan G | D99: EqualitySF | E99: P.O. Box 24297 | F99: San Francisco | G99: CA | H99: 94124 | K99: Physical | L99: Bayview
C100: Latoya Pitcher | D100: Family Equity Partners | E100: 2111 Lane Street #24196 | F100: San Francisco | G100: CA | H100: 94124 | I100: 415.499.2705 | J100: lpitcher@familyequitypartnerssf.org | K100: Electronic | L100: Bayview
...

Sheet Citywide
A1: ORGANIZATION | B1: ='Complete List_09252026'!C1 -> NAME | C1: ='Complete List_09252026'!E1 -> ADDRESS | D1: ='Complete List_09252026'!F1 -> CITY | E1: ='Complete List_09252026'!G1 -> STATE | F1: ='Complete List_09252026'!H1 -> ZIP | G1: ='Complete List_09252026'!J1 -> EMAIL | H1: NOTIFICATION PREFERENCES | I1: ='Complete List_09252026'!L1 -> NEIGHBORHOOD OF INTEREST
A2: PHYSICAL NOTICES
A3: AT&T | B3: ='Complete List_09252026'!C19 -> Construction and Engineering | C3: ='Complete List_09252026'!E19 -> 359 Washington Street, Room 205 | D3: ='Complete List_09252026'!F19 -> Daly City | E3: ='Complete List_09252026'!G19 -> CA | F3: ='Complete List_09252026'!H19 -> 94015 | G3: ='Complete List_09252026'!J19 -> 0 | H3: ='Complete List_09252026'!K19 -> Physical | I3: ='Complete List_09252026'!L19 -> Citywide
A4: Community Design Center | B4: ='Complete List_09252026'!C70 -> Chuck Turner | C4: ='Complete List_09252026'!E70 -> 5 Thomas Mellon Circle, #128 | D4: ='Complete List_09252026'!F70 -> San Francisco | E4: ='Complete List_09252026'!G70 -> CA | F4: ='Complete List_09252026'!H70 -> 94134 | G4: ='Complete List_09252026'!J70 -> charles.turner@communitydesigncentersf.com | H4: ='Complete List_09252026'!K70 -> Physical | I4: ='Complete List_09252026'!L70 -> Citywide
A5: SF Building and Construction Trades Council | B5: ='Complete List_09252026'!C250 -> Tim Paulson Rudy Gonzalez | C5: ='Complete List_09252026'!E250 -> 1188 Franklin Street, Ste.203 | D5: ='Complete List_09252026'!F250 -> San Francisco | E5: ='Complete List_09252026'!G250 -> CA | F5: ='Complete List_09252026'!H250 -> 94109 | G5: ='Complete List_09252026'!J250 -> tim@sfbuildingtradescouncil.org rudy@sfbuildingtradescouncil.org | H5: ='Complete List_09252026'!K250 -> Physical | I5: ='Complete List_09252026'!L250 -> Citywide
A6: - | B6: ='Complete List_09252026'!C2 -> Aaron Peskin | C6: ='Complete List_09252026'!E2 -> 470 Columbus Avenue, Ste. 211 | D6: ='Complete List_09252026'!F2 -> San Francisco | E6: ='Complete List_09252026'!G2 -> CA | F6: ='Complete List_09252026'!H2 -> 94133 | G6: ='Complete List_09252026'!J2 -> aaron.peskin@earthlink.net | H6: ='Complete List_09252026'!K2 -> Physical | I6: ='Complete List_09252026'!L2 -> Citywide
A7: Carpenters Local 22 | B7: ='Complete List_09252026'!C51 -> Leonard Basoco | C7: ='Complete List_09252026'!E51 -> 2085 Third Street | D7: ='Complete List_09252026'!F51 -> San Francisco | E7: ='Complete List_09252026'!G51 -> CA | F7: ='Complete List_09252026'!H51 -> 94107 | G7: ='Complete List_09252026'!J51 -> ASimi@nccrc.org | H7: ='Complete List_09252026'!K51 -> Physical | I7: ='Complete List_09252026'!L51 -> Citywide
A8: Coalition for Adequate Review | B8: ='Complete List_09252026'!C65 -> Mary Miles | C8: ='Complete List_09252026'!E65 -> 364 Page Street, #36 | D8: ='Complete List_09252026'!F65 -> San Francisco | E8: ='Complete List_09252026'!G65 -> CA | F8: ='Complete List_09252026'!H65 -> 94102 | G8: ='Complete List_09252026'!J65 -> 0 | H8: ='Complete List_09252026'!K65 -> Physical | I8: ='Complete List_09252026'!L65 -> Citywide
A9: Coalition for San Francisco Neighborhodos (CSFN) | B9: ='Complete List_09252026'!C66 -> George Wooding / Rose Hillson | C9: ='Complete List_09252026'!E66 -> P.O. Box 156616 | D9: ='Complete List_09252026'!F66 -> San Francisco | E9: ='Complete List_09252026'!G66 -> CA | F9: ='Complete List_09252026'!H66 -> 94115-6616 | G9: ='Complete List_09252026'!J66 -> CSFNnotices@gmail.com | H9: ='Complete List_09252026'!K66 -> Physical | I9: ='Complete List_09252026'!L66 -> Citywide
A10: Law Office of Stephen M. Williams | B10: ='Complete List_09252026'!C152 -> Stephen Williams | C10: ='Complete List_09252026'!E152 -> 1934 Divisadero Street | D10: ='Complete List_09252026'!F152 -> San Francisco | E10: ='Complete List_09252026'!G152 -> CA | F10: ='Complete List_09252026'!H152 -> 94115 | G10: ='Complete List_09252026'!J152 -> SMW@stevewilliamslaw.com | H10: ='Complete List_09252026'!K152 -> Physical | I10: ='Complete List_09252026'!L152 -> Citywide
A11: BOTH PHYSICAL & ELECTRONIC NOTICES
A12: Lozeau Drury LLP | B12: Maya Vishwanath | C12: 1939 Harrison Street, Suite 150 | D12: Oakland | E12: CA | F12: 94612 | G12: michael@lozeaudrury.com hannah@lozeaudrury.com maya@lozeaudrury.com | H12: Both | I12: Citywide
A13: ELECTRONIC NOTICES
A14: San Francisco Tenants Union | B14: ='Complete List_09252026'!C243 -> Layla Stanley | C14: ='Complete List_09252026'!E243 -> 558 Capp Street | D14: ='Complete List_09252026'!F243 -> San Francisco | E14: ='Complete List_09252026'!G243 -> CA | F14: ='Complete List_09252026'!H243 -> 94110 | G14: ='Complete List_09252026'!J243 -> sfplanningnotice@SFTU.org | H14: ='Complete List_09252026'!K243 -> Electronic | I14: ='Complete List_09252026'!L243 -> Citywide
A15: San Francisco Electrical Construction Industry (SFECI) | B15: ='Complete List_09252026'!C254 -> Alex Lantsberg | C15: ='Complete List_09252026'!E254 -> 55 Fillmore Street | D15: ='Complete List_09252026'!F254 -> San Francisco | E15: ='Complete List_09252026'!G254 -> CA | F15: ='Complete List_09252026'!H254 -> 94117 | G15: ='Complete List_09252026'!J254 -> alex@sfeci.org | H15: ='Complete List_09252026'!K254 -> Electronic | I15: ='Complete List_09252026'!L254 -> Citywide
A16: Sheet Metal Workers Local Union No. 104 | B16: ='Complete List_09252026'!C260 -> Danny Campbell | C16: ='Complete List_09252026'!E260 -> 1939 Market Street, Suite A | D16: ='Complete List_09252026'!F260 -> San Francisco | E16: ='Complete List_09252026'!G260 -> CA | F16: ='Complete List_09252026'!H260 -> 94103 | G16: ='Complete List_09252026'!J260 -> dannyc@smw104.org | H16: ='Complete List_09252026'!K260 -> Electronic | I16: ='Complete List_09252026'!L260 -> Citywide
A17: SOMA Neighborhood Association | B17: ='Complete List_09252026'!C265 -> John Valdez | C17: ='Complete List_09252026'!E265 -> 2 Townsend Street, 3-105 | D17: ='Complete List_09252026'!F265 -> San Francisco | E17: ='Complete List_09252026'!G265 -> CA | F17: ='Complete List_09252026'!H265 -> 94107 | G17: ='Complete List_09252026'!J265 -> sfloans@sbcglobal.net | H17: ='Complete List_09252026'!K265 -> Electronic | I17: ='Complete List_09252026'!L265 -> Citywide
A18: ='Complete List_09252026'!D256 -> San Francisco SAFE, Inc. | B18: ='Complete List_09252026'!C256 -> Kyra Worthy | C18: ='Complete List_09252026'!E256 -> 850 Bryant Street, Room 135 | D18: ='Complete List_09252026'!F256 -> San Francisco | E18: ='Complete List_09252026'!G256 -> CA | F18: ='Complete List_09252026'!H256 -> 94103 | G18: ='Complete List_09252026'!J256 -> info@sfsafe.org | H18: ='Complete List_09252026'!K256 -> Electronic | I18: ='Complete List_09252026'!L256 -> Citywide
A19: ='Complete List_09252026'!D182 -> Mission Awareness Project | B19: ='Complete List_09252026'!C182 -> Morgan Noble | C19: ='Complete List_09252026'!E182 -> 1198 S. Van Ness Ave #104 | D19: ='Complete List_09252026'!F182 -> San Francisco | E19: ='Complete List_09252026'!G182 -> CA | F19: ='Complete List_09252026'!H182 -> 94110 | G19: ='Complete List_09252026'!J182 -> info@missionawarenessproject.com | H19: ='Complete List_09252026'!K182 -> Electronic | I19: ='Complete List_09252026'!L182 -> Citywide

Sheet Bayview
A1: ORGANIZATION | B1: ='Complete List_09252026'!C1 -> NAME | C1: ='Complete List_09252026'!E1 -> ADDRESS | D1: ='Complete List_09252026'!F1 -> CITY | E1: ='Complete List_09252026'!G1 -> STATE | F1: ='Complete List_09252026'!H1 -> ZIP | G1: ='Complete List_09252026'!J1 -> EMAIL | H1: NOTIFICATION PREFERENCES | I1: ='Complete List_09252026'!L1 -> NEIGHBORHOOD OF INTEREST
A2: PHYSICAL NOTICES
A3: Anna Waden Library | B3: ='Complete List_09252026'!C16 -> Linda Burton | C3: ='Complete List_09252026'!E16 -> 5075 3rd Street | D3: ='Complete List_09252026'!F16 -> San Francisco | E3: ='Complete List_09252026'!G16 -> CA | F3: ='Complete List_09252026'!H16 -> 94124 | G3: ='Complete List_09252026'!J16 -> 0 | H3: ='Complete List_09252026'!K16 -> Physical | I3: ='Complete List_09252026'!L95 -> Bayview, Castro/Upper Market
A4: EqualitySF | C4: ='Complete List_09252026'!E99 -> P.O. Box 24297 | D4: ='Complete List_09252026'!F99 -> San Francisco | E4: ='Complete List_09252026'!G99 -> CA | F4: ='Complete List_09252026'!H99 -> 94124 | G4: ='Complete List_09252026'!J99 -> 0 | H4: ='Complete List_09252026'!K99 -> Physical | I4: ='Complete List_09252026'!L99 -> Bayview
A5: Samoan Development Centre | B5: ='Complete List_09252026'!C242 -> Patsy Tito | C5: ='Complete List_09252026'!E242 -> 2055 Sunnydale Avenue #100 | D5: ='Complete List_09252026'!F242 -> San Francisco | E5: ='Complete List_09252026'!G242 -> CA | F5: ='Complete List_09252026'!H242 -> 94134-2611 | G5: ='Complete List_09252026'!J242 -> 0 | H5: ='Complete List_09252026'!K242 -> Physical | I5: ='Complete List_09252026'!L25 -> Bayview
A6: Sherwin Williams | B6: ='Complete List_09252026'!C261 -> Francesca Panullo | C6: ='Complete List_09252026'!E261 -> 1415 Ocean Ave | D6: ='Complete List_09252026'!F261 -> San Francisco | E6: ='Complete List_09252026'!G261 -> CA | F6: ='Complete List_09252026'!H261 -> 94112 | G6: ='Complete List_09252026'!J261 -> sw8644@sherwin.com | H6: ='Complete List_09252026'!K261 -> Physical | I6: ='Complete List_09252026'!L248 -> Bayview, Potrero Hill, Visitacion Valley
A7: Southeast Community Facility | B7: ='Complete List_09252026'!C272 -> Larry Berry | C7: ='Complete List_09252026'!E272 -> 1800 Oakdale Avenue | D7: ='Complete List_09252026'!F272 -> San Francisco | E7: ='Complete List_09252026'!G272 -> CA | F7: ='Complete List_09252026'!H272 -> 94124 | G7: ='Complete List_09252026'!J272 -> 0 | H7: ='Complete List_09252026'!K272 -> Physical | I7: ='Complete List_09252026'!L258 -> Bayview
A8: St. Paul of the Shipwreck Church | B8: ='Complete List_09252026'!C276 -> Paul Gawlowski | C8: ='Complete List_09252026'!E276 -> 1122 Jamestown Aveue | D8: ='Complete List_09252026'!F276 -> San Francisco | E8: ='Complete List_09252026'!G276 -> CA | F8: ='Complete List_09252026'!H276 -> 94124 | G8: ='Complete List_09252026'!J276 -> spswoffice@aol.com | H8: ='Complete List_09252026'!K276 -> Physical | I8: ='Complete List_09252026'!L133 -> Bayview
A9: - | B9: ='Complete List_09252026'!C7 -> Russel Morine | C9: ='Complete List_09252026'!E7 -> 64 Gillette Avenue | D9: ='Complete List_09252026'!F7 -> San Francisco | E9: ='Complete List_09252026'!G7 -> CA | F9: ='Complete List_09252026'!H7 -> 94134 | G9: ='Complete List_09252026'!J7 -> rmorine@aol.com | H9: ='Complete List_09252026'!K7 -> Physical | I9: ='Complete List_09252026'!L242 -> Bayview, South of Market
A10: Eureka Valley Trails/Art Network | B10: ='Complete List_09252026'!C95 -> Bruce Murphy | C10: ='Complete List_09252026'!E95 -> 1281 Quesada Ave | D10: ='Complete List_09252026'!F95 -> San Francisco | E10: ='Complete List_09252026'!G95 -> CA | F10: ='Complete List_09252026'!H95 -> 94124-3334 | G10: ='Complete List_09252026'!J95 -> luckylaowai.sf@gmail.com | H10: ='Complete List_09252026'!K95 -> Physical | I10: ='Complete List_09252026'!L276 -> Bayview
A11: Portola Place Homeowners Association | B11: ='Complete List_09252026'!C231 -> David Gilliam | C11: ='Complete List_09252026'!E231 -> P.O. Box 24181 | D11: ='Complete List_09252026'!F231 -> San Francisco | E11: ='Complete List_09252026'!G231 -> CA | F11: ='Complete List_09252026'!H231 -> 94124-0181 | G11: ='Complete List_09252026'!J231 -> dgumpire@aol.com | H11: ='Complete List_09252026'!K231 -> Physical | I11: ='Complete List_09252026'!L272 -> Bayview
A12: Shafter Avenue Community Club | B12: ='Complete List_09252026'!C258 -> Maverick Madison | C12: ='Complete List_09252026'!E258 -> 1629 Shafter Avenue | D12: ='Complete List_09252026'!F258 -> San Francisco | E12: ='Complete List_09252026'!G258 -> CA | F12: ='Complete List_09252026'!H258 -> 94124 | G12: ='Complete List_09252026'!J258 -> misterfingers04@yahoo.com | H12: ='Complete List_09252026'!K258 -> Physical | I12: ='Complete List_09252026'!L99 -> Bayview
A13: BOTH PHYSICAL & ELECTRONIC NOTICES
A14: Board of Supervisors | B14: ='Complete List_09252026'!C34 -> Shamann Walton | C14: ='Complete List_09252026'!E34 -> 1 Dr. Carlton B Goodlett Place, Room #244 | D14: ='Complete List_09252026'!F34 -> San Francisco | E14: ='Complete List_09252026'!G34 -> CA | F14: ='Complete List_09252026'!H34 -> 94102-4689 | G14: ='Complete List_09252026'!J34 -> waltonstaff@sfgov.org; Percy.Burch@sfgov.org; Tracy.Gallardo@sfgov.org; Natalie.Gee@sfgov.org | H14: ='Complete List_09252026'!K34 -> Both | I14: ='Complete List_09252026'!L34 -> Bayview, Potrero Hill, Visitacion Valley
A15: India Basin Neighborhood Association | B15: ='Complete List_09252026'!C133 -> Michael Hamman | C15: ='Complete List_09252026'!E133 -> 702 Earl Street | D15: ='Complete List_09252026'!F133 -> San Francisco | E15: ='Complete List_09252026'!G133 -> CA | F15: ='Complete List_09252026'!H133 -> 94124 | G15: ='Complete List_09252026'!J133 -> mhamman@igc.org; info@indiabasin.org | H15: ='Complete List_09252026'!K133 -> Both | I15: ='Complete List_09252026'!L133 -> Bayview
A16: ELECTRONIC NOTICES
A17: BayView Community Planning | B17: ='Complete List_09252026'!C24 -> Daniel Dodt | C17: ='Complete List_09252026'!E24 -> 2027 Oakdale Avenue | D17: ='Complete List_09252026'!F24 -> San Francisco | E17: ='Complete List_09252026'!G24 -> CA | F17: ='Complete List_09252026'!H24 -> 94124 | G17: ='Complete List_09252026'!J24 -> bvhpwatch@mac.com | H17: ='Complete List_09252026'!K24 -> Electronic | I17: ='Complete List_09252026'!L261 -> Bayview, Bernal Heights, Crocker Amazon, Diamond Heights, Excelsior, Glen Park, Inner Sunset, Lakeshore, Noe Valley, Ocean View, Outer Mission, Outer Sunset, Parkside, Potrero Hill, South Bayshore, Twin Peaks, Visitacion Valley, West of Twin Peaks
A18: Bayview Hunters Point Citizens Advisory Committee | C18: ='Complete List_09252026'!E26 -> 1550 Evans Avenue | D18: ='Complete List_09252026'!F26 -> San Francisco | E18: ='Complete List_09252026'!G26 -> CA | F18: ='Complete List_09252026'!H26 -> 94124 | G18: ='Complete List_09252026'!J26 -> bayviewcac@sfgov.org | H18: ='Complete List_09252026'!K26 -> Electronic | I18: ='Complete List_09252026'!L26 -> Bayview
A19: Economic Development on Third (EDoT) | B19: ='Complete List_09252026'!C89 -> Earl Shaddix | C19: ='Complete List_09252026'!E89 -> 4800 Third Street #404 | D19: ='Complete List_09252026'!F89 -> San Francisco | E19: ='Complete List_09252026'!G89 -> CA | F19: ='Complete List_09252026'!H89 -> 94124 | G19: ='Complete List_09252026'!J89 -> earl@edotbayview.com | H19: ='Complete List_09252026'!K89 -> Electronic | I19: ='Complete List_09252026'!L89 -> Bayview
A20: Greenaction for Health and Environmental Justice | B20: ='Complete List_09252026'!C119 -> Bradley Angel | C20: ='Complete List_09252026'!E119 -> 315 Sutter Street, 2nd Floor | D20: ='Complete List_09252026'!F119 -> San Francisco | E20: ='Complete List_09252026'!G119 -> CA | F20: ='Complete List_09252026'!H119 -> 94108 | G20: ='Complete List_09252026'!J119 -> greenaction@greenaction.org | H20: ='Complete List_09252026'!K119 -> Electronic | I20: ='Complete List_09252026'!#REF! -> #REF!
A21: SF Bay View Newspaper | B21: ='Complete List_09252026'!C248 -> Nube Brown | C21: ='Complete List_09252026'!E248 -> 4917 Third Street | D21: ='Complete List_09252026'!F248 -> San Francisco | E21: ='Complete List_09252026'!G248 -> CA | F21: ='Complete List_09252026'!H248 -> 94124 | G21: ='Complete List_09252026'!J248 -> editor@sfbayview.com | H21: ='Complete List_09252026'!K248 -> Electronic | I21: ='Complete List_09252026'!L26 -> Bayview
A22: Young Community Developers (YCD) | B22: ='Complete List_09252026'!C317 -> Zachary Weisenburger | C22: ='Complete List_09252026'!E317 -> 1715 Yosemite Avenue | D22: ='Complete List_09252026'!F317 -> San Francisco | E22: ='Complete List_09252026'!G317 -> CA | F22: ='Complete List_09252026'!H317 -> 94124 | G22: ='Complete List_09252026'!J317 -> zweisenburger@ycdjobs.org | H22: ='Complete List_09252026'!K317 -> Electronic | I22: ='Complete List_09252026'!L217 -> Bayview, Crocker Amazon, Excelsior, Ocean View, Potrero Hill, Visitacion Valley
A23: Bayview Hill Neighborhood Association | B23: ='Complete List_09252026'!C25 -> Board Secretary | C23: ='Complete List_09252026'!E25 -> 0 | D23: ='Complete List_09252026'!F25 -> 0 | E23: ='Complete List_09252026'!G25 -> 0 | F23: ='Complete List_09252026'!H25 -> 0 | G23: ='Complete List_09252026'!J25 -> bvhna.secretary@gmail.com bayviewhillsf@gmail.com | H23: ='Complete List_09252026'!K25 -> Electronic | I23: ='Complete List_09252026'!L7 -> Bayview
A24: ='Complete List_09252026'!D45 -> Both Sides of the Conversation | B24: ='Complete List_09252026'!C45 -> Jon Henry | C24: ='Complete List_09252026'!E45 -> P.O. Box 347518 | D24: ='Complete List_09252026'!F45 -> San Francisco | E24: ='Complete List_09252026'!G45 -> CA | F24: ='Complete List_09252026'!H45 -> 94134 | G24: ='Complete List_09252026'!J45 -> jonhenry@bsotc.org | H24: ='Complete List_09252026'!K45 -> Electronic | I24: ='Complete List_09252026'!L45 -> Bayview, Bernal Heights, Crocker Amazon, Downtown/Civic Center, Excelsior, Glen Park, Haight Ashbury, Potrero Hill, South of Market, Treasure Island, Visitacion Valley, West of Twin Peaks, Western Addition
A25: ='Complete List_09252026'!D154 -> Liberation Alliance for Economic and Social Change | B25: ='Complete List_09252026'!C154 -> Keith Pavlik | C25: ='Complete List_09252026'!E154 -> 2969 Mission Street | D25: ='Complete List_09252026'!F154 -> San Francisco | E25: ='Complete List_09252026'!G154 -> CA | F25: ='Complete List_09252026'!H154 -> 94110 | G25: ='Complete List_09252026'!J154 -> info@liberationalliance.org | H25: ='Complete List_09252026'!K154 -> Electronic | I25: ='Complete List_09252026'!L154 -> Bayview, Bernal Heights, Castro/Upper Market, Chinatown, Downtown/Civic Center, Excelsior, Mission, Nob Hill, Noe Valley, Outer Mission, Potrero Hill, South of Market, Western Addition
A26: ='Complete List_09252026'!D249 -> SF Black Wallstreet | B26: ='Complete List_09252026'!C249 -> Tiffany Carter | C26: ='Complete List_09252026'!E249 -> 744 Innes Avenue | D26: ='Complete List_09252026'!F249 -> San Francisco | E26: ='Complete List_09252026'!G249 -> CA | F26: ='Complete List_09252026'!H249 -> 94124 | G26: ='Complete List_09252026'!J249 -> tiffanysfblackwallstreet@gmail.com | H26: ='Complete List_09252026'!K249 -> Electronic | I26: ='Complete List_09252026'!L249 -> Bayview
A27: ='Complete List_09252026'!D235 -> Rafiki Coalition for Health and Wellness | B27: ='Complete List_09252026'!C235 -> Dr. Monique LeSarre | C27: ='Complete List_09252026'!E235 -> 601 Cesar Chavez Street | D27: ='Complete List_09252026'!F235 -> San Francisco | E27: ='Complete List_09252026'!G235 -> CA | F27: ='Complete List_09252026'!H235 -> 94124 | G27: ='Complete List_09252026'!J235 -> devopmentdirector@rafikicoalition.org | H27: ='Complete List_09252026'!K235 -> Electronic | I27: ='Complete List_09252026'!L235 -> Bayview
A28: ='Complete List_09252026'!D277 -> Stand in Peace International | B28: ='Complete List_09252026'!C277 -> Shervon Hunter | C28: ='Complete List_09252026'!E277 -> 45 Tioga Avenue | D28: ='Complete List_09252026'!F277 -> San Francisco | E28: ='Complete List_09252026'!G277 -> CA | F28: ='Complete List_09252026'!H277 -> 94134 | G28: ='Complete List_09252026'!J277 -> standinpeacecommunityprograms@gmail.com | H28: ='Complete List_09252026'!K277 -> Electronic | I28: ='Complete List_09252026'!L277 -> Bayview, Potrero Hill, Visitacion Valley
A29: ='Complete List_09252026'!D100 -> Family Equity Partners | B29: ='Complete List_09252026'!C100 -> Latoya Pitcher | C29: ='Complete List_09252026'!E100 -> 2111 Lane Street #24196 | D29: ='Complete List_09252026'!F100 -> San Francisco | E29: ='Complete List_09252026'!G100 -> CA | F29: ='Complete List_09252026'!H100 -> 94124 | G29: ='Complete List_09252026'!J100 -> lpitcher@familyequitypartnerssf.org | H29: ='Complete List_09252026'!K100 -> Electronic | I29: ='Complete List_09252026'!L100 -> Bayview
A30: OneBayview | B30: ='Complete List_09252026'!C217 -> Anietie Ekanem | C30: ='Complete List_09252026'!E217 -> 5800 3rd Street #1320 | D30: ='Complete List_09252026'!F217 -> San Francisco | E30: ='Complete List_09252026'!G217 -> CA | F30: ='Complete List_09252026'!H217 -> 94124 | G30: ='Complete List_09252026'!J217 -> sfplanningdepartment@onebayview.com aekanem@onebayview.com | H30: ='Complete List_09252026'!K217 -> Electronic | I30: ='Complete List_09252026'!L217 -> Bayview, Crocker Amazon, Excelsior, Ocean View, Potrero Hill, Visitacion Valley
A31: ='Complete List_09252026'!D84 -> Dogpatch Neighborhood Association | B31: ='Complete List_09252026'!C84 -> Michael Berkowitz | C31: ='Complete List_09252026'!E84 -> 1278 Minnesota Street | D31: ='Complete List_09252026'!F84 -> San Francisco | E31: ='Complete List_09252026'!G84 -> CA | F31: ='Complete List_09252026'!H84 -> 94107 | G31: ='Complete List_09252026'!J84 -> info@dogpatchna.org; president@dogpatchna.org | H31: ='Complete List_09252026'!K84 -> Electronic | I31: ='Complete List_09252026'!L84 -> Bayview, Mission, Potrero Hill, South of Market
A32: ='Complete List_09252026'!D85 -> Dogpatch Neighborhood Association | B32: ='Complete List_09252026'!C85 -> Donovan Lacy | C32: ='Complete List_09252026'!E85 -> 1278 Minnesota Street | D32: ='Complete List_09252026'!F85 -> San Francisco | E32: ='Complete List_09252026'!G85 -> CA | F32: ='Complete List_09252026'!H85 -> 94107 | G32: ='Complete List_09252026'!J85 -> vp@dogpatchna.org | H32: ='Complete List_09252026'!K85 -> Electronic | I32: ='Complete List_09252026'!L85 -> Bayview, Mission, Potrero Hill, South of Market
A33: ='Complete List_09252026'!D146 -> Keep Crocker Real | B33: ='Complete List_09252026'!C146 -> KC Real | C33: ='Complete List_09252026'!E146 -> 0 | D33: ='Complete List_09252026'!F146 -> San Francisco | E33: ='Complete List_09252026'!G146 -> CA | F33: ='Complete List_09252026'!H146 -> 94112 | G33: ='Complete List_09252026'!J146 -> hello@keepcrockerreal.com | H33: ='Complete List_09252026'!K146 -> Electronic | I33: ='Complete List_09252026'!L146 -> Bayview, Crocker Amazon, Excelsior, Glen Park, Outer Mission, Visitacion Valley

Sheet Bernal Heights
A1: ORGANIZATION | B1: ='Complete List_09252026'!C1 -> NAME | C1: ='Complete List_09252026'!E1 -> ADDRESS | D1: ='Complete List_09252026'!F1 -> CITY | E1: ='Complete List_09252026'!G1 -> STATE | F1: ='Complete List_09252026'!H1 -> ZIP | G1: ='Complete List_09252026'!J1 -> EMAIL | H1: NOTIFICATION PREFERENCES | I1: ='Complete List_09252026'!L1 -> NEIGHBORHOOD OF INTEREST
A2: PHYSICAL NOTICES
A3: Bernal Heights Housing Corporation | B3: ='Complete List_09252026'!C29 -> Rachel Ebora | C3: ='Complete List_09252026'!E29 -> 515 Cortland Avenue | D3: ='Complete List_09252026'!F29 -> San Francisco | E3: ='Complete List_09252026'!G29 -> CA | F3: ='Complete List_09252026'!H29 -> 94110 | G3: ='Complete List_09252026'!J29 -> 0 | H3: ='Complete List_09252026'!K29 -> Physical | I3: ='Complete List_09252026'!L29 -> Bernal Heights
A4: Coleridge St. Neighbors | B4: ='Complete List_09252026'!C69 -> Buddy Choy | C4: ='Complete List_09252026'!E69 -> 157 Coleridge Street | D4: ='Complete List_09252026'!F69 -> San Francisco | E4: ='Complete List_09252026'!G69 -> CA | F4: ='Complete List_09252026'!H69 -> 94110 | G4: ='Complete List_09252026'!J69 -> choytate@gmail.com | H4: ='Complete List_09252026'!K69 -> Physical | I4: ='Complete List_09252026'!L69 -> Bernal Heights, Mission, Noe Valley
A5: Florida Slope Association | B5: ='Complete List_09252026'!C103 -> Saskia Verbeck | C5: ='Complete List_09252026'!E103 -> 631 Florida Street | D5: ='Complete List_09252026'!F103 -> San Francisco | E5: ='Complete List_09252026'!G103 -> CA | F5: ='Complete List_09252026'!H103 -> 94110 | G5: ='Complete List_09252026'!J103 -> nohoo999@yahoo.com | H5: ='Complete List_09252026'!K103 -> Physical | I5: ='Complete List_09252026'!L103 -> Bernal Heights
A6: Hop Past Brew Pub | B6: ='Complete List_09252026'!C130 -> Aron Deorsey | C6: ='Complete List_09252026'!E130 -> 2887 Bryant St. | D6: ='Complete List_09252026'!F130 -> San Francisco | E6: ='Complete List_09252026'!G130 -> CA | F6: ='Complete List_09252026'!H130 -> 94110 | G6: ='Complete List_09252026'!J130 -> aron.deorsey@gmail.com | H6: ='Complete List_09252026'!K130 -> Physical | I6: ='Complete List_09252026'!L130 -> Bernal Heights, Outer Mission
A7: Sherwin Williams | B7: ='Complete List_09252026'!C261 -> Francesca Panullo | C7: ='Complete List_09252026'!E261 -> 1415 Ocean Ave | D7: ='Complete List_09252026'!F261 -> San Francisco | E7: ='Complete List_09252026'!G261 -> CA | F7: ='Complete List_09252026'!H261 -> 94112 | G7: ='Complete List_09252026'!J261 -> sw8644@sherwin.com | H7: ='Complete List_09252026'!K261 -> Physical | I7: ='Complete List_09252026'!L261 -> Bayview, Bernal Heights, Crocker Amazon, Diamond Heights, Excelsior, Glen Park, Inner Sunset, Lakeshore, Noe Valley, Ocean View, Outer Mission, Outer Sunset, Parkside, Potrero Hill, South Bayshore, Twin Peaks, Visitacion Valley, West of Twin Peaks
A8: Bernal Heights Preservation | B8: ='Complete List_09252026'!C31 -> Andre Rothblatt | C8: ='Complete List_09252026'!E31 -> 475 Nevada Street | D8: ='Complete List_09252026'!F31 -> San Francisco | E8: ='Complete List_09252026'!G31 -> CA | F8: ='Complete List_09252026'!H31 -> 94110 | G8: ='Complete List_09252026'!J31 -> arothblatt@aol.com | H8: ='Complete List_09252026'!K31 -> Physical | I8: ='Complete List_09252026'!L31 -> Bernal Heights
A9: San Franciscans for Reasonable Growth (SFRG) | B9: ='Complete List_09252026'!C244 -> Sue Hestor | C9: ='Complete List_09252026'!E244 -> 329 Highland Ave | D9: ='Complete List_09252026'!F244 -> San Francisco | E9: ='Complete List_09252026'!G244 -> CA | F9: ='Complete List_09252026'!H244 -> 94110 | G9: ='Complete List_09252026'!J244 -> hestor@earthlink.net | H9: Physical | I9: ='Complete List_09252026'!L244 -> Bernal Heights, Chinatown, Downtown/Civic Center, Mission
A10: BOTH PHYSICAL & ELECTRONIC NOTICES
A11: ='Complete List_09252026'!D44 -> Board of Supervisors | B11: ='Complete List_09252026'!C44 -> Jackie Fielder | C11: ='Complete List_09252026'!E44 -> 1 Dr. Carlton B Goodlett Place, Room #244 | D11: ='Complete List_09252026'!F44 -> San Francisco | E11: ='Complete List_09252026'!G44 -> CA | F11: ='Complete List_09252026'!H44 -> 94102-4689 | G11: ='Complete List_09252026'!J44 -> FielderStaff@sfgov.org; Ana.Herrera@sfgov.org; Preston.Kilgore@sfgov.org | H11: ='Complete List_09252026'!K44 -> Both | I11: ='Complete List_09252026'!L44 -> Bernal Heights, Excelsior, Mission, Visitacion Valley
A12: ELECTRONIC NOTICES
A13: Bernal Cut Neighborhood Alliace | B13: ='Complete List_09252026'!C27 -> Sophie Constantinou | C13: ='Complete List_09252026'!E27 -> 22 Richland Avenue | D13: ='Complete List_09252026'!F27 -> San Francisco | E13: ='Complete List_09252026'!G27 -> CA | F13: ='Complete List_09252026'!H27 -> 94110 | G13: ='Complete List_09252026'!J27 -> bernalcutpath@gmail.com | H13: ='Complete List_09252026'!K27 -> Electronic | I13: ='Complete List_09252026'!L27 -> Bernal Heights, Glen Park
A14: Bernal Heights East Slope Design Review Board | B14: ='Complete List_09252026'!C28 -> Wendy Cowles | C14: ='Complete List_09252026'!E28 -> 89 Banks Street | D14: ='Complete List_09252026'!F28 -> San Francisco | E14: ='Complete List_09252026'!G28 -> CA | F14: ='Complete List_09252026'!H28 -> 94110 | G14: ='Complete List_09252026'!J28 -> bhesdrb@gmail.com | H14: ='Complete List_09252026'!K28 -> Electronic | I14: ='Complete List_09252026'!L28 -> Bernal Heights
A15: Bernal Heights Neighborhood Center | B15: ='Complete List_09252026'!C30 -> Sulaiman Hyatt | C15: ='Complete List_09252026'!E30 -> 1591 Treat Avenue | D15: ='Complete List_09252026'!F30 -> San Francisco | E15: ='Complete List_09252026'!G30 -> CA | F15: ='Complete List_09252026'!H30 -> 94110 | G15: ='Complete List_09252026'!J30 -> shyatt@bhnc.org | H15: ='Complete List_09252026'!K30 -> Electronic | I15: ='Complete List_09252026'!L30 -> Bernal Heights
A16: Bernal Heights South Slope Organization | B16: ='Complete List_09252026'!C32 -> Kathy Angus | C16: ='Complete List_09252026'!E32 -> 99 Banks Street | D16: ='Complete List_09252026'!F32 -> San Francisco | E16: ='Complete List_09252026'!G32 -> CA | F16: ='Complete List_09252026'!H32 -> 94110 | G16: ='Complete List_09252026'!J32 -> kathyangus@gmail.com | H16: ='Complete List_09252026'!K32 -> Electronic | I16: ='Complete List_09252026'!L32 -> Bernal Heights
A17: Mission Local | B17: ='Complete List_09252026'!C186 -> Annika Hom | C17: ='Complete List_09252026'!E186 -> 2489 Mission Street #14 | D17: ='Complete List_09252026'!F186 -> San Francisco | E17: ='Complete List_09252026'!G186 -> CA | F17: ='Complete List_09252026'!H186 -> 94110 | G17: ='Complete List_09252026'!J186 -> joe.rivanobarros@missionlocal.com | H17: ='Complete List_09252026'!K186 -> Electronic | I17: ='Complete List_09252026'!L186 -> Bernal Heights, Mission
A18: Northwest Bernal Heights Design Review Board | B18: ='Complete List_09252026'!C211 | C18: ='Complete List_09252026'!E211 -> 32 Aztec Street | D18: ='Complete List_09252026'!F211 -> San Francisco | E18: ='Complete List_09252026'!G211 -> CA | F18: ='Complete List_09252026'!H211 -> 94110 | G18: ='Complete List_09252026'!J211 -> nwbhdrb@gmail.com | H18: ='Complete List_09252026'!K211 -> Electronic | I18: ='Complete List_09252026'!L211 -> Bernal Heights
A19: Both Sides of the Conversation | B19: Jon Henry | C19: P.O. Box 347518 | D19: San Francisco | E19: CA | F19: 94134 | G19: jonhenry@bsotc.org | H19: Electronic | I19: Bayview, Bernal Heights, Crocker Amazon, Downtown/Civic Center, Excelsior, Glen Park, Haight Ashbury, Potrero Hill, South of Market, Treasure Island, Visitacion Valley, West of Twin Peaks, Western Addition
A20: ='Complete List_09252026'!D53 -> Castro LGBTQ Cultural District | B20: ='Complete List_09252026'!C53 -> Jesse Sanford & Stephen Torres | C20: ='Complete List_09252026'!E53 -> 1800 Market Street | D20: ='Complete List_09252026'!F53 -> San Francisco | E20: ='Complete List_09252026'!G53 -> CA | F20: ='Complete List_09252026'!H53 -> 94102 | G20: ='Complete List_09252026'!J53 -> landuse@castrolgbtq.org | H20: ='Complete List_09252026'!K53 -> Electronic | I20: ='Complete List_09252026'!L53 -> Bernal Heights, Castro/Upper Market, Downtown/Civic Center, Mission, Noe Valley, South of Market
A21: ='Complete List_09252026'!D257 -> SFCOV | B21: ='Complete List_09252026'!C257 -> Chris Lee | C21: ='Complete List_09252026'!E257 -> P.O. Box 883392 | D21: ='Complete List_09252026'!F257 -> San Francisco | E21: ='Complete List_09252026'!G257 -> CA | F21: ='Complete List_09252026'!H257 -> 94188 | G21: ='Complete List_09252026'!J257 -> neighbor@sfcov.org | H21: ='Complete List_09252026'!K257 -> Electronic | I21: ='Complete List_09252026'!L257 -> Bernal Heights, Mission, Potrero Hill
A22: ='Complete List_09252026'!D154 -> Liberation Alliance for Economic and Social Change | B22: ='Complete List_09252026'!C154 -> Keith Pavlik | C22: ='Complete List_09252026'!E154 -> 2969 Mission Street | D22: ='Complete List_09252026'!F154 -> San Francisco | E22: ='Complete List_09252026'!G154 -> CA | F22: ='Complete List_09252026'!H154 -> 94110 | G22: ='Complete List_09252026'!J154 -> info@liberationalliance.org | H22: ='Complete List_09252026'!K154 -> Electronic | I22: ='Complete List_09252026'!L154 -> Bayview, Bernal Heights, Castro/Upper Market, Chinatown, Downtown/Civic Center, Excelsior, Mission, Nob Hill, Noe Valley, Outer Mission, Potrero Hill, South of Market, Western Addition

Sheet Castro Upper Market
A1: ORGANIZATION | B1: ='Complete List_09252026'!C1 -> NAME | C1: ='Complete List_09252026'!E1 -> ADDRESS | D1: ='Complete List_09252026'!F1 -> CITY | E1: ='Complete List_09252026'!G1 -> STATE | F1: ='Complete List_09252026'!H1 -> ZIP | G1: ='Complete List_09252026'!J1 -> EMAIL | H1: NOTIFICATION PREFERENCES | I1: ='Complete List_09252026'!L1 -> NEIGHBORHOOD OF INTEREST
A2: PHYSICAL NOTICES
A3: Castro Area Planning + Action | B3: ='Complete List_09252026'!C52 -> Joe Curtin | C3: ='Complete List_09252026'!E52 -> 584 Castro Street, Suite 169 | D3: ='Complete List_09252026'!F52 -> San Francisco | E3: ='Complete List_09252026'!G52 -> CA | F3: ='Complete List_09252026'!H52 -> 94114 | G3: ='Complete List_09252026'!J52 -> 0 | H3: ='Complete List_09252026'!K52 -> Physical | I3: ='Complete List_09252026'!L52 -> Castro/Upper Market
A4: Eureka Heights Neighborhood Association | B4: ='Complete List_09252026'!C93 -> Priscilla Botsford | C4: ='Complete List_09252026'!E93 -> 382 Eureka Street | D4: ='Complete List_09252026'!F93 -> San Francisco | E4: ='Complete List_09252026'!G93 -> CA | F4: ='Complete List_09252026'!H93 -> 94114 | G4: ='Complete List_09252026'!J93 -> prbotsford@yahoo.com | H4: ='Complete List_09252026'!K93 -> Physical | I4: ='Complete List_09252026'!L93 -> Castro/Upper Market
A5: Hotel Zeppelin | B5: ='Complete List_09252026'!C131 -> Antonio Flores | C5: ='Complete List_09252026'!E131 -> 545 Post Street | D5: ='Complete List_09252026'!F131 -> San Francisco | E5: ='Complete List_09252026'!G131 -> CA | F5: ='Complete List_09252026'!H131 -> 94102 | G5: ='Complete List_09252026'!J131 -> antonio.flores@viceroyhotelgroup.com | H5: ='Complete List_09252026'!K131 -> Physical | I5: ='Complete List_09252026'!L131 -> Castro/Upper Market, Chinatown, Downtown/Civic Center, Financial District, Nob Hill, North Beach, South of Market, Treasure Island
A6: Market/Octavia Community Advisory Comm. | B6: ='Complete List_09252026'!C170 -> Ted Olsson | C6: ='Complete List_09252026'!E170 -> 30 Sharon Street | D6: ='Complete List_09252026'!F170 -> San Francisco | E6: ='Complete List_09252026'!G170 -> CA | F6: ='Complete List_09252026'!H170 -> 94114-1709 | G6: ='Complete List_09252026'!J170 -> olssonted@yahoo.com | H6: ='Complete List_09252026'!K170 -> Physical | I6: ='Complete List_09252026'!L170 -> Castro/Upper Market, Downtown/Civic Center, Mission
A7: Valencia Corridor Merchant Association | B7: ='Complete List_09252026'!C304 -> Sean Quigley | C7: ='Complete List_09252026'!E304 -> 766 Valencia Street, 3rd Floor | D7: ='Complete List_09252026'!F304 -> San Francisco | E7: ='Complete List_09252026'!G304 -> CA | F7: ='Complete List_09252026'!H304 -> 94110 | G7: ='Complete List_09252026'!J304 -> seanq@paxtongate.com | H7: ='Complete List_09252026'!K304 -> Physical | I7: ='Complete List_09252026'!L304 -> Castro/Upper Market, Mission, Potrero Hill
A8: Eureka Valley Trails/Art Network | B8: ='Complete List_09252026'!C95 -> Bruce Murphy | C8: ='Complete List_09252026'!E95 -> 1281 Quesada Ave | D8: ='Complete List_09252026'!F95 -> San Francisco | E8: ='Complete List_09252026'!G95 -> CA | F8: ='Complete List_09252026'!H95 -> 94124-3334 | G8: ='Complete List_09252026'!J95 -> luckylaowai.sf@gmail.com | H8: ='Complete List_09252026'!K95 -> Physical | I8: ='Complete List_09252026'!L95 -> Bayview, Castro/Upper Market
A9: Eureka/17th Street Neighbors | B9: ='Complete List_09252026'!C96 -> Jack Keating | C9: ='Complete List_09252026'!E96 -> 4134 17th Street | D9: ='Complete List_09252026'!F96 -> San Francisco | E9: ='Complete List_09252026'!G96 -> CA | F9: ='Complete List_09252026'!H96 -> 94114 | G9: ='Complete List_09252026'!J96 -> jteamj@comcast.net | H9: ='Complete List_09252026'!K96 -> Physical | I9: ='Complete List_09252026'!L96 -> Castro/Upper Market
A10: BOTH PHYSICAL & ELECTRONIC NOTICES
A11: Board of Supervisors | B11: ='Complete List_09252026'!C38 -> Rafael Mandelman | C11: ='Complete List_09252026'!E38 -> 1 Dr. Carlton B Goodlett Place, Room #244 | D11: ='Complete List_09252026'!F38 -> San Francisco | E11: ='Complete List_09252026'!G38 -> CA | F11: ='Complete List_09252026'!H38 -> 94102-4689 | G11: ='Complete List_09252026'!J38 -> Rafael.Mandelman@sfgov.org; Kyle.Smeallie@sfgov.org; Tom.Temprano@sfgov.org; jacob.bintliff@sfgov.org; mandelmanstaff@sfgov.org | H11: ='Complete List_09252026'!K38 -> Both | I11: ='Complete List_09252026'!L38 -> Castro/Upper Market, Diamond Heights, Glen Park, Noe Valley, Twin Peaks
A12: ='Complete List_09252026'!D263 -> SIPS Review Group | B12: ='Complete List_09252026'!C263 -> Patrick Mooney | C12: ='Complete List_09252026'!E263 -> 62 Carmelita Street | D12: ='Complete List_09252026'!F263 -> San Francisco | E12: ='Complete List_09252026'!G263 -> CA | F12: ='Complete List_09252026'!H263 -> 94117 | G12: ='Complete List_09252026'!J263 -> pmmsfo@gmail.com | H12: ='Complete List_09252026'!K263 -> Both | I12: ='Complete List_09252026'!L263 -> Castro / Upper Market, Haight Ashbury, Western Addition
A13: ELECTRONIC NOTICES
A14: Castro Merchants | B14: ='Complete List_09252026'!C54 -> Nikolas Blanchet | C14: ='Complete List_09252026'!E54 -> 584 Castro Street #333 | D14: ='Complete List_09252026'!F54 -> San Francisco | E14: ='Complete List_09252026'!G54 -> CA | F14: ='Complete List_09252026'!H54 -> 94114 | G14: ='Complete List_09252026'!J54 -> info@castromerchants.com | H14: ='Complete List_09252026'!K54 -> Electronic | I14: ='Complete List_09252026'!L174 -> Castro/Upper Market
A15: Castro Upper Market Community Benefit District | B15: ='Complete List_09252026'!C55 -> Andrea Aiello | C15: ='Complete List_09252026'!E55 -> 693 14th Street | D15: ='Complete List_09252026'!F55 -> San Francisco | E15: ='Complete List_09252026'!G55 -> CA | F15: ='Complete List_09252026'!H55 -> 94114 | G15: ='Complete List_09252026'!J55 -> ExecDirector@CastroCBD.org | H15: ='Complete List_09252026'!K55 -> Electronic | I15: ='Complete List_09252026'!L55 -> Castro/Upper Market, Haight Ashbury, Noe Valley
A16: Dolores Heights Improvement Club-DRC | B16: ='Complete List_09252026'!C86 -> Planning and Land Use Committee | C16: ='Complete List_09252026'!E86 -> 4016 20th Street | D16: ='Complete List_09252026'!F86 -> San Francisco | E16: ='Complete List_09252026'!G86 -> CA | F16: ='Complete List_09252026'!H86 -> 94114 | G16: ='Complete List_09252026'!J86 -> plu@doloresheights.org | H16: ='Complete List_09252026'!K86 -> Electronic | I16: ='Complete List_09252026'!L86 -> Castro/Upper Market, Mission, Noe Valley
A17: Duboce Triangle Neighborhood Association | B17: ='Complete List_09252026'!C87 -> Kevin Riley | C17: ='Complete List_09252026'!E87 -> 2261 Market Street PMB #301 | D17: ='Complete List_09252026'!F87 -> San Francisco | E17: ='Complete List_09252026'!G87 -> CA | F17: ='Complete List_09252026'!H87 -> 94114 | G17: ='Complete List_09252026'!J87 -> landuse@dtna.org | H17: ='Complete List_09252026'!K87 -> Electronic | I17: ='Complete List_09252026'!L87 -> Castro/Upper Market, Western Addition
A18: Eureka Valley Neighborhood Association | B18: ='Complete List_09252026'!C94 -> Jennifer Waggoner | C18: ='Complete List_09252026'!E94 -> P.O. Box 14137 | D18: ='Complete List_09252026'!F94 -> San Francisco | E18: ='Complete List_09252026'!G94 -> CA | F18: ='Complete List_09252026'!H94 -> 94114-2827 | G18: ='Complete List_09252026'!J94 -> president@evna.org | H18: ='Complete List_09252026'!K94 -> Electronic | I18: ='Complete List_09252026'!L94 -> Castro/Upper Market
A19: Hayes Valley Neighborhood Association | B19: ='Complete List_09252026'!C126 -> Jennifer Laska | C19: ='Complete List_09252026'!E126 -> 400 Grove Street, Suite 3 | D19: ='Complete List_09252026'!F126 -> San Francisco | E19: ='Complete List_09252026'!G126 -> CA | F19: ='Complete List_09252026'!H126 -> 94102 | G19: ='Complete List_09252026'!J126 -> president@hayesvalleysf.org | H19: ='Complete List_09252026'!K126 -> Electronic | I19: ='Complete List_09252026'!L126 -> Castro/Upper Market, Downtown/Civic Center, Mission, South of Market, Western Addition
A20: Hayes Valley Safe | B20: ='Complete List_09252026'!C128 -> Richard Johnson | C20: ='Complete List_09252026'!E128 -> 415 Buchanan St Apt C | D20: ='Complete List_09252026'!F128 -> San Francisco | E20: ='Complete List_09252026'!G128 -> CA | F20: ='Complete List_09252026'!H128 -> 94102 | G20: ='Complete List_09252026'!J128 -> info@hvsafe.com | H20: ='Complete List_09252026'!K128 -> Electronic | I20: ='Complete List_09252026'!L128 -> Castro/Upper Market, Downtown/Civic Center, Mission, South of Market, Western Addition
A21: Hayes Valley Small Business Association | B21: ='Complete List_09252026'!C127 -> Ramiz Y | C21: ='Complete List_09252026'!E127 -> 559 Hayes Street | D21: ='Complete List_09252026'!F127 -> San Francisco | E21: ='Complete List_09252026'!G127 -> CA | F21: ='Complete List_09252026'!H127 -> 94102 | G21: ='Complete List_09252026'!J127 -> info@hvsba.org | H21: ='Complete List_09252026'!K127 -> Electronic | I21: ='Complete List_09252026'!L127 -> Castro/Upper Market, Downtown/Civic Center, Mission, South of Market, Western Addition
A22: Mission Dolores Neighborhood Association | B22: ='Complete List_09252026'!C184 -> Peter Lewis | C22: ='Complete List_09252026'!E184 -> 72 Landers Street | D22: ='Complete List_09252026'!F184 -> San Francisco | E22: ='Complete List_09252026'!G184 -> CA | F22: ='Complete List_09252026'!H184 -> 94110 | G22: ='Complete List_09252026'!J184 -> missiondna@earthlink.net | H22: ='Complete List_09252026'!K184 -> Electronic | I22: ='Complete List_09252026'!L184 -> Castro/Upper Market, Mission
A23: Mt. Olympus Neighbors Association | B23: ='Complete List_09252026'!C192 -> Dan Slaughter | C23: ='Complete List_09252026'!E192 -> 379 Upper Terrace | D23: ='Complete List_09252026'!F192 -> San Francisco | E23: ='Complete List_09252026'!G192 -> CA | F23: ='Complete List_09252026'!H192 -> 94117 | G23: ='Complete List_09252026'!J192 -> dkslaughter@gmail.com | H23: ='Complete List_09252026'!K192 -> Electronic | I23: ='Complete List_09252026'!L192 -> Castro/Upper Market, Haight Ashbury
A24: San Francisco Land Use Coalition (SFLUC) | B24: ='Complete List_09252026'!C255 -> Gary Weiss | C24: ='Complete List_09252026'!E255 -> 78 Mars Street | D24: ='Complete List_09252026'!F255 -> San Francisco | E24: ='Complete List_09252026'!G255 -> CA | F24: ='Complete List_09252026'!H255 -> 94114 | G24: ='Complete List_09252026'!J255 -> garysfx@gmail.com | H24: ='Complete List_09252026'!K255 -> Electronic | I24: ='Complete List_09252026'!L255 -> Castro/Upper Market, Diamond Heights, Glen Park, Haight Ashbury, Mission, Noe Valley, South of Market, Twin Peaks, Upper Market, Western Addition
A25: Sharon Street Neighborhood Association | B25: ='Complete List_09252026'!C259 -> Bill Tannenbaum | C25: ='Complete List_09252026'!E259 -> 46 Sharon Street | D25: ='Complete List_09252026'!F259 -> San Francisco | E25: ='Complete List_09252026'!G259 -> CA | F25: ='Complete List_09252026'!H259 -> 94114 | G25: ='Complete List_09252026'!J259 -> Btannenbaum@arws.com | H25: ='Complete List_09252026'!K259 -> Electronic | I25: ='Complete List_09252026'!L259 -> Castro/Upper Market
A26: ='Complete List_09252026'!D53 -> Castro LGBTQ Cultural District | B26: ='Complete List_09252026'!C53 -> Jesse Sanford & Stephen Torres | C26: ='Complete List_09252026'!E53 -> 1800 Market Street | D26: ='Complete List_09252026'!F53 -> San Francisco | E26: ='Complete List_09252026'!G53 -> CA | F26: ='Complete List_09252026'!H53 -> 94102 | G26: ='Complete List_09252026'!J53 -> landuse@castrolgbtq.org | H26: ='Complete List_09252026'!K53 -> Electronic | I26: ='Complete List_09252026'!L53 -> Bernal Heights, Castro/Upper Market, Downtown/Civic Center, Mission, Noe Valley, South of Market
A27: ='Complete List_09252026'!D177 -> Mid-Market Neighbors | B27: ='Complete List_09252026'!C177 -> Chuck Obermeyer | C27: ='Complete List_09252026'!E177 -> 30 7th Street | D27: ='Complete List_09252026'!F177 -> San Francisco | E27: ='Complete List_09252026'!G177 -> CA | F27: ='Complete List_09252026'!H177 -> 94103 | G27: ='Complete List_09252026'!J177 -> chuck@midmarketneighbors.org | H27: ='Complete List_09252026'!K177 -> Electronic | I27: ='Complete List_09252026'!L177 -> Castro/Upper Market, Chinatown, Downtown/Civic Center, Financial District, Nob Hill, Potrero Hill, South of Market, Western Addition
A28: ='Complete List_09252026'!D154 -> Liberation Alliance for Economic and Social Change | B28: ='Complete List_09252026'!C154 -> Keith Pavlik | C28: ='Complete List_09252026'!E154 -> 2969 Mission Street | D28: ='Complete List_09252026'!F154 -> San Francisco | E28: ='Complete List_09252026'!G154 -> CA | F28: ='Complete List_09252026'!H154 -> 94110 | G28: ='Complete List_09252026'!J154 -> info@liberationalliance.org | H28: ='Complete List_09252026'!K154 -> Electronic | I28: ='Complete List_09252026'!L154 -> Bayview, Bernal Heights, Castro/Upper Market, Chinatown, Downtown/Civic Center, Excelsior, Mission, Nob Hill, Noe Valley, Outer Mission, Potrero Hill, South of Market, Western Addition
A29: ='Complete List_09252026'!D73 -> Corbett Heights Neighbors | B29: ='Complete List_09252026'!C73 -> Maryann Dresner | C29: ='Complete List_09252026'!E73 -> P.O. Box 14493 | D29: ='Complete List_09252026'!F73 -> San Francisco | E29: ='Complete List_09252026'!G73 -> CA | F29: ='Complete List_09252026'!H73 -> 94114 | G29: ='Complete List_09252026'!J73 -> info@corbettneighbors.com | H29: ='Complete List_09252026'!K73 -> Electronic | I29: ='Complete List_09252026'!L73 -> Castro/Upper Market, Noe Valley, West of Twin Peaks
A30: ='Complete List_09252026'!D47 -> Buena Vista Neighborhood Association | B30: ='Complete List_09252026'!C47 -> Rasheq Zarif | C30: ='Complete List_09252026'!E47 -> 1388 Haight Street #1236 | D30: ='Complete List_09252026'!F47 -> San Francisco | E30: ='Complete List_09252026'!G47 -> CA | F30: ='Complete List_09252026'!H47 -> 94117 | G30: ='Complete List_09252026'!J47 -> info@bvnasf.org | H30: ='Complete List_09252026'!K47 -> Electronic | I30: ='Complete List_09252026'!L47 -> Castro/Upper Market

Sheet Chinatown
A1: ORGANIZATION | B1: ='Complete List_09252026'!C1 -> NAME | C1: ='Complete List_09252026'!E1 -> ADDRESS | D1: ='Complete List_09252026'!F1 -> CITY | E1: ='Complete List_09252026'!G1 -> STATE | F1: ='Complete List_09252026'!H1 -> ZIP | G1: ='Complete List_09252026'!J1 -> EMAIL | H1: NOTIFICATION PREFERENCES | I1: ='Complete List_09252026'!L1 -> NEIGHBORHOOD OF INTEREST
A2: PHYSICAL NOTICES
A3: 874 Sacramento Street Tenants Association | B3: ='Complete List_09252026'!C10 -> Jeffrey Kwong | C3: ='Complete List_09252026'!E10 -> 1754 Hyde Street | D3: ='Complete List_09252026'!F10 -> San Francisco | E3: ='Complete List_09252026'!G10 -> CA | F3: ='Complete List_09252026'!H10 -> 94106 | G3: ='Complete List_09252026'!J10 -> cardinalsf@gmail.com | H3: ='Complete List_09252026'!K10 -> Physical | I3: ='Complete List_09252026'!L10 -> Chinatown, Downtown Civic Center, Financial District, Nob Hill, North Beach
A4: Chinese Chamber of Commerce | B4: ='Complete List_09252026'!C60 | C4: ='Complete List_09252026'!E60 -> 730 Sacramento Street | D4: ='Complete List_09252026'!F60 -> San Francisco | E4: ='Complete List_09252026'!G60 -> CA | F4: ='Complete List_09252026'!H60 -> 94108 | G4: ='Complete List_09252026'!J60 -> 0 | H4: ='Complete List_09252026'!K60 -> Physical | I4: ='Complete List_09252026'!L60 -> Chinatown
A5: Chinese Newcomers Service Center | B5: ='Complete List_09252026'!C61 -> George Chan | C5: ='Complete List_09252026'!E61 -> 777 Stockton Street #104 | D5: ='Complete List_09252026'!F61 -> San Francisco | E5: ='Complete List_09252026'!G61 -> CA | F5: ='Complete List_09252026'!H61 -> 94108 | G5: ='Complete List_09252026'!J61 -> georgechan@chinesenewcomers.org | H5: ='Complete List_09252026'!K61 -> Electronic | I5: ='Complete List_09252026'!L61 -> Chinatown
A6: Friends of Appleton-Wolfard Libraries | B6: ='Complete List_09252026'!C106 -> Howard Wong | C6: ='Complete List_09252026'!E106 -> 126 Varennes | D6: ='Complete List_09252026'!F106 -> San Francisco | E6: ='Complete List_09252026'!G106 -> CA | F6: ='Complete List_09252026'!H106 -> 94133 | G6: ='Complete List_09252026'!J106 -> WongAIA@aol.com | H6: ='Complete List_09252026'!K106 -> Physical | I6: ='Complete List_09252026'!L106 -> Chinatown, North Beach
A7: HERE Local 2 | B7: ='Complete List_09252026'!C129 -> Ian Lewis | C7: ='Complete List_09252026'!E129 -> 209 Golden Gate Avenue | D7: ='Complete List_09252026'!F129 -> San Francisco | E7: ='Complete List_09252026'!G129 -> CA | F7: ='Complete List_09252026'!H129 -> 94102 | G7: ='Complete List_09252026'!J129 -> 0 | H7: ='Complete List_09252026'!K129 -> Physical | I7: ='Complete List_09252026'!L129 -> Chinatown, Downtown/Civic Center, Marina, Mission, Nob Hill, North Beach, Pacific Heights, Presidio, South of Market
A8: Hotel Zeppelin | B8: ='Complete List_09252026'!C131 -> Antonio Flores | C8: ='Complete List_09252026'!E131 -> 545 Post Street | D8: ='Complete List_09252026'!F131 -> San Francisco | E8: ='Complete List_09252026'!G131 -> CA | F8: ='Complete List_09252026'!H131 -> 94102 | G8: ='Complete List_09252026'!J131 -> antonio.flores@viceroyhotelgroup.com | H8: ='Complete List_09252026'!K131 -> Physical | I8: ='Complete List_09252026'!L131 -> Castro/Upper Market, Chinatown, Downtown/Civic Center, Financial District, Nob Hill, North Beach, South of Market, Treasure Island
A9: Jackson Square Historic District Assn. | B9: ='Complete List_09252026'!C139 -> Sarah Stocking | C9: ='Complete List_09252026'!E139 -> 368 Jackson Street | D9: ='Complete List_09252026'!F139 -> San Francisco | E9: ='Complete List_09252026'!G139 -> CA | F9: ='Complete List_09252026'!H139 -> 94111 | G9: ='Complete List_09252026'!J139 -> sarah@sarahstocking.com | H9: ='Complete List_09252026'!K139 -> Physical | I9: ='Complete List_09252026'!L139 -> Chinatown, Financial District, North Beach
A10: St. Vincent de Paul Society, North Beach | B10: ='Complete List_09252026'!C283 -> Marc Bruno | C10: ='Complete List_09252026'!E283 -> 666 Filbert Street | D10: ='Complete List_09252026'!F283 -> San Francisco | E10: ='Complete List_09252026'!G283 -> CA | F10: ='Complete List_09252026'!H283 -> 94133 | G10: ='Complete List_09252026'!J283 -> marcabruno@yahoo.com | H10: ='Complete List_09252026'!K283 -> Physical | I10: ='Complete List_09252026'!L283 -> Chinatown, Financial District, Nob Hill, North Beach, Russian Hill
A11: San Franciscans for Reasonable Growth (SFRG) | B11: ='Complete List_09252026'!C244 -> Sue Hestor | C11: ='Complete List_09252026'!E244 -> 329 Highland Ave | D11: ='Complete List_09252026'!F244 -> San Francisco | E11: ='Complete List_09252026'!G244 -> CA | F11: ='Complete List_09252026'!H244 -> 94110 | G11: ='Complete List_09252026'!J244 -> hestor@earthlink.net | H11: Physical | I11: ='Complete List_09252026'!L244 -> Bernal Heights, Chinatown, Downtown/Civic Center, Mission
A12: BOTH PHYSICAL & ELECTRONIC NOTICES
A13: Board of Supervisors | B13: ='Complete List_09252026'!C36 -> Danny Sauter | C13: ='Complete List_09252026'!E36 -> 1 Dr. Carlton B Goodlett Place, Room #244 | D13: ='Complete List_09252026'!F36 -> San Francisco | E13: ='Complete List_09252026'!G36 -> CA | F13: ='Complete List_09252026'!H36 -> 94102-4689 | G13: ='Complete List_09252026'!J36 -> SauterStaff@sfgov.org; Michelle.Andrews@sfgov.org; Amy.Lee5@sfgov.org; tita.bell@sfgov.org; tomio.nagano@sfgov.org | H13: ='Complete List_09252026'!K36 -> Both | I13: ='Complete List_09252026'!L36 -> Chinatown, Financial District, Nob Hill, North Beach, Russian Hill
A14: ELECTRONIC NOTICES
A15: Chinatown Community Development Center (CCDC) | B15: ='Complete List_09252026'!C59 -> Malcom Yeung | C15: ='Complete List_09252026'!E59 -> 615 Grant Avenue | D15: ='Complete List_09252026'!F59 -> San Francisco | E15: ='Complete List_09252026'!G59 -> CA | F15: ='Complete List_09252026'!H59 -> 94133 | G15: ='Complete List_09252026'!J59 -> myeung@chinatowncdc.org; matthias.mormino@chinatowncdc.org; sharon.ng@chinatowncdc.org; tandchow@gmail.com; | H15: ='Complete List_09252026'!K59 -> Electronic | I15: ='Complete List_09252026'!L59 -> Chinatown, Financial District, Nob Hill, North Beach, Russian Hill
A16: North Beach Neighbors | B16: ='Complete List_09252026'!C205 -> Danny Sauter | C16: ='Complete List_09252026'!E205 -> P.O. Box 330115 | D16: ='Complete List_09252026'!F205 -> San Francisco | E16: ='Complete List_09252026'!G205 -> CA | F16: ='Complete List_09252026'!H205 -> 94133 | G16: ='Complete List_09252026'!J205 -> northbeachneighbors@ymail.com | H16: ='Complete List_09252026'!K205 -> Electronic | I16: ='Complete List_09252026'!L205 -> Chinatown, Financial District, Nob Hill, North Beach, Russian Hill
A17: Self-Help for the Elderly | B17: ='Complete List_09252026'!C247 -> Anni Chung | C17: ='Complete List_09252026'!E247 -> 731 Sansome Street, Suite 1000 | D17: ='Complete List_09252026'!F247 -> San Francisco | E17: ='Complete List_09252026'!G247 -> CA | F17: ='Complete List_09252026'!H247 -> 94111 | G17: ='Complete List_09252026'!J247 -> annic@selfhelpelderly.org | H17: ='Complete List_09252026'!K247 -> Electronic | I17: ='Complete List_09252026'!L247 -> Chinatown, Inner Richmond, Inner Sunset, Outer Richmond, Outer Sunset
A18: ='Complete List_09252026'!D203 -> Northeast San Francisco Conservancy | B18: ='Complete List_09252026'!C203 -> Nancy Shanahan | C18: ='Complete List_09252026'!E203 -> 224 Filbert Street | D18: ='Complete List_09252026'!F203 -> San Francisco | E18: ='Complete List_09252026'!G203 -> CA | F18: ='Complete List_09252026'!H203 -> 94133 | G18: ='Complete List_09252026'!J203 -> nshan@mindspring.com | H18: ='Complete List_09252026'!K203 -> Electronic | I18: ='Complete List_09252026'!L203 -> Chinatown, Financial District, North Beach, Russian Hill
A19: ='Complete List_09252026'!D210 -> Northern Neighbors | B19: ='Complete List_09252026'!C210 -> Michael Chen | C19: ='Complete List_09252026'!E210 -> 2655 Bush St. Apt. 303 | D19: ='Complete List_09252026'!F210 -> San Francisco | E19: ='Complete List_09252026'!G210 -> CA | F19: ='Complete List_09252026'!H210 -> 94115 | G19: ='Complete List_09252026'!J210 -> hello@northernneighbors.org | H19: ='Complete List_09252026'!K210 -> Electronic | I19: ='Complete List_09252026'!L210 -> Chinatown, Financial District, Nob Hill, North Beach, Pacific Heights, Presidio, Presidio Heights, Russian Hill, Seacliff
A20: ='Complete List_09252026'!D177 -> Mid-Market Neighbors | B20: ='Complete List_09252026'!C177 -> Chuck Obermeyer | C20: ='Complete List_09252026'!E177 -> 30 7th Street | D20: ='Complete List_09252026'!F177 -> San Francisco | E20: ='Complete List_09252026'!G177 -> CA | F20: ='Complete List_09252026'!H177 -> 94103 | G20: ='Complete List_09252026'!J177 -> chuck@midmarketneighbors.org | H20: ='Complete List_09252026'!K177 -> Electronic | I20: ='Complete List_09252026'!L177 -> Castro/Upper Market, Chinatown, Downtown/Civic Center, Financial District, Nob Hill, Potrero Hill, South of Market, Western Addition
A21: ='Complete List_09252026'!D154 -> Liberation Alliance for Economic and Social Change | B21: ='Complete List_09252026'!C154 -> Keith Pavlik | C21: ='Complete List_09252026'!E154 -> 2969 Mission Street | D21: ='Complete List_09252026'!F154 -> San Francisco | E21: ='Complete List_09252026'!G154 -> CA | F21: ='Complete List_09252026'!H154 -> 94110 | G21: ='Complete List_09252026'!J154 -> info@liberationalliance.org | H21: ='Complete List_09252026'!K154 -> Electronic | I21: ='Complete List_09252026'!L154 -> Bayview, Bernal Heights, Castro/Upper Market, Chinatown, Downtown/Civic Center, Excelsior, Mission, Nob Hill, Noe Valley, Outer Mission, Potrero Hill, South of Market, Western Addition
A22: ='Complete List_09252026'!D302 -> Upper Chinatown Neighborhood Association | B22: ='Complete List_09252026'!C302 -> Jennifer Mei | C22: ='Complete List_09252026'!E302 -> 1144 Pacific Avenue | D22: ='Complete List_09252026'!F302 -> San Francisco | E22: ='Complete List_09252026'!G302 -> CA | F22: ='Complete List_09252026'!H302 -> 94133 | G22: ='Complete List_09252026'!J302 -> upperchinatownassociation@gmail.com | H22: ='Complete List_09252026'!K302 -> Electronic | I22: ='Complete List_09252026'!L302 -> Chinatown, Nob Hill, Russian Hill

Sheet Crocker Amazon
A1: ORGANIZATION | B1: ='Complete List_09252026'!C1 -> NAME | C1: ='Complete List_09252026'!E1 -> ADDRESS | D1: ='Complete List_09252026'!F1 -> CITY | E1: ='Complete List_09252026'!G1 -> STATE | F1: ='Complete List_09252026'!H1 -> ZIP | G1: ='Complete List_09252026'!J1 -> EMAIL | H1: NOTIFICATION PREFERENCES | I1: ='Complete List_09252026'!L1 -> NEIGHBORHOOD OF INTEREST
A2: PHYSICAL NOTICES
A3: Excelsior District Improvement Association | B3: ='Complete List_09252026'!C98 -> Mel Flores | C3: ='Complete List_09252026'!E98 -> P.O. Box 12005 | D3: ='Complete List_09252026'!F98 -> San Francisco | E3: ='Complete List_09252026'!G98 -> CA | F3: ='Complete List_09252026'!H98 -> 94112 | G3: ='Complete List_09252026'!J98 -> melfloressf@gmail.com | H3: ='Complete List_09252026'!K98 -> Physical | I3: ='Complete List_09252026'!L98 -> Crocker Amazon, Excelsior, Ocean View, Outer Mission
A4: Sherwin Williams | B4: ='Complete List_09252026'!C261 -> Francesca Panullo | C4: ='Complete List_09252026'!E261 -> 1415 Ocean Ave | D4: ='Complete List_09252026'!F261 -> San Francisco | E4: ='Complete List_09252026'!G261 -> CA | F4: ='Complete List_09252026'!H261 -> 94112 | G4: ='Complete List_09252026'!J261 -> sw8644@sherwin.com | H4: ='Complete List_09252026'!K261 -> Physical | I4: ='Complete List_09252026'!L261 -> Bayview, Bernal Heights, Crocker Amazon, Diamond Heights, Excelsior, Glen Park, Inner Sunset, Lakeshore, Noe Valley, Ocean View, Outer Mission, Outer Sunset, Parkside, Potrero Hill, South Bayshore, Twin Peaks, Visitacion Valley, West of Twin Peaks
A5: People Organizing to Demand Environmental and Economic Rights (PODER) | B5: ='Complete List_09252026'!C228 -> Antonio Diaz | C5: ='Complete List_09252026'!E228 -> 474 Valencia Street #125 | D5: ='Complete List_09252026'!F228 -> San Francisco | E5: ='Complete List_09252026'!G228 -> CA | F5: ='Complete List_09252026'!H228 -> 94103 | G5: ='Complete List_09252026'!J228 -> info@podersf.org | H5: ='Complete List_09252026'!K228 -> Physical | I5: ='Complete List_09252026'!L228 -> Crocker Amazon, Excelsior, Mission, Ocean View, Outer Mission, South of Market
A6: New Mission Terrace Improvement Association (NMTIA) | B6: ='Complete List_09252026'!C197 -> David Hooper | C6: ='Complete List_09252026'!E197 -> P.O. Box 12111 | D6: ='Complete List_09252026'!F197 -> San Francisco | E6: ='Complete List_09252026'!G197 -> CA | F6: ='Complete List_09252026'!H197 -> 94112 | G6: ='Complete List_09252026'!J197 -> nmtiasf@gmail.com | H6: ='Complete List_09252026'!K197 -> Physical | I6: ='Complete List_09252026'!L197 -> Crocker Amazon, Excelsior, Glen Park, Outer Mission,
A7: Outer Mission Residents Association | B7: ='Complete List_09252026'!C221 -> Joelle Kenealey | C7: ='Complete List_09252026'!E221 -> P. O. Box 34426 | D7: ='Complete List_09252026'!F221 -> San Francisco | E7: ='Complete List_09252026'!G221 -> CA | F7: ='Complete List_09252026'!H221 -> 94134 | G7: ='Complete List_09252026'!J221 -> sfommra@gmail.com | H7: ='Complete List_09252026'!K221 -> Physical | I7: ='Complete List_09252026'!L221 -> Excelsior, Outer Mission, Crocker Amazon, Visitacion Valley
A8: BOTH PHYSICAL & ELECTRONIC NOTICES
A9: Board of Supervisors | B9: ='Complete List_09252026'!C37 -> Chyanne Chen | C9: ='Complete List_09252026'!E37 -> 1 Dr. Carlton B Goodlett Place, Room #244 | D9: ='Complete List_09252026'!F37 -> San Francisco | E9: ='Complete List_09252026'!G37 -> CA | F9: ='Complete List_09252026'!H37 -> 94102-4689 | G9: ='Complete List_09252026'!J37 -> ChenStaff@sfgov.org; Charlie.Sciammas@sfgov.org | H9: ='Complete List_09252026'!K37 -> Both | I9: ='Complete List_09252026'!L37 -> Crocker Amazon, Excelsior, Outer Mission, Visitacion Valley
A10: ELECTRONIC NOTICES
A11: Both Sides of the Conversation | B11: Jon Henry | C11: P.O. Box 347518 | D11: San Francisco | E11: CA | F11: 94134 | G11: jonhenry@bsotc.org | H11: Electronic | I11: Bayview, Bernal Heights, Crocker Amazon, Downtown/Civic Center, Excelsior, Glen Park, Haight Ashbury, Potrero Hill, South of Market, Treasure Island, Visitacion Valley, West of Twin Peaks, Western Addition
A12: ='Complete List_09252026'!D216 -> OMI Cultural Participation Project | B12: ='Complete List_09252026'!C216 -> Maurice Rivers | C12: ='Complete List_09252026'!E216 -> P.O. Box 12263 | D12: ='Complete List_09252026'!F216 -> San Francisco | E12: ='Complete List_09252026'!G216 -> CA | F12: ='Complete List_09252026'!H216 -> 94112 | G12: ='Complete List_09252026'!J216 -> jumpstreet1983@gmail.com | H12: ='Complete List_09252026'!K216 -> Electronic | I12: ='Complete List_09252026'!L216 -> Crocker Amazon, Excelsior, Ocean View, Outer Mission
A13: OneBayview | B13: ='Complete List_09252026'!C217 -> Anietie Ekanem | C13: ='Complete List_09252026'!E217 -> 5800 3rd Street #1320 | D13: ='Complete List_09252026'!F217 -> San Francisco | E13: ='Complete List_09252026'!G217 -> CA | F13: ='Complete List_09252026'!H217 -> 94124 | G13: ='Complete List_09252026'!J217 -> sfplanningdepartment@onebayview.com aekanem@onebayview.com | H13: ='Complete List_09252026'!K217 -> Electronic | I13: ='Complete List_09252026'!L217 -> Bayview, Crocker Amazon, Excelsior, Ocean View, Potrero Hill, Visitacion Valley
A14: ='Complete List_09252026'!D146 -> Keep Crocker Real | B14: ='Complete List_09252026'!C146 -> KC Real | C14: ='Complete List_09252026'!E146 -> 0 | D14: ='Complete List_09252026'!F146 -> San Francisco | E14: ='Complete List_09252026'!G146 -> CA | F14: ='Complete List_09252026'!H146 -> 94112 | G14: ='Complete List_09252026'!J146 -> hello@keepcrockerreal.com | H14: ='Complete List_09252026'!K146 -> Electronic | I14: ='Complete List_09252026'!L146 -> Bayview, Crocker Amazon, Excelsior, Glen Park, Outer Mission, Visitacion Valley

Sheet Diamond Heights
A1: ORGANIZATION | B1: ='Complete List_09252026'!C1 -> NAME | C1: ='Complete List_09252026'!E1 -> ADDRESS | D1: ='Complete List_09252026'!F1 -> CITY | E1: ='Complete List_09252026'!G1 -> STATE | F1: ='Complete List_09252026'!H1 -> ZIP | G1: ='Complete List_09252026'!J1 -> EMAIL | H1: NOTIFICATION PREFERENCES | I1: ='Complete List_09252026'!L1 -> NEIGHBORHOOD OF INTEREST
A2: PHYSICAL NOTICES
A3: Martin Luther Tower | C3: ='Complete List_09252026'!E172 -> 1001 Franklin Street, Apt. 10K | D3: ='Complete List_09252026'!F172 -> San Francisco | E3: ='Complete List_09252026'!G172 -> CA | F3: ='Complete List_09252026'!H172 -> 94109 | G3: ='Complete List_09252026'!J172 -> larnder@aol.com | H3: ='Complete List_09252026'!K172 -> Physical | I3: ='Complete List_09252026'!L172 -> Downtown/Civic Center
A4: Sherwin Williams | B4: ='Complete List_09252026'!C261 -> Francesca Panullo | C4: ='Complete List_09252026'!E261 -> 1415 Ocean Ave | D4: ='Complete List_09252026'!F261 -> San Francisco | E4: ='Complete List_09252026'!G261 -> CA | F4: ='Complete List_09252026'!H261 -> 94112 | G4: ='Complete List_09252026'!J261 -> sw8644@sherwin.com | H4: ='Complete List_09252026'!K261 -> Physical | I4: ='Complete List_09252026'!L261 -> Bayview, Bernal Heights, Crocker Amazon, Diamond Heights, Excelsior, Glen Park, Inner Sunset, Lakeshore, Noe Valley, Ocean View, Outer Mission, Outer Sunset, Parkside, Potrero Hill, South Bayshore, Twin Peaks, Visitacion Valley, West of Twin Peaks
A5: West of Twin Peaks Central Council | B5: ='Complete List_09252026'!C309 -> Matt Chamberlain | C5: ='Complete List_09252026'!E309 -> P.O. Box 27112 | D5: ='Complete List_09252026'!F309 -> San Francisco | E5: ='Complete List_09252026'!G309 -> CA | F5: ='Complete List_09252026'!H309 -> 94127 | G5: ='Complete List_09252026'!J309 -> info@WestOfTwinPeaks.org President@WestOfTwinPeaks.org | H5: ='Complete List_09252026'!K309 -> Physical | I5: ='Complete List_09252026'!L309 -> Diamond Heights, Lakeshore, Parkside, Twin Peaks, West of Twin Peaks
A6: BOTH PHYSICAL & ELECTRONIC NOTICES
A7: Board of Supervisors | B7: ='Complete List_09252026'!C38 -> Rafael Mandelman | C7: ='Complete List_09252026'!E38 -> 1 Dr. Carlton B Goodlett Place, Room #244 | D7: ='Complete List_09252026'!F38 -> San Francisco | E7: ='Complete List_09252026'!G38 -> CA | F7: ='Complete List_09252026'!H38 -> 94102-4689 | G7: ='Complete List_09252026'!J38 -> Rafael.Mandelman@sfgov.org; Kyle.Smeallie@sfgov.org; Tom.Temprano@sfgov.org; jacob.bintliff@sfgov.org; mandelmanstaff@sfgov.org | H7: ='Complete List_09252026'!K38 -> Both | I7: ='Complete List_09252026'!L38 -> Castro/Upper Market, Diamond Heights, Glen Park, Noe Valley, Twin Peaks
A8: ELECTRONIC NOTICES
A9: Diamond Heights Community Association | B9: ='Complete List_09252026'!C79 -> Daniel Schereck | C9: ='Complete List_09252026'!E79 -> P.O. Box 31529 | D9: ='Complete List_09252026'!F79 -> San Francisco | E9: ='Complete List_09252026'!G79 -> CA | F9: ='Complete List_09252026'!H79 -> 94131 | G9: ='Complete List_09252026'!J79 -> dhcasf@gmail.com | H9: ='Complete List_09252026'!K79 -> Electronic | I9: ='Complete List_09252026'!L79 -> Diamond Heights, Glen Park, Noe Valley
A10: Diamond Heights Homeowners Association (DHHOA) | B10: ='Complete List_09252026'!C80 -> Carey Rutigliano | C10: ='Complete List_09252026'!E80 -> 108 Everson Street | D10: ='Complete List_09252026'!F80 -> San Francisco | E10: ='Complete List_09252026'!G80 -> CA | F10: ='Complete List_09252026'!H80 -> 94131 | G10: ='Complete List_09252026'!J80 -> careyruttig@yahoo.com | H10: ='Complete List_09252026'!K80 -> Electronic | I10: ='Complete List_09252026'!L80 -> Diamond Heights, Glen Park
A11: San Francisco Land Use Coalition (SFLUC) | B11: ='Complete List_09252026'!C255 -> Gary Weiss | C11: ='Complete List_09252026'!E255 -> 78 Mars Street | D11: ='Complete List_09252026'!F255 -> San Francisco | E11: ='Complete List_09252026'!G255 -> CA | F11: ='Complete List_09252026'!H255 -> 94114 | G11: ='Complete List_09252026'!J255 -> garysfx@gmail.com | H11: ='Complete List_09252026'!K255 -> Electronic | I11: ='Complete List_09252026'!L255 -> Castro/Upper Market, Diamond Heights, Glen Park, Haight Ashbury, Mission, Noe Valley, South of Market, Twin Peaks, Upper Market, Western Addition
A12: Sherwood Forest Homeowners Association | B12: ='Complete List_09252026'!C262 -> Tom Hoshiyama / Hiliarie Connolly | C12: ='Complete List_09252026'!E262 -> 111 Robinhood Drive | D12: ='Complete List_09252026'!F262 -> San Francisco | E12: ='Complete List_09252026'!G262 -> CA | F12: ='Complete List_09252026'!H262 -> 94127 | G12: ='Complete List_09252026'!J262 -> ConnollyHilarie@gmail.com | H12: ='Complete List_09252026'!K262 -> Electronic | I12: ='Complete List_09252026'!L262 -> Diamond Heights, Twin Peaks, West of Twin Peaks
A13: Twin Peaks Eastside Neighborhood Alliance (TPENA) | B13: ='Complete List_09252026'!C296 -> Nancy O'Brien | C13: ='Complete List_09252026'!E296 -> 74 Crestline Drive, #9 | D13: ='Complete List_09252026'!F296 -> San Francisco | E13: ='Complete List_09252026'!G296 -> CA | F13: ='Complete List_09252026'!H296 -> 94131 | G13: ='Complete List_09252026'!J296 -> nancyob6@comcast.net | H13: ='Complete List_09252026'!K296 -> Electronic | I13: ='Complete List_09252026'!L296 -> Diamond Heights, Twin Peaks

Sheet Downtown Civic Center
A1: ORGANIZATION | B1: ='Complete List_09252026'!C1 -> NAME | C1: ='Complete List_09252026'!E1 -> ADDRESS | D1: ='Complete List_09252026'!F1 -> CITY | E1: ='Complete List_09252026'!G1 -> STATE | F1: ='Complete List_09252026'!H1 -> ZIP | G1: ='Complete List_09252026'!J1 -> EMAIL | H1: NOTIFICATION PREFERENCES | I1: ='Complete List_09252026'!L1 -> NEIGHBORHOOD OF INTEREST
A2: PHYSICAL NOTICES
A3: 874 Sacramento Street Tenants Association | B3: ='Complete List_09252026'!C10 -> Jeffrey Kwong | C3: ='Complete List_09252026'!E10 -> 1754 Hyde Street | D3: ='Complete List_09252026'!F10 -> San Francisco | E3: ='Complete List_09252026'!G10 -> CA | F3: ='Complete List_09252026'!H10 -> 94106 | G3: ='Complete List_09252026'!J10 -> cardinalsf@gmail.com | H3: ='Complete List_09252026'!K10 -> Physical | I3: ='Complete List_09252026'!L10 -> Chinatown, Downtown Civic Center, Financial District, Nob Hill, North Beach
A4: Civic Center Community Benefit District | B4: ='Complete List_09252026'!C62 -> Tracy Everwine | C4: ='Complete List_09252026'!E62 -> 234 Van Ness Avenue | D4: ='Complete List_09252026'!F62 -> San Francisco | E4: ='Complete List_09252026'!G62 -> CA | F4: ='Complete List_09252026'!H62 -> 94102 | G4: ='Complete List_09252026'!J62 -> info@sfciviccenter.org | H4: ='Complete List_09252026'!K62 -> Physical | I4: ='Complete List_09252026'!L62 -> Downtown/Civic Center
A5: HERE Local 2 | B5: ='Complete List_09252026'!C129 -> Ian Lewis | C5: ='Complete List_09252026'!E129 -> 209 Golden Gate Avenue | D5: ='Complete List_09252026'!F129 -> San Francisco | E5: ='Complete List_09252026'!G129 -> CA | F5: ='Complete List_09252026'!H129 -> 94102 | G5: ='Complete List_09252026'!J129 -> 0 | H5: ='Complete List_09252026'!K129 -> Physical | I5: ='Complete List_09252026'!L129 -> Chinatown, Downtown/Civic Center, Marina, Mission, Nob Hill, North Beach, Pacific Heights, Presidio, South of Market
A6: Hotel Zeppelin | B6: ='Complete List_09252026'!C131 -> Antonio Flores | C6: ='Complete List_09252026'!E131 -> 545 Post Street | D6: ='Complete List_09252026'!F131 -> San Francisco | E6: ='Complete List_09252026'!G131 -> CA | F6: ='Complete List_09252026'!H131 -> 94102 | G6: ='Complete List_09252026'!J131 -> antonio.flores@viceroyhotelgroup.com | H6: ='Complete List_09252026'!K131 -> Physical | I6: ='Complete List_09252026'!L131 -> Castro/Upper Market, Chinatown, Downtown/Civic Center, Financial District, Nob Hill, North Beach, South of Market, Treasure Island
A7: Market Street for the Masses - Housing Equity | B7: ='Complete List_09252026'!C169 -> Kasey Rios Asberry | C7: ='Complete List_09252026'!E169 -> 245 Hyde Street | D7: ='Complete List_09252026'!F169 -> San Francisco | E7: ='Complete List_09252026'!G169 -> CA | F7: ='Complete List_09252026'!H169 -> 94102 | G7: ='Complete List_09252026'!J169 -> grow@demonstration-gardens.org | H7: ='Complete List_09252026'!K169 -> Physical | I7: ='Complete List_09252026'!L169 -> Downtown / Civic Center
A8: Market/Octavia Community Advisory Comm. | B8: ='Complete List_09252026'!C170 -> Ted Olsson | C8: ='Complete List_09252026'!E170 -> 30 Sharon Street | D8: ='Complete List_09252026'!F170 -> San Francisco | E8: ='Complete List_09252026'!G170 -> CA | F8: ='Complete List_09252026'!H170 -> 94114-1709 | G8: ='Complete List_09252026'!J170 -> olssonted@yahoo.com | H8: ='Complete List_09252026'!K170 -> Physical | I8: ='Complete List_09252026'!L170 -> Castro/Upper Market, Downtown/Civic Center, Mission
A9: Market/Van Ness Neighborhood Association | B9: ='Complete List_09252026'!C171 -> Mark Moreno | C9: ='Complete List_09252026'!E171 -> 77 Van Ness Avenue | D9: ='Complete List_09252026'!F171 -> San Francisco | E9: ='Complete List_09252026'!G171 -> CA | F9: ='Complete List_09252026'!H171 -> 94102 | G9: ='Complete List_09252026'!J171 -> mmoreno@citiscapesf.com | H9: ='Complete List_09252026'!K171 -> Physical | I9: ='Complete List_09252026'!L171 -> Downton/Civic Center
A10: Middle Polk Neighborhood Association | B10: ='Complete List_09252026'!C175 -> Adam Mayer | C10: ='Complete List_09252026'!E175 -> PO Box 640918 | D10: ='Complete List_09252026'!F175 -> San Francisco | E10: ='Complete List_09252026'!G175 -> CA | F10: ='Complete List_09252026'!H175 -> 94164 | G10: ='Complete List_09252026'!J175 -> moe@middlepolk.org | H10: ='Complete List_09252026'!K175 -> Physical | I10: ='Complete List_09252026'!L175 -> Downtown/Civic Center, Nob Hill, Russian Hill
A11: SF CityWide | B11: ='Complete List_09252026'!C251 -> David Lal | C11: ='Complete List_09252026'!E251 -> 142 S. Van Ness Ave | D11: ='Complete List_09252026'!F251 -> San Francisco | E11: ='Complete List_09252026'!G251 -> CA | F11: ='Complete List_09252026'!H251 -> 94103 | G11: ='Complete List_09252026'!J251 -> info@sfcitywide.org | H11: ='Complete List_09252026'!K251 -> Physical | I11: ='Complete List_09252026'!L251 -> Downtown/Civic Center, Financial District, South of Market, Treasure Island
A12: SoMaBend Neighborhood Association | B12: ='Complete List_09252026'!C268 -> Eric Lopez | C12: ='Complete List_09252026'!E268 -> P.O. Box 410805 | D12: ='Complete List_09252026'!F268 -> San Francisco | E12: ='Complete List_09252026'!G268 -> CA | F12: ='Complete List_09252026'!H268 -> 94141 | G12: ='Complete List_09252026'!J268 -> somabend.na@gmail.com | H12: ='Complete List_09252026'!K268 -> Physical | I12: ='Complete List_09252026'!L268 -> Downtown/Civic Center, Mission, South of Market
A13: Tenderloin Housing Clinic | B13: ='Complete List_09252026'!C291 -> Randy Shaw | C13: ='Complete List_09252026'!E291 -> 126 Hyde Street | D13: ='Complete List_09252026'!F291 -> San Francisco | E13: ='Complete List_09252026'!G291 -> CA | F13: ='Complete List_09252026'!H291 -> 94102 | G13: ='Complete List_09252026'!J291 -> randy@thclinic.org | H13: ='Complete List_09252026'!K291 -> Physical | I13: ='Complete List_09252026'!L291 -> Downtown/Civic Center
A14: Alliance for a Better District 6 | B14: ='Complete List_09252026'!C14 -> Michael Nulty | C14: ='Complete List_09252026'!E14 -> P.O. Box 420782 | D14: ='Complete List_09252026'!F14 -> San Francisco | E14: ='Complete List_09252026'!G14 -> CA | F14: ='Complete List_09252026'!H14 -> 94142 | G14: ='Complete List_09252026'!J14 -> sf_district6@yahoo.com | H14: ='Complete List_09252026'!K14 -> Physical | I14: ='Complete List_09252026'!L14 -> Downtown/Civic Center, Financial District, Mission, Nob Hill, South of Market, Treasure Island, Western Addition
A15: Tenderloin People's Congress | B15: ='Complete List_09252026'!C292 -> Curtis Bradford | C15: ='Complete List_09252026'!E292 -> 1390 Market Street #2206 | D15: ='Complete List_09252026'!F292 -> San Francisco | E15: ='Complete List_09252026'!G292 -> CA | F15: ='Complete List_09252026'!H292 -> 94102 | G15: ='Complete List_09252026'!J292 -> cbradford@tndc.org | H15: ='Complete List_09252026'!K292 -> Physical | I15: ='Complete List_09252026'!L292 -> Downtown/Civic Center, South of Market
A16: BOTH PHYSICAL & ELECTRONIC NOTICES
A17: Board of Supervisors | B17: ='Complete List_09252026'!C35 -> Bilal Mahmood | C17: ='Complete List_09252026'!E35 -> 1 Dr. Carlton B Goodlett Place, Room #244 | D17: ='Complete List_09252026'!F35 -> San Francisco | E17: ='Complete List_09252026'!G35 -> CA | F17: ='Complete List_09252026'!H35 -> 94102-4689 | G17: ='Complete List_09252026'!J35 -> MahmoodStaff@sfgov.org; Raynell.Cooper@sfgov.org | H17: ='Complete List_09252026'!K35 -> Both | I17: ='Complete List_09252026'!L35 -> Downtown/Civic Center, Haight Ashbury, Western Addition
A18: Board of Supervisors | B18: ='Complete List_09252026'!C43 -> Matt Dorsey | C18: ='Complete List_09252026'!E43 -> 1 Dr. Carlton B Goodlett Place, Room #244 | D18: ='Complete List_09252026'!F43 -> San Francisco | E18: ='Complete List_09252026'!G43 -> CA | F18: ='Complete List_09252026'!H43 -> 94102-4689 | G18: ='Complete List_09252026'!J43 -> DorseyStaff@sfgov.org; Madison.R.Tam@sfgov.org; Bryan.Dahl@sfgov.org; Leo.Alfaro@sfgov.org | H18: ='Complete List_09252026'!K43 -> Both | I18: ='Complete List_09252026'!L43 -> Downtown/Civic Center, South of Market, Treasure Island/YBI
A19: ='Complete List_09252026'!D71 -> Comptons Community Land Trust | B19: ='Complete List_09252026'!C71 -> Chandra LaBorde | C19: ='Complete List_09252026'!E71 -> 80 Turk St | D19: ='Complete List_09252026'!F71 -> San Franicsco | E19: ='Complete List_09252026'!G71 -> CA | F19: ='Complete List_09252026'!H71 -> 94102 | G19: ='Complete List_09252026'!J71 -> admin@turkxtaylor.net | H19: ='Complete List_09252026'!K71 -> Both | I19: ='Complete List_09252026'!L71 -> Downtown / Civic Center
A20: ELECTRONIC NOTICES
A21: Hayes Valley Safe | B21: ='Complete List_09252026'!C128 -> Richard Johnson | C21: ='Complete List_09252026'!E128 -> 415 Buchanan St Apt C | D21: ='Complete List_09252026'!F128 -> San Francisco | E21: ='Complete List_09252026'!G128 -> CA | F21: ='Complete List_09252026'!H128 -> 94102 | G21: ='Complete List_09252026'!J128 -> info@hvsafe.com | H21: ='Complete List_09252026'!K128 -> Electronic | I21: ='Complete List_09252026'!L128 -> Castro/Upper Market, Downtown/Civic Center, Mission, South of Market, Western Addition
A22: Hayes Valley Small Business Association | B22: ='Complete List_09252026'!C127 -> Ramiz Y | C22: ='Complete List_09252026'!E127 -> 559 Hayes Street | D22: ='Complete List_09252026'!F127 -> San Francisco | E22: ='Complete List_09252026'!G127 -> CA | F22: ='Complete List_09252026'!H127 -> 94102 | G22: ='Complete List_09252026'!J127 -> info@hvsba.org | H22: ='Complete List_09252026'!K127 -> Electronic | I22: ='Complete List_09252026'!L127 -> Castro/Upper Market, Downtown/Civic Center, Mission, South of Market, Western Addition
A23: Lower Polk Neighbors | B23: ='Complete List_09252026'!C164 -> Andrew Dunbar | C23: ='Complete List_09252026'!E164 -> 1450 Sutter Street #525 | D23: ='Complete List_09252026'!F164 -> San Francisco | E23: ='Complete List_09252026'!G164 -> CA | F23: ='Complete List_09252026'!H164 -> 94109 | G23: ='Complete List_09252026'!J164 -> lowerpolkneighbors@gmail.com | H23: ='Complete List_09252026'!K164 -> Electronic | I23: ='Complete List_09252026'!L164 -> Downtown/Civic Center, Nob Hill
A24: Cathedral Hill Neighbors Association | B24: ='Complete List_09252026'!C56 -> Marlayne Morgan | C24: ='Complete List_09252026'!E56 -> 1200 Gough Street, #17A | D24: ='Complete List_09252026'!F56 -> San Francisco | E24: ='Complete List_09252026'!G56 -> CA | F24: ='Complete List_09252026'!H56 -> 94109 | G24: ='Complete List_09252026'!J56 -> marlayne16@gmail.com | H24: ='Complete List_09252026'!K56 -> Electronic | I24: ='Complete List_09252026'!L56 -> Downtown/Civic Center, Western Addition
A25: Civic Center Stakeholder Group | B25: ='Complete List_09252026'!C63 -> James Haas | C25: ='Complete List_09252026'!E63 -> 100 Van Ness Avenue Apt 1906 | D25: ='Complete List_09252026'!F63 -> San Francisco | E25: ='Complete List_09252026'!G63 -> CA | F25: ='Complete List_09252026'!H63 -> 94102 | G25: ='Complete List_09252026'!J63 -> JWHaasESQ@AOL.com | H25: ='Complete List_09252026'!K63 -> Electronic | I25: ='Complete List_09252026'!L63 -> Downtown/Civic Center
A26: Hayes Valley Neighborhood Association | B26: ='Complete List_09252026'!C126 -> Jennifer Laska | C26: ='Complete List_09252026'!E126 -> 400 Grove Street, Suite 3 | D26: ='Complete List_09252026'!F126 -> San Francisco | E26: ='Complete List_09252026'!G126 -> CA | F26: ='Complete List_09252026'!H126 -> 94102 | G26: ='Complete List_09252026'!J126 -> president@hayesvalleysf.org | H26: ='Complete List_09252026'!K126 -> Electronic | I26: ='Complete List_09252026'!L126 -> Castro/Upper Market, Downtown/Civic Center, Mission, South of Market, Western Addition
A27: Union Square Alliance (Union Square Business Improvement District) | B27: ='Complete List_09252026'!C299 -> Lisa Frisch | C27: ='Complete List_09252026'!E299 -> 291 Gearu Street, Suite 200 | D27: ='Complete List_09252026'!F299 -> San Francisco | E27: ='Complete List_09252026'!G299 -> CA | F27: ='Complete List_09252026'!H299 -> 94102 | G27: ='Complete List_09252026'!J299 -> info@unionsquarebid.com | H27: ='Complete List_09252026'!K299 -> Electronic | I27: ='Complete List_09252026'!L299 -> Downtown/Civic Center
A28: Both Sides of the Conversation | B28: Jon Henry | C28: P.O. Box 347518 | D28: San Francisco | E28: CA | F28: 94134 | G28: jonhenry@bsotc.org | H28: Electronic | I28: Bayview, Bernal Heights, Crocker Amazon, Downtown/Civic Center, Excelsior, Glen Park, Haight Ashbury, Potrero Hill, South of Market, Treasure Island, Visitacion Valley, West of Twin Peaks, Western Addition
A29: ='Complete List_09252026'!D53 -> Castro LGBTQ Cultural District | B29: ='Complete List_09252026'!C53 -> Jesse Sanford & Stephen Torres | C29: ='Complete List_09252026'!E53 -> 1800 Market Street | D29: ='Complete List_09252026'!F53 -> San Francisco | E29: ='Complete List_09252026'!G53 -> CA | F29: ='Complete List_09252026'!H53 -> 94102 | G29: ='Complete List_09252026'!J53 -> landuse@castrolgbtq.org | H29: ='Complete List_09252026'!K53 -> Electronic | I29: ='Complete List_09252026'!L53 -> Bernal Heights, Castro/Upper Market, Downtown/Civic Center, Mission, Noe Valley, South of Market
A30: ='Complete List_09252026'!D165 -> Lower Nob Hill Neighborhood Alliance | B30: ='Complete List_09252026'!C165 -> Thao Jones-Hill | C30: ='Complete List_09252026'!E165 -> 834 Jones Street, Unit B | D30: ='Complete List_09252026'!F165 -> San Francisco | E30: ='Complete List_09252026'!G165 -> CA | F30: ='Complete List_09252026'!H165 -> 94109 | G30: ='Complete List_09252026'!J165 -> ec@lowernobhill.org | H30: ='Complete List_09252026'!K165 -> Electronic | I30: ='Complete List_09252026'!L165 -> Downtown/Civic Center, Nob Hill
A31: ='Complete List_09252026'!D177 -> Mid-Market Neighbors | B31: ='Complete List_09252026'!C177 -> Chuck Obermeyer | C31: ='Complete List_09252026'!E177 -> 30 7th Street | D31: ='Complete List_09252026'!F177 -> San Francisco | E31: ='Complete List_09252026'!G177 -> CA | F31: ='Complete List_09252026'!H177 -> 94103 | G31: ='Complete List_09252026'!J177 -> chuck@midmarketneighbors.org | H31: ='Complete List_09252026'!K177 -> Electronic | I31: ='Complete List_09252026'!L177 -> Castro/Upper Market, Chinatown, Downtown/Civic Center, Financial District, Nob Hill, Potrero Hill, South of Market, Western Addition
A32: ='Complete List_09252026'!D154 -> Liberation Alliance for Economic and Social Change | B32: ='Complete List_09252026'!C154 -> Keith Pavlik | C32: ='Complete List_09252026'!E154 -> 2969 Mission Street | D32: ='Complete List_09252026'!F154 -> San Francisco | E32: ='Complete List_09252026'!G154 -> CA | F32: ='Complete List_09252026'!H154 -> 94110 | G32: ='Complete List_09252026'!J154 -> info@liberationalliance.org | H32: ='Complete List_09252026'!K154 -> Electronic | I32: ='Complete List_09252026'!L154 -> Bayview, Bernal Heights, Castro/Upper Market, Chinatown, Downtown/Civic Center, Excelsior, Mission, Nob Hill, Noe Valley, Outer Mission, Potrero Hill, South of Market, Western Addition
A33: ='Complete List_09252026'!D288 -> Tenderloin Land Use Committee | B33: ='Complete List_09252026'!C288 -> Erick Arguello | C33: ='Complete List_09252026'!E288 -> 330 Ellis Street | D33: ='Complete List_09252026'!F288 -> San Francisco | E33: ='Complete List_09252026'!G288 -> CA | F33: ='Complete List_09252026'!H288 -> 94102 | G33: ='Complete List_09252026'!J288 -> earguello@glide.org | H33: ='Complete List_09252026'!K288 -> Electronic | I33: ='Complete List_09252026'!L288 -> Downtown / Civic Center
A34: San Franciscans for Reasonable Growth (SFRG) | B34: ='Complete List_09252026'!C244 -> Sue Hestor | C34: ='Complete List_09252026'!E244 -> 329 Highland Ave | D34: ='Complete List_09252026'!F244 -> San Francisco | E34: ='Complete List_09252026'!G244 -> CA | F34: ='Complete List_09252026'!H244 -> 94110 | G34: ='Complete List_09252026'!J244 -> hestor@earthlink.net | H34: Electronic | I34: ='Complete List_09252026'!L244 -> Bernal Heights, Chinatown, Downtown/Civic Center, Mission

Sheet Excelsior
A1: ORGANIZATION | B1: ='Complete List_09252026'!C1 -> NAME | C1: ='Complete List_09252026'!E1 -> ADDRESS | D1: ='Complete List_09252026'!F1 -> CITY | E1: ='Complete List_09252026'!G1 -> STATE | F1: ='Complete List_09252026'!H1 -> ZIP | G1: ='Complete List_09252026'!J1 -> EMAIL | H1: NOTIFICATION PREFERENCES | I1: ='Complete List_09252026'!L1 -> NEIGHBORHOOD OF INTEREST
A2: PHYSICAL NOTICES
A3: Excelsior District Improvement Association | B3: ='Complete List_09252026'!C98 -> Mel Flores | C3: ='Complete List_09252026'!E98 -> P.O. Box 12005 | D3: ='Complete List_09252026'!F98 -> San Francisco | E3: ='Complete List_09252026'!G98 -> CA | F3: ='Complete List_09252026'!H98 -> 94112 | G3: ='Complete List_09252026'!J98 -> melfloressf@gmail.com | H3: ='Complete List_09252026'!K98 -> Physical | I3: ='Complete List_09252026'!L98 -> Crocker Amazon, Excelsior, Ocean View, Outer Mission
A4: People Organizing to Demand Environmental and Economic Rights (PODER) | B4: ='Complete List_09252026'!C228 -> Antonio Diaz | C4: ='Complete List_09252026'!E228 -> 474 Valencia Street #125 | D4: ='Complete List_09252026'!F228 -> San Francisco | E4: ='Complete List_09252026'!G228 -> CA | F4: ='Complete List_09252026'!H228 -> 94103 | G4: ='Complete List_09252026'!J228 -> info@podersf.org | H4: ='Complete List_09252026'!K228 -> Physical | I4: ='Complete List_09252026'!L228 -> Crocker Amazon, Excelsior, Mission, Ocean View, Outer Mission, South of Market
A5: Sherwin Williams | B5: ='Complete List_09252026'!C261 -> Francesca Panullo | C5: ='Complete List_09252026'!E261 -> 1415 Ocean Ave | D5: ='Complete List_09252026'!F261 -> San Francisco | E5: ='Complete List_09252026'!G261 -> CA | F5: ='Complete List_09252026'!H261 -> 94112 | G5: ='Complete List_09252026'!J261 -> sw8644@sherwin.com | H5: ='Complete List_09252026'!K261 -> Physical | I5: ='Complete List_09252026'!L261 -> Bayview, Bernal Heights, Crocker Amazon, Diamond Heights, Excelsior, Glen Park, Inner Sunset, Lakeshore, Noe Valley, Ocean View, Outer Mission, Outer Sunset, Parkside, Potrero Hill, South Bayshore, Twin Peaks, Visitacion Valley, West of Twin Peaks
A6: New Mission Terrace Improvement Association (NMTIA) | B6: ='Complete List_09252026'!C197 -> David Hooper | C6: ='Complete List_09252026'!E197 -> P.O. Box 12111 | D6: ='Complete List_09252026'!F197 -> San Francisco | E6: ='Complete List_09252026'!G197 -> CA | F6: ='Complete List_09252026'!H197 -> 94112 | G6: ='Complete List_09252026'!J197 -> nmtiasf@gmail.com | H6: ='Complete List_09252026'!K197 -> Physical | I6: ='Complete List_09252026'!L197 -> Crocker Amazon, Excelsior, Glen Park, Outer Mission,
A7: Outer Mission Residents Association | B7: ='Complete List_09252026'!C221 -> Joelle Kenealey | C7: ='Complete List_09252026'!E221 -> P. O. Box 34426 | D7: ='Complete List_09252026'!F221 -> San Francisco | E7: ='Complete List_09252026'!G221 -> CA | F7: ='Complete List_09252026'!H221 -> 94134 | G7: ='Complete List_09252026'!J221 -> sfommra@gmail.com | H7: ='Complete List_09252026'!K221 -> Physical | I7: ='Complete List_09252026'!L221 -> Excelsior, Outer Mission, Crocker Amazon, Visitacion Valley
A8: BOTH PHYSICAL & ELECTRONIC NOTICES
A9: Board of Supervisors | B9: ='Complete List_09252026'!C37 -> Chyanne Chen | C9: ='Complete List_09252026'!E37 -> 1 Dr. Carlton B Goodlett Place, Room #244 | D9: ='Complete List_09252026'!F37 -> San Francisco | E9: ='Complete List_09252026'!G37 -> CA | F9: ='Complete List_09252026'!H37 -> 94102-4689 | G9: ='Complete List_09252026'!J37 -> ChenStaff@sfgov.org; Charlie.Sciammas@sfgov.org | H9: ='Complete List_09252026'!K37 -> Both | I9: ='Complete List_09252026'!L37 -> Crocker Amazon, Excelsior, Outer Mission, Visitacion Valley
A10: ='Complete List_09252026'!D44 -> Board of Supervisors | B10: ='Complete List_09252026'!C44 -> Jackie Fielder | C10: ='Complete List_09252026'!E44 -> 1 Dr. Carlton B Goodlett Place, Room #244 | D10: ='Complete List_09252026'!F44 -> San Francisco | E10: ='Complete List_09252026'!G44 -> CA | F10: ='Complete List_09252026'!H44 -> 94102-4689 | G10: ='Complete List_09252026'!J44 -> FielderStaff@sfgov.org; Ana.Herrera@sfgov.org; Preston.Kilgore@sfgov.org | H10: ='Complete List_09252026'!K44 -> Both | I10: ='Complete List_09252026'!L44 -> Bernal Heights, Excelsior, Mission, Visitacion Valley
A11: ELECTRONIC NOTICES
A12: Excelsior Action Group | B12: ='Complete List_09252026'!C97 -> Maribel Ramirez | C12: ='Complete List_09252026'!E97 -> 35 San Juan Ave | D12: ='Complete List_09252026'!F97 -> San Francisco | E12: ='Complete List_09252026'!G97 -> CA | F12: ='Complete List_09252026'!H97 -> 94112 | G12: ='Complete List_09252026'!J97 -> maribel@eagsf.org | H12: ='Complete List_09252026'!K97 -> Electronic | I12: ='Complete List_09252026'!L97 -> Excelsior
A13: Cayuga Improvement Association | B13: ='Complete List_09252026'!C57 -> CNIA President | C13: ='Complete List_09252026'!E57 -> 311 Foote Ave | D13: ='Complete List_09252026'!F57 -> San Francisco | E13: ='Complete List_09252026'!G57 -> CA | F13: ='Complete List_09252026'!H57 -> 94112 | G13: ='Complete List_09252026'!J57 -> cayugaimprovement@gmail.com | H13: ='Complete List_09252026'!K57 -> Electronic | I13: ='Complete List_09252026'!L57 -> Excelsior, Outer Mission
A14: Friends of the Havelock Street Bridge | B14: ='Complete List_09252026'!C108 -> C. Weibel | C14: ='Complete List_09252026'!E108 -> 0 | D14: ='Complete List_09252026'!F108 -> 0 | E14: ='Complete List_09252026'!G108 -> 0 | F14: ='Complete List_09252026'!H108 -> 0 | G14: ='Complete List_09252026'!J108 -> havelockstreetbridge@gmail.com | H14: ='Complete List_09252026'!K108 -> Electronic | I14: ='Complete List_09252026'!L108 -> Excelsior, Outer Mission
A15: Mission Economic Development Association | B15: ='Complete List_09252026'!C185 -> Jessica Rubio | C15: ='Complete List_09252026'!E185 -> 2301 Mission Street #301 | D15: ='Complete List_09252026'!F185 -> San Francisco | E15: ='Complete List_09252026'!G185 -> CA | F15: ='Complete List_09252026'!H185 -> 94110 | G15: ='Complete List_09252026'!J185 -> jrubio@medasf.org | H15: ='Complete List_09252026'!K185 -> Electronic | I15: ='Complete List_09252026'!L185 -> Excelsior, Mission, Outer Mission
A16: Portola Neighborhood Association | B16: ='Complete List_09252026'!C230 -> Maggie Weis | C16: ='Complete List_09252026'!E230 -> 2555 San Bruno Avenue | D16: ='Complete List_09252026'!F230 -> San Francisco | E16: ='Complete List_09252026'!G230 -> CA | F16: ='Complete List_09252026'!H230 -> 94134 | G16: ='Complete List_09252026'!J230 -> hello@portolasf.org | H16: ='Complete List_09252026'!K230 -> Electronic | I16: ='Complete List_09252026'!L230 -> Excelsior
A17: Both Sides of the Conversation | B17: Jon Henry | C17: P.O. Box 347518 | D17: San Francisco | E17: CA | F17: 94134 | G17: jonhenry@bsotc.org | H17: Electronic | I17: Bayview, Bernal Heights, Crocker Amazon, Downtown/Civic Center, Excelsior, Glen Park, Haight Ashbury, Potrero Hill, South of Market, Treasure Island, Visitacion Valley, West of Twin Peaks, Western Addition
A18: ='Complete List_09252026'!D154 -> Liberation Alliance for Economic and Social Change | B18: ='Complete List_09252026'!C154 -> Keith Pavlik | C18: ='Complete List_09252026'!E154 -> 2969 Mission Street | D18: ='Complete List_09252026'!F154 -> San Francisco | E18: ='Complete List_09252026'!G154 -> CA | F18: ='Complete List_09252026'!H154 -> 94110 | G18: ='Complete List_09252026'!J154 -> info@liberationalliance.org | H18: ='Complete List_09252026'!K154 -> Electronic | I18: ='Complete List_09252026'!L154 -> Bayview, Bernal Heights, Castro/Upper Market, Chinatown, Downtown/Civic Center, Excelsior, Mission, Nob Hill, Noe Valley, Outer Mission, Potrero Hill, South of Market, Western Addition
A19: ='Complete List_09252026'!D216 -> OMI Cultural Participation Project | B19: ='Complete List_09252026'!C216 -> Maurice Rivers | C19: ='Complete List_09252026'!E216 -> P.O. Box 12263 | D19: ='Complete List_09252026'!F216 -> San Francisco | E19: ='Complete List_09252026'!G216 -> CA | F19: ='Complete List_09252026'!H216 -> 94112 | G19: ='Complete List_09252026'!J216 -> jumpstreet1983@gmail.com | H19: ='Complete List_09252026'!K216 -> Electronic | I19: ='Complete List_09252026'!L216 -> Crocker Amazon, Excelsior, Ocean View, Outer Mission
A20: ='Complete List_09252026'!D33 -> Better Housing Policies | B20: ='Complete List_09252026'!C33 -> Josephine Zhao | C20: ='Complete List_09252026'!E33 -> 945 Taraval Street | D20: ='Complete List_09252026'!F33 -> San Francisco | E20: ='Complete List_09252026'!G33 -> CA | F20: ='Complete List_09252026'!H33 -> 94116 | G20: ='Complete List_09252026'!J33 -> info@betterhousingpolicies.org | H20: ='Complete List_09252026'!K33 -> Electronic | I20: ='Complete List_09252026'!L33 -> Excelsior, Outer Richmond, Outer Sunset, Parkside, Visitacion Valley
A21: OneBayview | B21: ='Complete List_09252026'!C217 -> Anietie Ekanem | C21: ='Complete List_09252026'!E217 -> 5800 3rd Street #1320 | D21: ='Complete List_09252026'!F217 -> San Francisco | E21: ='Complete List_09252026'!G217 -> CA | F21: ='Complete List_09252026'!H217 -> 94124 | G21: ='Complete List_09252026'!J217 -> sfplanningdepartment@onebayview.com aekanem@onebayview.com | H21: ='Complete List_09252026'!K217 -> Electronic | I21: ='Complete List_09252026'!L217 -> Bayview, Crocker Amazon, Excelsior, Ocean View, Potrero Hill, Visitacion Valley
A22: ='Complete List_09252026'!D146 -> Keep Crocker Real | B22: ='Complete List_09252026'!C146 -> KC Real | C22: ='Complete List_09252026'!E146 -> 0 | D22: ='Complete List_09252026'!F146 -> San Francisco | E22: ='Complete List_09252026'!G146 -> CA | F22: ='Complete List_09252026'!H146 -> 94112 | G22: ='Complete List_09252026'!J146 -> hello@keepcrockerreal.com | H22: ='Complete List_09252026'!K146 -> Electronic | I22: ='Complete List_09252026'!L146 -> Bayview, Crocker Amazon, Excelsior, Glen Park, Outer Mission, Visitacion Valley

Sheet Financial District
A1: ORGANIZATION | B1: ='Complete List_09252026'!C1 -> NAME | C1: ='Complete List_09252026'!E1 -> ADDRESS | D1: ='Complete List_09252026'!F1 -> CITY | E1: ='Complete List_09252026'!G1 -> STATE | F1: ='Complete List_09252026'!H1 -> ZIP | G1: ='Complete List_09252026'!J1 -> EMAIL | H1: NOTIFICATION PREFERENCES | I1: ='Complete List_09252026'!L1 -> NEIGHBORHOOD OF INTEREST
A2: PHYSICAL NOTICES
A3: 874 Sacramento Street Tenants Association | B3: ='Complete List_09252026'!C10 -> Jeffrey Kwong | C3: ='Complete List_09252026'!E10 -> 1754 Hyde Street | D3: ='Complete List_09252026'!F10 -> San Francisco | E3: ='Complete List_09252026'!G10 -> CA | F3: ='Complete List_09252026'!H10 -> 94106 | G3: ='Complete List_09252026'!J10 -> cardinalsf@gmail.com | H3: ='Complete List_09252026'!K10 -> Physical | I3: ='Complete List_09252026'!L10 -> Chinatown, Downtown Civic Center, Financial District, Nob Hill, North Beach
A4: Hotel Zeppelin | B4: ='Complete List_09252026'!C131 -> Antonio Flores | C4: ='Complete List_09252026'!E131 -> 545 Post Street | D4: ='Complete List_09252026'!F131 -> San Francisco | E4: ='Complete List_09252026'!G131 -> CA | F4: ='Complete List_09252026'!H131 -> 94102 | G4: ='Complete List_09252026'!J131 -> antonio.flores@viceroyhotelgroup.com | H4: ='Complete List_09252026'!K131 -> Physical | I4: ='Complete List_09252026'!L131 -> Castro/Upper Market, Chinatown, Downtown/Civic Center, Financial District, Nob Hill, North Beach, South of Market, Treasure Island
A5: Jackson Square Historic District Assn. | B5: ='Complete List_09252026'!C139 -> Sarah Stocking | C5: ='Complete List_09252026'!E139 -> 368 Jackson Street | D5: ='Complete List_09252026'!F139 -> San Francisco | E5: ='Complete List_09252026'!G139 -> CA | F5: ='Complete List_09252026'!H139 -> 94111 | G5: ='Complete List_09252026'!J139 -> sarah@sarahstocking.com | H5: ='Complete List_09252026'!K139 -> Physical | I5: ='Complete List_09252026'!L139 -> Chinatown, Financial District, North Beach
A6: One Ecker Owners Association | B6: ='Complete List_09252026'!C218 -> Ethan Hough | C6: ='Complete List_09252026'!E218 -> 16 Jessie Street Unit 301 | D6: ='Complete List_09252026'!F218 -> San Francisco | E6: ='Complete List_09252026'!G218 -> CA | F6: ='Complete List_09252026'!H218 -> 94105 | G6: ='Complete List_09252026'!J218 -> ethanhough@gmail.com | H6: ='Complete List_09252026'!K218 -> Physical | I6: ='Complete List_09252026'!L218 -> Financial District, South of Market
A7: SF CityWide | B7: ='Complete List_09252026'!C251 -> David Lal | C7: ='Complete List_09252026'!E251 -> 142 S. Van Ness Ave | D7: ='Complete List_09252026'!F251 -> San Francisco | E7: ='Complete List_09252026'!G251 -> CA | F7: ='Complete List_09252026'!H251 -> 94103 | G7: ='Complete List_09252026'!J251 -> info@sfcitywide.org | H7: ='Complete List_09252026'!K251 -> Physical | I7: ='Complete List_09252026'!L251 -> Downtown/Civic Center, Financial District, South of Market, Treasure Island
A8: St. Vincent de Paul Society, North Beach | B8: ='Complete List_09252026'!C283 -> Marc Bruno | C8: ='Complete List_09252026'!E283 -> 666 Filbert Street | D8: ='Complete List_09252026'!F283 -> San Francisco | E8: ='Complete List_09252026'!G283 -> CA | F8: ='Complete List_09252026'!H283 -> 94133 | G8: ='Complete List_09252026'!J283 -> marcabruno@yahoo.com | H8: ='Complete List_09252026'!K283 -> Physical | I8: ='Complete List_09252026'!L283 -> Chinatown, Financial District, Nob Hill, North Beach, Russian Hill
A9: TJPA CAC | B9: ='Complete List_09252026'!C293 -> Anna Harvey | C9: ='Complete List_09252026'!E293 -> 425 Mission Street, Suite 250 | D9: ='Complete List_09252026'!F293 -> San Francisco | E9: ='Complete List_09252026'!G293 -> CA | F9: ='Complete List_09252026'!H293 -> 94105 | G9: ='Complete List_09252026'!J293 -> aharvey@tjpa.org lmadjuswu@tjpa.org | H9: ='Complete List_09252026'!K293 -> Electronic | I9: ='Complete List_09252026'!L293 -> Financial District, South of Market
A10: Alliance for a Better District 6 | B10: ='Complete List_09252026'!C14 -> Michael Nulty | C10: ='Complete List_09252026'!E14 -> P.O. Box 420782 | D10: ='Complete List_09252026'!F14 -> San Francisco | E10: ='Complete List_09252026'!G14 -> CA | F10: ='Complete List_09252026'!H14 -> 94142 | G10: ='Complete List_09252026'!J14 -> sf_district6@yahoo.com | H10: ='Complete List_09252026'!K14 -> Physical | I10: ='Complete List_09252026'!L14 -> Downtown/Civic Center, Financial District, Mission, Nob Hill, South of Market, Treasure Island, Western Addition
A11: BOTH PHYSICAL & ELECTRONIC NOTICES
A12: Board of Supervisors | B12: ='Complete List_09252026'!C36 -> Danny Sauter | C12: ='Complete List_09252026'!E36 -> 1 Dr. Carlton B Goodlett Place, Room #244 | D12: ='Complete List_09252026'!F36 -> San Francisco | E12: ='Complete List_09252026'!G36 -> CA | F12: ='Complete List_09252026'!H36 -> 94102-4689 | G12: ='Complete List_09252026'!J36 -> SauterStaff@sfgov.org; Michelle.Andrews@sfgov.org; Amy.Lee5@sfgov.org; tita.bell@sfgov.org; tomio.nagano@sfgov.org | H12: ='Complete List_09252026'!K36 -> Both | I12: ='Complete List_09252026'!L36 -> Chinatown, Financial District, Nob Hill, North Beach, Russian Hill
A13: ELECTRONIC NOTICES
A14: Barbary Coast Neighborhood Association | B14: ='Complete List_09252026'!C23 -> Diana Taylor | C14: ='Complete List_09252026'!E23 -> P.O. Box 2045 | D14: ='Complete List_09252026'!F23 -> San Francisco | E14: ='Complete List_09252026'!G23 -> CA | F14: ='Complete List_09252026'!H23 -> 94126 | G14: ='Complete List_09252026'!J23 -> bcna@bcnasf.org | H14: ='Complete List_09252026'!K23 -> Electronic | I14: ='Complete List_09252026'!L23 -> Financial District, North Beach
A15: Gateway Tenants Association | B15: ='Complete List_09252026'!C115 -> Alec Bash | C15: ='Complete List_09252026'!E115 -> 155 Jackson Street Apt. 2501 | D15: ='Complete List_09252026'!F115 -> San Francisco | E15: ='Complete List_09252026'!G115 -> CA | F15: ='Complete List_09252026'!H115 -> 94111 | G15: ='Complete List_09252026'!J115 -> alec.bash@gmail.com | H15: ='Complete List_09252026'!K115 -> Electronic | I15: ='Complete List_09252026'!L115 -> Financial District, North Beach
A16: North Beach Neighbors | B16: ='Complete List_09252026'!C205 -> Danny Sauter | C16: ='Complete List_09252026'!E205 -> P.O. Box 330115 | D16: ='Complete List_09252026'!F205 -> San Francisco | E16: ='Complete List_09252026'!G205 -> CA | F16: ='Complete List_09252026'!H205 -> 94133 | G16: ='Complete List_09252026'!J205 -> northbeachneighbors@ymail.com | H16: ='Complete List_09252026'!K205 -> Electronic | I16: ='Complete List_09252026'!L205 -> Chinatown, Financial District, Nob Hill, North Beach, Russian Hill
A17: ='Complete List_09252026'!D203 -> Northeast San Francisco Conservancy | B17: ='Complete List_09252026'!C285 -> Nancy Shanahan | C17: ='Complete List_09252026'!E203 -> 224 Filbert Street | D17: ='Complete List_09252026'!F203 -> San Francisco | E17: ='Complete List_09252026'!G203 -> CA | F17: ='Complete List_09252026'!H203 -> 94133 | G17: ='Complete List_09252026'!J203 -> nshan@mindspring.com | H17: ='Complete List_09252026'!K203 -> Electronic | I17: ='Complete List_09252026'!L203 -> Chinatown, Financial District, North Beach, Russian Hill
A18: Chinatown Community Development Center (CCDC) | B18: ='Complete List_09252026'!C59 -> Malcom Yeung | C18: ='Complete List_09252026'!E59 -> 615 Grant Avenue | D18: ='Complete List_09252026'!F59 -> San Francisco | E18: ='Complete List_09252026'!G59 -> CA | F18: ='Complete List_09252026'!H59 -> 94133 | G18: ='Complete List_09252026'!J59 -> myeung@chinatowncdc.org; matthias.mormino@chinatowncdc.org; sharon.ng@chinatowncdc.org; tandchow@gmail.com; | H18: ='Complete List_09252026'!K59 -> Electronic | I18: ='Complete List_09252026'!L59 -> Chinatown, Financial District, Nob Hill, North Beach, Russian Hill
A19: ='Complete List_09252026'!D285 -> Telegraph Hill Dwellers - Planning & Zoning Committee | B19: ='Complete List_09252026'!C285 -> Nancy Shanahan | C19: ='Complete List_09252026'!E285 -> 470 Columbus Ave. #211 | D19: ='Complete List_09252026'!F285 -> San Francisco | E19: ='Complete List_09252026'!G285 -> CA | F19: ='Complete List_09252026'!H285 -> 94133 | G19: ='Complete List_09252026'!J285 -> pz@thd.org | H19: ='Complete List_09252026'!K285 -> Electronic | I19: ='Complete List_09252026'!L285 -> North Beach, Financial District
A20: ='Complete List_09252026'!D284 -> Telegraph Hill Dwellers | B20: ='Complete List_09252026'!C284 -> Al Fontes | C20: ='Complete List_09252026'!E284 -> P.O. Box 330159 | D20: ='Complete List_09252026'!F284 -> San Francisco | E20: ='Complete List_09252026'!G284 -> CA | F20: ='Complete List_09252026'!H284 -> 94133 | G20: ='Complete List_09252026'!J284 -> president@thd.org | H20: ='Complete List_09252026'!K284 -> Electronic | I20: ='Complete List_09252026'!L284 -> North Beach, Financial District
A21: ='Complete List_09252026'!D210 -> Northern Neighbors | C21: ='Complete List_09252026'!E210 -> 2655 Bush St. Apt. 303 | D21: ='Complete List_09252026'!F210 -> San Francisco | E21: ='Complete List_09252026'!G210 -> CA | F21: ='Complete List_09252026'!H210 -> 94115 | G21: ='Complete List_09252026'!J210 -> hello@northernneighbors.org | H21: ='Complete List_09252026'!K210 -> Electronic | I21: ='Complete List_09252026'!L210 -> Chinatown, Financial District, Nob Hill, North Beach, Pacific Heights, Presidio, Presidio Heights, Russian Hill, Seacliff
A22: ='Complete List_09252026'!D177 -> Mid-Market Neighbors | B22: ='Complete List_09252026'!C177 -> Chuck Obermeyer | C22: ='Complete List_09252026'!E177 -> 30 7th Street | D22: ='Complete List_09252026'!F177 -> San Francisco | E22: ='Complete List_09252026'!G177 -> CA | F22: ='Complete List_09252026'!H177 -> 94103 | G22: ='Complete List_09252026'!J177 -> chuck@midmarketneighbors.org | H22: ='Complete List_09252026'!K177 -> Electronic | I22: ='Complete List_09252026'!L177 -> Castro/Upper Market, Chinatown, Downtown/Civic Center, Financial District, Nob Hill, Potrero Hill, South of Market, Western Addition

Sheet Glen Park
A1: ORGANIZATION | B1: ='Complete List_09252026'!C1 -> NAME | C1: ='Complete List_09252026'!E1 -> ADDRESS | D1: ='Complete List_09252026'!F1 -> CITY | E1: ='Complete List_09252026'!G1 -> STATE | F1: ='Complete List_09252026'!H1 -> ZIP | G1: ='Complete List_09252026'!J1 -> EMAIL | H1: NOTIFICATION PREFERENCES | I1: ='Complete List_09252026'!L1 -> NEIGHBORHOOD OF INTEREST
A2: PHYSICAL NOTICES
A3: Sherwin Williams | B3: ='Complete List_09252026'!C261 -> Francesca Panullo | C3: ='Complete List_09252026'!E261 -> 1415 Ocean Ave | D3: ='Complete List_09252026'!F261 -> San Francisco | E3: ='Complete List_09252026'!G261 -> CA | F3: ='Complete List_09252026'!H261 -> 94112 | G3: ='Complete List_09252026'!J261 -> sw8644@sherwin.com | H3: ='Complete List_09252026'!K261 -> Physical | I3: ='Complete List_09252026'!L261 -> Bayview, Bernal Heights, Crocker Amazon, Diamond Heights, Excelsior, Glen Park, Inner Sunset, Lakeshore, Noe Valley, Ocean View, Outer Mission, Outer Sunset, Parkside, Potrero Hill, South Bayshore, Twin Peaks, Visitacion Valley, West of Twin Peaks
A4: New Mission Terrace Improvement Association (NMTIA) | B4: ='Complete List_09252026'!C197 -> David Hooper | C4: ='Complete List_09252026'!E197 -> P.O. Box 12111 | D4: ='Complete List_09252026'!F197 -> San Francisco | E4: ='Complete List_09252026'!G197 -> CA | F4: ='Complete List_09252026'!H197 -> 94112 | G4: ='Complete List_09252026'!J197 -> nmtiasf@gmail.com | H4: ='Complete List_09252026'!K197 -> Physical | I4: ='Complete List_09252026'!L197 -> Crocker Amazon, Excelsior, Glen Park, Outer Mission,
A5: BOTH PHYSICAL & ELECTRONIC NOTICES
A6: Board of Supervisors | B6: ='Complete List_09252026'!C38 -> Rafael Mandelman | C6: ='Complete List_09252026'!E38 -> 1 Dr. Carlton B Goodlett Place, Room #244 | D6: ='Complete List_09252026'!F38 -> San Francisco | E6: ='Complete List_09252026'!G38 -> CA | F6: ='Complete List_09252026'!H38 -> 94102-4689 | G6: ='Complete List_09252026'!J38 -> Rafael.Mandelman@sfgov.org; Kyle.Smeallie@sfgov.org; Tom.Temprano@sfgov.org; jacob.bintliff@sfgov.org; mandelmanstaff@sfgov.org | H6: ='Complete List_09252026'!K38 -> Both | I6: ='Complete List_09252026'!L38 -> Castro/Upper Market, Diamond Heights, Glen Park, Noe Valley, Twin Peaks
A7: ELECTRONIC NOTICES
A8: Bernal Cut Neighborhood Alliace | B8: ='Complete List_09252026'!C27 -> Sophie Constantinou | C8: ='Complete List_09252026'!E27 -> 22 Richland Avenue | D8: ='Complete List_09252026'!F27 -> San Francisco | E8: ='Complete List_09252026'!G27 -> CA | F8: ='Complete List_09252026'!H27 -> 94110 | G8: ='Complete List_09252026'!J27 -> bernalcutpath@gmail.com | H8: ='Complete List_09252026'!K27 -> Electronic | I8: ='Complete List_09252026'!L27 -> Bernal Heights, Glen Park
A9: Diamond Heights Community Association | B9: ='Complete List_09252026'!C79 -> Daniel Schereck | C9: ='Complete List_09252026'!E79 -> P.O. Box 31529 | D9: ='Complete List_09252026'!F79 -> San Francisco | E9: ='Complete List_09252026'!G79 -> CA | F9: ='Complete List_09252026'!H79 -> 94131 | G9: ='Complete List_09252026'!J79 -> dhcasf@gmail.com | H9: ='Complete List_09252026'!K79 -> Electronic | I9: ='Complete List_09252026'!L79 -> Diamond Heights, Glen Park, Noe Valley
A10: Diamond Heights Homeowners Association (DHHOA) | B10: ='Complete List_09252026'!C80 -> Carey Rutigliano | C10: ='Complete List_09252026'!E80 -> 108 Everson Street | D10: ='Complete List_09252026'!F80 -> San Francisco | E10: ='Complete List_09252026'!G80 -> CA | F10: ='Complete List_09252026'!H80 -> 94131 | G10: ='Complete List_09252026'!J80 -> careyruttig@yahoo.com | H10: ='Complete List_09252026'!K80 -> Electronic | I10: ='Complete List_09252026'!L80 -> Diamond Heights, Glen Park
A11: Glen Park Association | B11: ='Complete List_09252026'!C111 | C11: ='Complete List_09252026'!E111 -> P.O. Box 31292 | D11: ='Complete List_09252026'!F111 -> San Francisco | E11: ='Complete List_09252026'!G111 -> CA | F11: ='Complete List_09252026'!H111 -> 94131 | G11: ='Complete List_09252026'!J111 -> president@glenparkassociation.org; info@glenparkassociation.org | H11: ='Complete List_09252026'!K111 -> Electronic | I11: ='Complete List_09252026'!L111 -> Glen Park
A12: Glen Park Urbanists | B12: ='Complete List_09252026'!C112 | C12: ='Complete List_09252026'!E112 -> 556 Laidley Street, Unit G | D12: ='Complete List_09252026'!F112 -> San Francisco | E12: ='Complete List_09252026'!G112 -> CA | F12: ='Complete List_09252026'!H112 -> 94131 | G12: ='Complete List_09252026'!J112 -> glenparkurbanists@gmail.com | H12: ='Complete List_09252026'!K112 -> Electronic | I12: ='Complete List_09252026'!L112 -> Glen Park
A13: San Francisco Land Use Coalition (SFLUC) | B13: ='Complete List_09252026'!C255 -> Gary Weiss | C13: ='Complete List_09252026'!E255 -> 78 Mars Street | D13: ='Complete List_09252026'!F255 -> San Francisco | E13: ='Complete List_09252026'!G255 -> CA | F13: ='Complete List_09252026'!H255 -> 94114 | G13: ='Complete List_09252026'!J255 -> garysfx@gmail.com | H13: ='Complete List_09252026'!K255 -> Electronic | I13: ='Complete List_09252026'!L255 -> Castro/Upper Market, Diamond Heights, Glen Park, Haight Ashbury, Mission, Noe Valley, South of Market, Twin Peaks, Upper Market, Western Addition
A14: Both Sides of the Conversation | B14: Jon Henry | C14: P.O. Box 347518 | D14: San Francisco | E14: CA | F14: 94134 | G14: jonhenry@bsotc.org | H14: Electronic | I14: Bayview, Bernal Heights, Crocker Amazon, Downtown/Civic Center, Excelsior, Glen Park, Haight Ashbury, Potrero Hill, South of Market, Treasure Island, Visitacion Valley, West of Twin Peaks, Western Addition
A15: ='Complete List_09252026'!D146 -> Keep Crocker Real | B15: ='Complete List_09252026'!C146 -> KC Real | C15: ='Complete List_09252026'!E146 -> 0 | D15: ='Complete List_09252026'!F146 -> San Francisco | E15: ='Complete List_09252026'!G146 -> CA | F15: ='Complete List_09252026'!H146 -> 94112 | G15: ='Complete List_09252026'!J146 -> hello@keepcrockerreal.com | H15: ='Complete List_09252026'!K146 -> Electronic | I15: ='Complete List_09252026'!L146 -> Bayview, Crocker Amazon, Excelsior, Glen Park, Outer Mission, Visitacion Valley

Sheet Golden Gate Park
A1: ORGANIZATION | B1: ='Complete List_09252026'!C1 -> NAME | C1: ='Complete List_09252026'!E1 -> ADDRESS | D1: ='Complete List_09252026'!F1 -> CITY | E1: ='Complete List_09252026'!G1 -> STATE | F1: ='Complete List_09252026'!H1 -> ZIP | G1: ='Complete List_09252026'!J1 -> EMAIL | H1: NOTIFICATION PREFERENCES | I1: ='Complete List_09252026'!L1 -> NEIGHBORHOOD OF INTEREST
A2: PHYSICAL NOTICES
A3: ='Complete List_09252026'!D122 -> Haight Ashbury Neighborhood Council | B3: ='Complete List_09252026'!C122 -> Land Use and Housing Chair | C3: ='Complete List_09252026'!E122 -> P.O. Box 170518 | D3: ='Complete List_09252026'!F122 -> San Francisco | E3: ='Complete List_09252026'!G122 -> CA | F3: ='Complete List_09252026'!H122 -> 94117 | G3: ='Complete List_09252026'!J122 -> info@hanc-sf.org | H3: ='Complete List_09252026'!K122 -> Physical | I3: ='Complete List_09252026'!L122 -> Haight Ashbury, Inner Sunset, Golden Gate Park
A4: ='Complete List_09252026'!D132 -> Housing Rights Committee of San Francisco | B4: ='Complete List_09252026'!C132 -> Sarah Sherburn-Zimmer | C4: ='Complete List_09252026'!E132 -> 1663 Mission Street, Suite 504 | D4: ='Complete List_09252026'!F132 -> San Francisco | E4: ='Complete List_09252026'!G132 -> CA | F4: ='Complete List_09252026'!H132 -> 94103 | G4: ='Complete List_09252026'!J132 -> fred@hrcsf.org | H4: ='Complete List_09252026'!K132 -> Physical | I4: ='Complete List_09252026'!L132 -> Golden Gate Park, Inner Richmond, Inner Sunset, Lakeshore, Outer Richmond, Outer Sunset, Parkside, West of Twin Peaks
A5: ELECTRONIC NOTICES
A6: ='Complete List_09252026'!D67 -> Coalition to Save Ocean Beach / Friends of Sutro Park | B6: ='Complete List_09252026'!C67 -> Jason Jungreis | C6: ='Complete List_09252026'!E67 -> 527 47th Avenue | D6: ='Complete List_09252026'!F67 -> San Francisco | E6: ='Complete List_09252026'!G67 -> CA | F6: ='Complete List_09252026'!H67 -> 94121 | G6: ='Complete List_09252026'!J67 -> jasonzjungreis@gmail.com | H6: ='Complete List_09252026'!K67 -> Electronic | I6: ='Complete List_09252026'!L67 -> Golden Gate Park, Outer Richmond, Seacliff
A7: ='Complete List_09252026'!D124 -> Haight Ashbury Panhandle Tenants Into Community (HAPTIC) | B7: ='Complete List_09252026'!C124 -> Nick Chapman | C7: ='Complete List_09252026'!E124 -> 1484 Page Street | D7: ='Complete List_09252026'!F124 -> San Francisco | E7: ='Complete List_09252026'!G124 -> CA | F7: ='Complete List_09252026'!H124 -> 94117 | G7: ='Complete List_09252026'!J124 -> sfhaptic@gmail.com | H7: ='Complete List_09252026'!K124 -> Electronic | I7: ='Complete List_09252026'!L124 -> Golden Gate Park, Haight Ashbury, Western Addition

Sheet Haight Ashbury
A1: ORGANIZATION | B1: ='Complete List_09252026'!C1 -> NAME | C1: ='Complete List_09252026'!E1 -> ADDRESS | D1: ='Complete List_09252026'!F1 -> CITY | E1: ='Complete List_09252026'!G1 -> STATE | F1: ='Complete List_09252026'!H1 -> ZIP | G1: ='Complete List_09252026'!J1 -> EMAIL | H1: NOTIFICATION PREFERENCES | I1: ='Complete List_09252026'!L1 -> NEIGHBORHOOD OF INTEREST
A2: PHYSICAL NOTICES
A3: ='Complete List_09252026'!D122 -> Haight Ashbury Neighborhood Council | B3: ='Complete List_09252026'!C122 -> Land Use and Housing Chair | C3: ='Complete List_09252026'!E122 -> P.O. Box 170518 | D3: ='Complete List_09252026'!F122 -> San Francisco | E3: ='Complete List_09252026'!G122 -> CA | F3: ='Complete List_09252026'!H122 -> 94117 | G3: ='Complete List_09252026'!J122 -> info@hanc-sf.org | H3: ='Complete List_09252026'!K122 -> Physical | I3: ='Complete List_09252026'!L122 -> Haight Ashbury, Inner Sunset, Golden Gate Park
A4: ='Complete List_09252026'!D123 -> Haight Ashbury Neighbors for Density (HAND) | B4: ='Complete List_09252026'!C123 -> Phillip Kobernick | C4: ='Complete List_09252026'!E123 -> 401 Cole Street | D4: ='Complete List_09252026'!F123 -> San Francisco | E4: ='Complete List_09252026'!G123 -> CA | F4: ='Complete List_09252026'!H123 -> 94117 | G4: ='Complete List_09252026'!J123 -> hand4sf@gmail.com | H4: ='Complete List_09252026'!K123 -> Physical | I4: ='Complete List_09252026'!L123 -> Haight Ashbury
A5: ='Complete List_09252026'!D202 -> NOPA West Neighbors (NOPAWN) | B5: ='Complete List_09252026'!C202 -> Henry Tang & Brian Kingan | C5: ='Complete List_09252026'!E202 -> 627 Masonic Avenue | D5: ='Complete List_09252026'!F202 -> San Francisco | E5: ='Complete List_09252026'!G202 -> CA | F5: ='Complete List_09252026'!H202 -> 94117 | G5: ='Complete List_09252026'!J202 -> nopawestneighbors@gmail.com | H5: ='Complete List_09252026'!K202 -> Physical | I5: ='Complete List_09252026'!L202 -> Haight Ashbury
A6: ='Complete List_09252026'!D4 -> - | B6: ='Complete List_09252026'!C4 -> Marianne Hesse | C6: ='Complete List_09252026'!E4 -> 101 Belvedere Street | D6: ='Complete List_09252026'!F4 -> San Francisco | E6: ='Complete List_09252026'!G4 -> CA | F6: ='Complete List_09252026'!H4 -> 94117 | G6: ='Complete List_09252026'!J4 -> mhesse@pacbell.net | H6: ='Complete List_09252026'!K4 -> Physical | I6: ='Complete List_09252026'!L4 -> Haight Ashbury
A7: ='Complete List_09252026'!D121 -> Haight Ashbury Improvement Association | B7: ='Complete List_09252026'!C121 -> Ted Loewenberg | C7: ='Complete List_09252026'!E121 -> P.O. Box 170098 | D7: ='Complete List_09252026'!F121 -> San Francisco | E7: ='Complete List_09252026'!G121 -> CA | F7: ='Complete List_09252026'!H121 -> 94117 | G7: ='Complete List_09252026'!J121 -> tedlsf@sbcglobal.net | H7: ='Complete List_09252026'!K121 -> Physical | I7: ='Complete List_09252026'!L121 -> Haight Ashbury
A8: ='Complete List_09252026'!D289 -> Temescal Terrace Association | B8: ='Complete List_09252026'!C289 -> Richard Rabbitt | C8: ='Complete List_09252026'!E289 -> 55 Temescal Terrace | D8: ='Complete List_09252026'!F289 -> San Francisco | E8: ='Complete List_09252026'!G289 -> CA | F8: ='Complete List_09252026'!H289 -> 94118 | G8: ='Complete List_09252026'!J289 -> richard.rabbitt@stanfordalumni.org | H8: ='Complete List_09252026'!K289 -> Physical | I8: ='Complete List_09252026'!L289 -> Haight Ashbury, Inner Richmond, Presidio Heights, Western Addition
A9: BOTH PHYSICAL & ELECTRONIC NOTICES
A10: ='Complete List_09252026'!D35 -> Board of Supervisors | B10: ='Complete List_09252026'!C35 -> Bilal Mahmood | C10: ='Complete List_09252026'!E35 -> 1 Dr. Carlton B Goodlett Place, Room #244 | D10: ='Complete List_09252026'!F35 -> San Francisco | E10: ='Complete List_09252026'!G35 -> CA | F10: ='Complete List_09252026'!H35 -> 94102-4689 | G10: ='Complete List_09252026'!J35 -> MahmoodStaff@sfgov.org; Raynell.Cooper@sfgov.org | H10: ='Complete List_09252026'!K35 -> Both | I10: ='Complete List_09252026'!L35 -> Downtown/Civic Center, Haight Ashbury, Western Addition
A11: ='Complete List_09252026'!D263 -> SIPS Review Group | B11: ='Complete List_09252026'!D263 -> SIPS Review Group | C11: ='Complete List_09252026'!E263 -> 62 Carmelita Street | D11: ='Complete List_09252026'!F263 -> San Francisco | E11: ='Complete List_09252026'!G263 -> CA | F11: ='Complete List_09252026'!H263 -> 94117 | G11: ='Complete List_09252026'!J263 -> pmmsfo@gmail.com | H11: ='Complete List_09252026'!K263 -> Both | I11: ='Complete List_09252026'!L263 -> Castro / Upper Market, Haight Ashbury, Western Addition
A12: ELECTRONIC NOTICES
A13: ='Complete List_09252026'!D55 -> Castro Upper Market Community Benefit District | B13: ='Complete List_09252026'!C55 -> Andrea Aiello | C13: ='Complete List_09252026'!E55 -> 693 14th Street | D13: ='Complete List_09252026'!F55 -> San Francisco | E13: ='Complete List_09252026'!G55 -> CA | F13: ='Complete List_09252026'!H55 -> 94114 | G13: ='Complete List_09252026'!J55 -> ExecDirector@CastroCBD.org | H13: ='Complete List_09252026'!K55 -> Electronic | I13: ='Complete List_09252026'!L55 -> Castro/Upper Market, Haight Ashbury, Noe Valley
A14: ='Complete List_09252026'!D68 -> Cole Valley Improvement Association | B14: ='Complete List_09252026'!C68 -> Carole Glosenger | C14: ='Complete List_09252026'!E68 -> P.O. Box 170611 | D14: ='Complete List_09252026'!F68 -> San Francisco | E14: ='Complete List_09252026'!G68 -> CA | F14: ='Complete List_09252026'!H68 -> 94117 | G14: ='Complete List_09252026'!J68 -> cviasf@aol.com | H14: ='Complete List_09252026'!K68 -> Electronic | I14: ='Complete List_09252026'!L68 -> Haight Ashbury
A15: ='Complete List_09252026'!D192 -> Mt. Olympus Neighbors Association | B15: ='Complete List_09252026'!C192 -> Dan Slaughter | C15: ='Complete List_09252026'!E192 -> 379 Upper Terrace | D15: ='Complete List_09252026'!F192 -> San Francisco | E15: ='Complete List_09252026'!G192 -> CA | F15: ='Complete List_09252026'!H192 -> 94117 | G15: ='Complete List_09252026'!J192 -> dkslaughter@gmail.com | H15: ='Complete List_09252026'!K192 -> Electronic | I15: ='Complete List_09252026'!L192 -> Castro/Upper Market, Haight Ashbury
A16: ='Complete List_09252026'!D209 -> North of Panhandle Neighborhood Association | B16: ='Complete List_09252026'!C209 -> Meg Rahner | C16: ='Complete List_09252026'!E209 -> 1936 McAllister Street, #1 | D16: ='Complete List_09252026'!F209 -> San Franicsco | E16: ='Complete List_09252026'!G209 -> CA | F16: ='Complete List_09252026'!H209 -> 94115 | G16: ='Complete List_09252026'!J209 -> board@nopna.org | H16: ='Complete List_09252026'!K209 -> Electronic | I16: ='Complete List_09252026'!L209 -> Haight Ashbury, Western Addition
A17: ='Complete List_09252026'!D255 -> San Francisco Land Use Coalition (SFLUC) | B17: ='Complete List_09252026'!C255 -> Gary Weiss | C17: ='Complete List_09252026'!E255 -> 78 Mars Street | D17: ='Complete List_09252026'!F255 -> San Francisco | E17: ='Complete List_09252026'!G255 -> CA | F17: ='Complete List_09252026'!H255 -> 94114 | G17: ='Complete List_09252026'!J255 -> garysfx@gmail.com | H17: ='Complete List_09252026'!K255 -> Electronic | I17: ='Complete List_09252026'!L255 -> Castro/Upper Market, Diamond Heights, Glen Park, Haight Ashbury, Mission, Noe Valley, South of Market, Twin Peaks, Upper Market, Western Addition
A18: Both Sides of the Conversation | B18: Jon Henry | C18: P.O. Box 347518 | D18: San Francisco | E18: CA | F18: 94134 | G18: jonhenry@bsotc.org | H18: Electronic | I18: Bayview, Bernal Heights, Crocker Amazon, Downtown/Civic Center, Excelsior, Glen Park, Haight Ashbury, Potrero Hill, South of Market, Treasure Island, Visitacion Valley, West of Twin Peaks, Western Addition
A19: ='Complete List_09252026'!D9 -> 318 Frederick St. Tenancy In Common Owner's Association and Board | B19: ='Complete List_09252026'!C9 -> Michelle Brown | C19: ='Complete List_09252026'!E9 -> 318 Frederick Street | D19: ='Complete List_09252026'!F9 -> San Francisco | E19: ='Complete List_09252026'!G9 -> CA | F19: ='Complete List_09252026'!H9 -> 94117 | G19: ='Complete List_09252026'!J9 -> brownmi@stanford.edu | H19: ='Complete List_09252026'!K9 -> Electronic | I19: ='Complete List_09252026'!L9 -> Haight Ashbury
A20: ='Complete List_09252026'!D124 -> Haight Ashbury Panhandle Tenants Into Community (HAPTIC) | B20: ='Complete List_09252026'!C124 -> Nick Chapman | C20: ='Complete List_09252026'!E124 -> 1484 Page Street | D20: ='Complete List_09252026'!F124 -> San Francisco | E20: ='Complete List_09252026'!G124 -> CA | F20: ='Complete List_09252026'!H124 -> 94117 | G20: ='Complete List_09252026'!J124 -> sfhaptic@gmail.com | H20: ='Complete List_09252026'!K124 -> Electronic | I20: ='Complete List_09252026'!L124 -> Golden Gate Park, Haight Ashbury, Western Addition

Sheet Inner Richmond
A1: ORGANIZATION | B1: ='Complete List_09252026'!C1 -> NAME | C1: ='Complete List_09252026'!E1 -> ADDRESS | D1: ='Complete List_09252026'!F1 -> CITY | E1: ='Complete List_09252026'!G1 -> STATE | F1: ='Complete List_09252026'!H1 -> ZIP | G1: ='Complete List_09252026'!J1 -> EMAIL | H1: NOTIFICATION PREFERENCES | I1: ='Complete List_09252026'!L1 -> NEIGHBORHOOD OF INTEREST
A2: PHYSICAL NOTICES
A3: ='Complete List_09252026'!D48 -> Cabrillo Alley Neighbors Association | B3: ='Complete List_09252026'!C48 -> John Hou | C3: ='Complete List_09252026'!E48 -> 742 4th Avenue | D3: ='Complete List_09252026'!F48 -> San Francisco | E3: ='Complete List_09252026'!G48 -> CA | F3: ='Complete List_09252026'!H48 -> 94118 | G3: ='Complete List_09252026'!J48 -> cabrillo-alley-neighbors-association@googlegroups.com | H3: ='Complete List_09252026'!K48 -> Physical | I3: ='Complete List_09252026'!L48 -> Inner Richmond
A4: ='Complete List_09252026'!D122 -> Haight Ashbury Neighborhood Council | B4: ='Complete List_09252026'!C122 -> Land Use and Housing Chair | C4: ='Complete List_09252026'!E122 -> P.O. Box 170518 | D4: ='Complete List_09252026'!F122 -> San Francisco | E4: ='Complete List_09252026'!G122 -> CA | F4: ='Complete List_09252026'!H122 -> 94117 | G4: ='Complete List_09252026'!J122 -> info@hanc-sf.org | H4: ='Complete List_09252026'!K122 -> Physical | I4: ='Complete List_09252026'!L122 -> Haight Ashbury, Inner Sunset, Golden Gate Park
A5: ='Complete List_09252026'!D132 -> Housing Rights Committee of San Francisco | B5: ='Complete List_09252026'!C132 -> Sarah Sherburn-Zimmer | C5: ='Complete List_09252026'!E132 -> 1663 Mission Street, Suite 504 | D5: ='Complete List_09252026'!F132 -> San Francisco | E5: ='Complete List_09252026'!G132 -> CA | F5: ='Complete List_09252026'!H132 -> 94103 | G5: ='Complete List_09252026'!J132 -> fred@hrcsf.org | H5: ='Complete List_09252026'!K132 -> Physical | I5: ='Complete List_09252026'!L132 -> Golden Gate Park, Inner Richmond, Inner Sunset, Lakeshore, Outer Richmond, Outer Sunset, Parkside, West of Twin Peaks
A6: ='Complete List_09252026'!D144 -> Jordan Park Improvement Assocation | B6: ='Complete List_09252026'!C144 -> Rose Hillson | C6: ='Complete List_09252026'!E144 -> 115 Parker Avenue | D6: ='Complete List_09252026'!F144 -> San Francisco | E6: ='Complete List_09252026'!G144 -> CA | F6: ='Complete List_09252026'!H144 -> 94118-2607 | G6: ='Complete List_09252026'!J144 -> 0 | H6: ='Complete List_09252026'!K144 -> Physical | I6: ='Complete List_09252026'!L144 -> Inner Richmond, Marina, Pacific Heights, Presidio Heights, Outer Richmond, Seacliff
A7: ='Complete List_09252026'!D151 -> Laurel Heights Improvement Association of SF, Inc. | B7: ='Complete List_09252026'!C151 -> Kathryn Devincenzi | C7: ='Complete List_09252026'!E151 -> 22 Iris Avenue | D7: ='Complete List_09252026'!F151 -> San Francisco | E7: ='Complete List_09252026'!G151 -> CA | F7: ='Complete List_09252026'!H151 -> 94118 | G7: ='Complete List_09252026'!J151 -> KRDevincenzi@gmail.com | H7: ='Complete List_09252026'!K151 -> Physical | I7: ='Complete List_09252026'!L151 -> Inner Richmond, Pacific Heights, Presidio Heights
A8: ='Complete List_09252026'!D178 -> Mid-Richmond Coalition | B8: ='Complete List_09252026'!C178 -> Megan Sullivan | C8: ='Complete List_09252026'!E178 -> 376 17th Avenue | D8: ='Complete List_09252026'!F178 -> San Francisco | E8: ='Complete List_09252026'!G178 -> CA | F8: ='Complete List_09252026'!H178 -> 94121 | G8: ='Complete List_09252026'!J178 -> sulliblums@gmail.com | H8: ='Complete List_09252026'!K178 -> Physical | I8: ='Complete List_09252026'!L178 -> Inner Richmond, Outer Richmond
A9: ='Complete List_09252026'!D289 -> Temescal Terrace Association | B9: ='Complete List_09252026'!C289 -> Richard Rabbitt | C9: ='Complete List_09252026'!E289 -> 55 Temescal Terrace | D9: ='Complete List_09252026'!F289 -> San Francisco | E9: ='Complete List_09252026'!G289 -> CA | F9: ='Complete List_09252026'!H289 -> 94118 | G9: ='Complete List_09252026'!J289 -> richard.rabbitt@stanfordalumni.org | H9: ='Complete List_09252026'!K289 -> Physical | I9: ='Complete List_09252026'!L289 -> Haight Ashbury, Inner Richmond, Presidio Heights, Western Addition
A10: BOTH PHYSICAL & ELECTRONIC NOTICES
A11: ='Complete List_09252026'!D39 -> Board of Supervisors | B11: ='Complete List_09252026'!C39 -> Connie Chan | C11: ='Complete List_09252026'!E39 -> 1 Dr. Carlton B Goodlett Place, Room #244 | D11: ='Complete List_09252026'!F39 -> San Francisco | E11: ='Complete List_09252026'!G39 -> CA | F11: ='Complete List_09252026'!H39 -> 94102-4689 | G11: ='Complete List_09252026'!J39 -> connie.chan@sfgov.org; ian.fregosi@sfgov.org; frances.hsieh@sfgov.org; kelly.groth@sfgov.org; angelina.yu@sfgov.org; ChanStaff@sfgov.org | H11: ='Complete List_09252026'!K39 -> Both | I11: ='Complete List_09252026'!L39 -> Inner Richmond, Outer Richmond, Seacliff
A12: ELECTRONIC NOTICES
A13: ='Complete List_09252026'!D237 -> Richmond District Rising | B13: ='Complete List_09252026'!C237 -> Joseph Smooke | C13: ='Complete List_09252026'!E237 -> 366 10th Ave | D13: ='Complete List_09252026'!F237 -> San Francisco | E13: ='Complete List_09252026'!G237 -> CA | F13: ='Complete List_09252026'!H237 -> 94118 | G13: ='Complete List_09252026'!J237 -> joseph_smooke@yahoo.com | H13: ='Complete List_09252026'!K237 -> Electronic | I13: ='Complete List_09252026'!L237 -> Inner Richmond, Outer Richmond
A14: ='Complete List_09252026'!D120 -> Grow the Richmond | B14: ='Complete List_09252026'!C120 -> Jane Natoli | C14: ='Complete List_09252026'!E120 -> 759 6th Ave #7 | D14: ='Complete List_09252026'!F120 -> San Francisco | E14: ='Complete List_09252026'!G120 -> CA | F14: ='Complete List_09252026'!H120 -> 94118 | G14: ='Complete List_09252026'!J120 -> hello@growtherichmond.com | H14: ='Complete List_09252026'!K120 -> Electronic | I14: ='Complete List_09252026'!L120 -> Inner Richmond, Outer Richmond, Presidio Heights, Seacliff
A15: ='Complete List_09252026'!D229 -> Planning Association for the Richmond (PAR) | B15: ='Complete List_09252026'!C229 -> Dan Baroni | C15: ='Complete List_09252026'!E229 -> 2828 Fulton Street | D15: ='Complete List_09252026'!F229 -> San Francisco | E15: ='Complete List_09252026'!G229 -> CA | F15: ='Complete List_09252026'!H229 -> 94118-3300 | G15: ='Complete List_09252026'!J229 -> dmbaroni@mac.com; sfparlanduse@gmail.com | H15: ='Complete List_09252026'!K229 -> Electronic | I15: ='Complete List_09252026'!L229 -> Inner Richmond, Outer Richmond, Seacliff
A16: ='Complete List_09252026'!D247 -> Self-Help for the Elderly | B16: ='Complete List_09252026'!C247 -> Anni Chung | C16: ='Complete List_09252026'!E247 -> 731 Sansome Street, Suite 1000 | D16: ='Complete List_09252026'!F247 -> San Francisco | E16: ='Complete List_09252026'!G247 -> CA | F16: ='Complete List_09252026'!H247 -> 94111 | G16: ='Complete List_09252026'!J247 -> annic@selfhelpelderly.org | H16: ='Complete List_09252026'!K247 -> Electronic | I16: ='Complete List_09252026'!L247 -> Chinatown, Inner Richmond, Inner Sunset, Outer Richmond, Outer Sunset
A17: ='Complete List_09252026'!D301 -> University Terrace Association | B17: ='Complete List_09252026'!C301 -> Niall Vignoles | C17: ='Complete List_09252026'!E301 -> 52 Roselyn Terrace | D17: ='Complete List_09252026'!F301 -> San Francisco | E17: ='Complete List_09252026'!G301 -> CA | F17: ='Complete List_09252026'!H301 -> 94118 | G17: ='Complete List_09252026'!J301 -> universityterraceassociation@yahoo.com | H17: ='Complete List_09252026'!K301 -> Electronic | I17: ='Complete List_09252026'!L301 -> Inner Richmond
A18: ='Complete List_09252026'!D312 -> Westside Community Coalition | B18: ='Complete List_09252026'!C312 -> Joseph Smooke | C18: ='Complete List_09252026'!E312 -> 366 10th Ave | D18: ='Complete List_09252026'!F312 -> San Francisco | E18: ='Complete List_09252026'!G312 -> CA | F18: ='Complete List_09252026'!H312 -> 94118 | G18: ='Complete List_09252026'!J312 -> joseph_smooke@yahoo.com | H18: ='Complete List_09252026'!K312 -> Electronic | I18: ='Complete List_09252026'!L312 -> Inner Richmond, Inner Sunset, Lakeshore, Outer Richmond, Outer Sunset, Parkside

Sheet Inner Sunset
A1: ORGANIZATION | B1: ='Complete List_09252026'!C1 -> NAME | C1: ='Complete List_09252026'!E1 -> ADDRESS | D1: ='Complete List_09252026'!F1 -> CITY | E1: ='Complete List_09252026'!G1 -> STATE | F1: ='Complete List_09252026'!H1 -> ZIP | G1: ='Complete List_09252026'!J1 -> EMAIL | H1: NOTIFICATION PREFERENCES | I1: ='Complete List_09252026'!L1 -> NEIGHBORHOOD OF INTEREST
A2: PHYSICAL NOTICES
A3: ='Complete List_09252026'!D91 -> Edgewood Neighborhood Association | B3: ='Complete List_09252026'!C91 -> Sarah Jones | C3: ='Complete List_09252026'!E91 -> 190 Edgewood Ave | D3: ='Complete List_09252026'!F91 -> San Francisco | E3: ='Complete List_09252026'!G91 -> CA | F3: ='Complete List_09252026'!H91 -> 94117 | G3: ='Complete List_09252026'!J91 -> sarahsmithjones@gmail.com | H3: ='Complete List_09252026'!K91 -> Physical | I3: ='Complete List_09252026'!L91 -> Inner Sunset
A4: ='Complete List_09252026'!D132 -> Housing Rights Committee of San Francisco | B4: ='Complete List_09252026'!C132 -> Sarah Sherburn-Zimmer | C4: ='Complete List_09252026'!E132 -> 1663 Mission Street, Suite 504 | D4: ='Complete List_09252026'!F132 -> San Francisco | E4: ='Complete List_09252026'!G132 -> CA | F4: ='Complete List_09252026'!H132 -> 94103 | G4: ='Complete List_09252026'!J132 -> fred@hrcsf.org | H4: ='Complete List_09252026'!K132 -> Physical | I4: ='Complete List_09252026'!L132 -> Golden Gate Park, Inner Richmond, Inner Sunset, Lakeshore, Outer Richmond, Outer Sunset, Parkside, West of Twin Peaks
A5: ='Complete List_09252026'!D136 -> Inner Sunset Neighborhood Association | B5: ='Complete List_09252026'!C136 -> Cheryl L. Switzer | C5: ='Complete List_09252026'!E136 -> 1309 - 12th Avenue | D5: ='Complete List_09252026'!F136 -> San Francisco | E5: ='Complete List_09252026'!G136 -> CA | F5: ='Complete List_09252026'!H136 -> 94122 | G5: ='Complete List_09252026'!J136 -> 0 | H5: ='Complete List_09252026'!K136 -> Physical | I5: ='Complete List_09252026'!L136 -> Inner Sunset
A6: ='Complete List_09252026'!D137 -> Inner Sunset Neighborhood Association | C6: ='Complete List_09252026'!E137 -> 1515 5th Ave | D6: ='Complete List_09252026'!F137 -> San Francisco | E6: ='Complete List_09252026'!G137 -> CA | F6: ='Complete List_09252026'!H137 -> 94122 | G6: ='Complete List_09252026'!J137 -> mariawabl@gmail.com | H6: ='Complete List_09252026'!K137 -> Physical | I6: ='Complete List_09252026'!L137 -> Inner Sunset
A7: ='Complete List_09252026'!D193 -> Mt. Sutro Woods Owners Association Inc. | B7: ='Complete List_09252026'!C193 -> Everett Hewlett | C7: ='Complete List_09252026'!E193 -> 419 Crestmont Drive | D7: ='Complete List_09252026'!F193 -> San Francisco | E7: ='Complete List_09252026'!G193 -> CA | F7: ='Complete List_09252026'!H193 -> 94131 | G7: ='Complete List_09252026'!J193 -> ehewlettjr@earthlink.net | H7: ='Complete List_09252026'!K193 -> Physical | I7: ='Complete List_09252026'!L193 -> Inner Sunset
A8: ='Complete List_09252026'!D261 -> Sherwin Williams | B8: ='Complete List_09252026'!C261 -> Francesca Panullo | C8: ='Complete List_09252026'!E261 -> 1415 Ocean Ave | D8: ='Complete List_09252026'!F261 -> San Francisco | E8: ='Complete List_09252026'!G261 -> CA | F8: ='Complete List_09252026'!H261 -> 94112 | G8: ='Complete List_09252026'!J261 -> sw8644@sherwin.com | H8: ='Complete List_09252026'!K261 -> Physical | I8: ='Complete List_09252026'!L261 -> Bayview, Bernal Heights, Crocker Amazon, Diamond Heights, Excelsior, Glen Park, Inner Sunset, Lakeshore, Noe Valley, Ocean View, Outer Mission, Outer Sunset, Parkside, Potrero Hill, South Bayshore, Twin Peaks, Visitacion Valley, West of Twin Peaks
A9: ='Complete List_09252026'!D105 -> Forest Knolls Neighborhood Organization | B9: ='Complete List_09252026'!C105 -> Walter Caplan | C9: ='Complete List_09252026'!E105 -> 157 Warren Drive | D9: ='Complete List_09252026'!F105 -> San Francisco | E9: ='Complete List_09252026'!G105 -> CA | F9: ='Complete List_09252026'!H105 -> 94131-1030 | G9: ='Complete List_09252026'!J105 -> forestknolls@comcast.net | H9: ='Complete List_09252026'!K105 -> Physical | I9: ='Complete List_09252026'!L105 -> Inner Sunset, Twin Peaks
A10: ='Complete List_09252026'!D113 -> Golden Gate Heights Neighborhood Association | B10: ='Complete List_09252026'!C113 -> Sally Stephens | C10: ='Complete List_09252026'!E113 -> P.O. Box 27608 | D10: ='Complete List_09252026'!F113 -> San Francisco | E10: ='Complete List_09252026'!G113 -> CA | F10: ='Complete List_09252026'!H113 -> 94127 | G10: ='Complete List_09252026'!J113 -> info@goldengateheights.org | H10: ='Complete List_09252026'!K113 -> Physical | I10: ='Complete List_09252026'!L113 -> Inner Sunset, Parkside, West of Twin Peaks
A11: ='Complete List_09252026'!D273 -> SPEAK (Sunset-Parkside Education and Action Committee) | B11: ='Complete List_09252026'!C273 -> Eileen Boken | C11: ='Complete List_09252026'!E273 -> 1329 7th Ave | D11: ='Complete List_09252026'!F273 -> San Francisco | E11: ='Complete List_09252026'!G273 -> CA | F11: ='Complete List_09252026'!H273 -> 94122 | G11: ='Complete List_09252026'!J273 -> speaksanfrancisco@yahoo.com | H11: ='Complete List_09252026'!K273 -> Physical | I11: ='Complete List_09252026'!L273 -> Inner Sunset, Outer Sunset, Parkside
A12: BOTH PHYSICAL & ELECTRONIC NOTICES
A13: ='Complete List_09252026'!D40 -> Board of Supervisors | B13: ='Complete List_09252026'!C40 -> Myrna Melgar | C13: ='Complete List_09252026'!E40 -> 1 Dr. Carlton B Goodlett Place, Room #244 | D13: ='Complete List_09252026'!F40 -> San Francisco | E13: ='Complete List_09252026'!G40 -> CA | F13: ='Complete List_09252026'!H40 -> 94102-4689 | G13: ='Complete List_09252026'!J40 -> myrna.melgar@sfgov.org; Jennifer.Fieber@sfgov.org; Megan.Imperial@sfgov.org; Lila.Carrillo@sfgov.org; Jen.Low@sfgov.org; melgarstaff@sfgov.org | H13: ='Complete List_09252026'!K40 -> Both | I13: ='Complete List_09252026'!L40 -> Inner Sunset, Lakeshore, Ocean View, Parkside, Twin Peaks, West of Twin Peaks
A14: ELECTRONIC NOTICES
A15: ='Complete List_09252026'!D135 -> Inner Sunset Merchants Association | B15: ='Complete List_09252026'!C135 -> Board President | C15: ='Complete List_09252026'!E135 -> P. O. Box 225057 | D15: ='Complete List_09252026'!F135 -> San Francisco | E15: ='Complete List_09252026'!G135 -> CA | F15: ='Complete List_09252026'!H135 -> 94122 | G15: ='Complete List_09252026'!J135 -> innersunsetmerchants@gmail.com | H15: ='Complete List_09252026'!K135 -> Electronic | I15: ='Complete List_09252026'!L135 -> Inner Sunset
A16: ='Complete List_09252026'!D311 -> Westside = best side! | B16: ='Complete List_09252026'!C311 -> Maelig Morvan | C16: ='Complete List_09252026'!E311 -> 1444 48th Avenue | D16: ='Complete List_09252026'!F311 -> San Francisco | E16: ='Complete List_09252026'!G311 -> CA | F16: ='Complete List_09252026'!H311 -> 94122 | G16: ='Complete List_09252026'!J311 -> westsidebestsidesf@gmail.com | H16: ='Complete List_09252026'!K311 -> Electronic | I16: ='Complete List_09252026'!L311 -> Inner Sunset, Lakeshore, Outer Sunset, Parkside, West of Twin Peaks
A17: ='Complete List_09252026'!D138 -> Inner Sunset Park Neighbors | B17: ='Complete List_09252026'!C138 -> Lawrence Rosenfeld | C17: ='Complete List_09252026'!E138 -> 1032 Irving Street PMB #511 | D17: ='Complete List_09252026'!F138 -> San Francisco | E17: ='Complete List_09252026'!G138 -> CA | F17: ='Complete List_09252026'!H138 -> 94122 | G17: ='Complete List_09252026'!J138 -> info@inner-sunset.org | H17: ='Complete List_09252026'!K138 -> Electronic | I17: ='Complete List_09252026'!L138 -> Inner Sunset
A18: ='Complete List_09252026'!D200 -> Ninth Avenue Neighbors | B18: ='Complete List_09252026'!C200 -> Harriet Rohmer | C18: ='Complete List_09252026'!E200 -> 1461 Ninth Avenue | D18: ='Complete List_09252026'!F200 -> San Francisco | E18: ='Complete List_09252026'!G200 -> CA | F18: ='Complete List_09252026'!H200 -> 94122 | G18: ='Complete List_09252026'!J200 -> harrietrohmer@gmail.com | H18: ='Complete List_09252026'!K200 -> Electronic | I18: ='Complete List_09252026'!L200 -> Inner Sunset
A19: ='Complete List_09252026'!D247 -> Self-Help for the Elderly | B19: ='Complete List_09252026'!C247 -> Anni Chung | C19: ='Complete List_09252026'!E247 -> 731 Sansome Street, Suite 1000 | D19: ='Complete List_09252026'!F247 -> San Francisco | E19: ='Complete List_09252026'!G247 -> CA | F19: ='Complete List_09252026'!H247 -> 94111 | G19: ='Complete List_09252026'!J247 -> annic@selfhelpelderly.org | H19: ='Complete List_09252026'!K247 -> Electronic | I19: ='Complete List_09252026'!L247 -> Chinatown, Inner Richmond, Inner Sunset, Outer Richmond, Outer Sunset
A20: ='Complete List_09252026'!D281 -> Sunset Heights Association of Responsible People (SHARP) | B20: ='Complete List_09252026'!C281 -> Dennis Minnick | C20: ='Complete List_09252026'!E281 -> 1608A 11th Avenue | D20: ='Complete List_09252026'!F281 -> San Francisco | E20: ='Complete List_09252026'!G281 -> CA | F20: ='Complete List_09252026'!H281 -> 94122 | G20: ='Complete List_09252026'!J281 -> sharp@sharpsf.com | H20: ='Complete List_09252026'!K281 -> Electronic | I20: ='Complete List_09252026'!L281 -> Inner Sunset
A21: ='Complete List_09252026'!D312 -> Westside Community Coalition | B21: ='Complete List_09252026'!C312 -> Joseph Smooke | C21: ='Complete List_09252026'!E312 -> 366 10th Ave | D21: ='Complete List_09252026'!F312 -> San Francisco | E21: ='Complete List_09252026'!G312 -> CA | F21: ='Complete List_09252026'!H312 -> 94118 | G21: ='Complete List_09252026'!J312 -> joseph_smooke@yahoo.com | H21: ='Complete List_09252026'!K312 -> Electronic | I21: ='Complete List_09252026'!L312 -> Inner Richmond, Inner Sunset, Lakeshore, Outer Richmond, Outer Sunset, Parkside
A22: ='Complete List_09252026'!D282 -> Sunset Small Business Network | B22: ='Complete List_09252026'!C282 -> Poppy Gilman | C22: ='Complete List_09252026'!E282 -> 2309 Noriega Street | D22: ='Complete List_09252026'!F282 -> San Francisco | E22: ='Complete List_09252026'!G282 -> CA | F22: ='Complete List_09252026'!H282 -> 94122 | G22: ='Complete List_09252026'!J282 -> poppy.noriegast@gmail.com | H22: ='Complete List_09252026'!K282 -> Electronic | I22: ='Complete List_09252026'!L282 -> Inner Sunset, Outer Sunset, Parkside

Sheet Lakeshore
A1: ORGANIZATION | B1: ='Complete List_09252026'!C1 -> NAME | C1: ='Complete List_09252026'!E1 -> ADDRESS | D1: ='Complete List_09252026'!F1 -> CITY | E1: ='Complete List_09252026'!G1 -> STATE | F1: ='Complete List_09252026'!H1 -> ZIP | G1: ='Complete List_09252026'!J1 -> EMAIL | H1: NOTIFICATION PREFERENCES | I1: ='Complete List_09252026'!L1 -> NEIGHBORHOOD OF INTEREST
A2: PHYSICAL NOTICES
A3: ='Complete List_09252026'!D132 -> Housing Rights Committee of San Francisco | B3: ='Complete List_09252026'!C132 -> Sarah Sherburn-Zimmer | C3: ='Complete List_09252026'!E132 -> 1663 Mission Street, Suite 504 | D3: ='Complete List_09252026'!F132 -> San Francisco | E3: ='Complete List_09252026'!G132 -> CA | F3: ='Complete List_09252026'!H132 -> 94103 | G3: ='Complete List_09252026'!J132 -> fred@hrcsf.org | H3: ='Complete List_09252026'!K132 -> Physical | I3: ='Complete List_09252026'!L132 -> Golden Gate Park, Inner Richmond, Inner Sunset, Lakeshore, Outer Richmond, Outer Sunset, Parkside, West of Twin Peaks
A4: ='Complete List_09252026'!D150 -> Lakeside Property Owners Association | B4: ='Complete List_09252026'!C150 | C4: ='Complete List_09252026'!E150 -> P.O. Box 27516 | D4: ='Complete List_09252026'!F150 -> San Francisco | E4: ='Complete List_09252026'!G150 -> CA | F4: ='Complete List_09252026'!H150 -> 94127 | G4: ='Complete List_09252026'!J150 -> LPOA@lakesidepoa.org | H4: ='Complete List_09252026'!K150 -> Physical | I4: ='Complete List_09252026'!L150 -> Lakeshore
A5: ='Complete List_09252026'!D227 -> Parkmerced Action Coalition | B5: ='Complete List_09252026'!C227 -> Cathy Lentz | C5: ='Complete List_09252026'!E227 -> P.O. BOX 320162 | D5: ='Complete List_09252026'!F227 -> San Francisco | E5: ='Complete List_09252026'!G227 -> CA | F5: ='Complete List_09252026'!H227 -> 94132 | G5: ='Complete List_09252026'!J227 -> parkmercedac@gmail.com | H5: ='Complete List_09252026'!K227 -> Physical | I5: ='Complete List_09252026'!L227 -> Lakeshore, Parkside
A6: ='Complete List_09252026'!D261 -> Sherwin Williams | B6: ='Complete List_09252026'!C261 -> Francesca Panullo | C6: ='Complete List_09252026'!E261 -> 1415 Ocean Ave | D6: ='Complete List_09252026'!F261 -> San Francisco | E6: ='Complete List_09252026'!G261 -> CA | F6: ='Complete List_09252026'!H261 -> 94112 | G6: ='Complete List_09252026'!J261 -> sw8644@sherwin.com | H6: ='Complete List_09252026'!K261 -> Physical | I6: ='Complete List_09252026'!L261 -> Bayview, Bernal Heights, Crocker Amazon, Diamond Heights, Excelsior, Glen Park, Inner Sunset, Lakeshore, Noe Valley, Ocean View, Outer Mission, Outer Sunset, Parkside, Potrero Hill, South Bayshore, Twin Peaks, Visitacion Valley, West of Twin Peaks
A7: ='Complete List_09252026'!D309 -> West of Twin Peaks Central Council | B7: ='Complete List_09252026'!C309 -> Matt Chamberlain | C7: ='Complete List_09252026'!E309 -> P.O. Box 27112 | D7: ='Complete List_09252026'!F309 -> San Francisco | E7: ='Complete List_09252026'!G309 -> CA | F7: ='Complete List_09252026'!H309 -> 94127 | G7: ='Complete List_09252026'!J309 -> info@WestOfTwinPeaks.org President@WestOfTwinPeaks.org | H7: ='Complete List_09252026'!K309 -> Physical | I7: ='Complete List_09252026'!L309 -> Diamond Heights, Lakeshore, Parkside, Twin Peaks, West of Twin Peaks
A8: ='Complete List_09252026'!D149 -> Lakeshore Acres Improvement Club | B8: ='Complete List_09252026'!C149 -> Bill Chionsini | C8: ='Complete List_09252026'!E149 -> P.O. Box 320222 | D8: ='Complete List_09252026'!F149 -> San Francisco | E8: ='Complete List_09252026'!G149 -> CA | F8: ='Complete List_09252026'!H149 -> 94132-0222 | G8: ='Complete List_09252026'!J149 -> SIEL94132@gmail.com | H8: ='Complete List_09252026'!K149 -> Physical | I8: ='Complete List_09252026'!L149 -> Lakeshore
A9: ='Complete List_09252026'!D173 -> Merced Extension Triangle Neighborhood Association (METNA) | B9: ='Complete List_09252026'!C173 -> Marc Christensen | C9: ='Complete List_09252026'!E173 -> 60 Kempton Avenue | D9: ='Complete List_09252026'!F173 -> San Francisco | E9: ='Complete List_09252026'!G173 -> CA | F9: ='Complete List_09252026'!H173 -> 94132-3221 | G9: ='Complete List_09252026'!J173 -> christensen.marc.metna@gmail.com; ragtime217@gmail.com | H9: ='Complete List_09252026'!K173 -> Physical | I9: ='Complete List_09252026'!L173 -> Lakeshore, Ocean View
A10: BOTH PHYSICAL & ELECTRONIC NOTICES
A11: ='Complete List_09252026'!D40 -> Board of Supervisors | B11: ='Complete List_09252026'!C40 -> Myrna Melgar | C11: ='Complete List_09252026'!E40 -> 1 Dr. Carlton B Goodlett Place, Room #244 | D11: ='Complete List_09252026'!F40 -> San Francisco | E11: ='Complete List_09252026'!G40 -> CA | F11: ='Complete List_09252026'!H40 -> 94102-4689 | G11: ='Complete List_09252026'!J40 -> myrna.melgar@sfgov.org; Jennifer.Fieber@sfgov.org; Megan.Imperial@sfgov.org; Lila.Carrillo@sfgov.org; Jen.Low@sfgov.org; melgarstaff@sfgov.org | H11: ='Complete List_09252026'!K40 -> Both | I11: ='Complete List_09252026'!L40 -> Inner Sunset, Lakeshore, Ocean View, Parkside, Twin Peaks, West of Twin Peaks
A12: ='Complete List_09252026'!D42 -> Board of Supervisors | B12: ='Complete List_09252026'!C42 -> Alan Wong | C12: ='Complete List_09252026'!E42 -> 1 Dr. Carlton B Goodlett Place, Room #244 | D12: ='Complete List_09252026'!F42 -> San Francisco | E12: ='Complete List_09252026'!G42 -> CA | F12: ='Complete List_09252026'!H42 -> 94102-4689 | G12: ='Complete List_09252026'!J42 -> Tiff.Lee@sfgov.org; Jessica.Cen@sfgov.org; Andrew.Sinn@sfgov.org; Derek.Lee@sfgov.org; WongStaff@sfgov.org | H12: ='Complete List_09252026'!K42 -> Both | I12: ='Complete List_09252026'!L42 -> Lakeshore, Outer Sunset, Parkside
A13: ELECTRONIC NOTICES
A14: ='Complete List_09252026'!D134 -> Ingleside Terraces Homes Association | B14: ='Complete List_09252026'!C134 -> Paul Conroy | C14: ='Complete List_09252026'!E134 -> P.O. Box 27304 | D14: ='Complete List_09252026'!F134 -> San Francisco | E14: ='Complete List_09252026'!G134 -> CA | F14: ='Complete List_09252026'!H134 -> 94127-0304 | G14: ='Complete List_09252026'!J134 -> President@ithasf.org | H14: ='Complete List_09252026'!K134 -> Electronic | I14: ='Complete List_09252026'!L134 -> Lakeshore, Ocean View, West of Twin Peaks
A15: ='Complete List_09252026'!D311 -> Westside = best side! | B15: ='Complete List_09252026'!C311 -> Maelig Morvan | C15: ='Complete List_09252026'!E311 -> 1444 48th Avenue | D15: ='Complete List_09252026'!F311 -> San Francisco | E15: ='Complete List_09252026'!G311 -> CA | F15: ='Complete List_09252026'!H311 -> 94122 | G15: ='Complete List_09252026'!J311 -> westsidebestsidesf@gmail.com | H15: ='Complete List_09252026'!K311 -> Electronic | I15: ='Complete List_09252026'!L311 -> Inner Sunset, Lakeshore, Outer Sunset, Parkside, West of Twin Peaks
A16: ='Complete List_09252026'!D312 -> Westside Community Coalition | B16: ='Complete List_09252026'!C312 -> Joseph Smooke | C16: ='Complete List_09252026'!E312 -> 366 10th Ave | D16: ='Complete List_09252026'!F312 -> San Francisco | E16: ='Complete List_09252026'!G312 -> CA | F16: ='Complete List_09252026'!H312 -> 94118 | G16: ='Complete List_09252026'!J312 -> joseph_smooke@yahoo.com | H16: ='Complete List_09252026'!K312 -> Electronic | I16: ='Complete List_09252026'!L312 -> Inner Richmond, Inner Sunset, Lakeshore, Outer Richmond, Outer Sunset, Parkside

Sheet Marina
A1: ORGANIZATION | B1: ='Complete List_09252026'!C1 -> NAME | C1: ='Complete List_09252026'!E1 -> ADDRESS | D1: ='Complete List_09252026'!F1 -> CITY | E1: ='Complete List_09252026'!G1 -> STATE | F1: ='Complete List_09252026'!H1 -> ZIP | G1: ='Complete List_09252026'!J1 -> EMAIL | H1: NOTIFICATION PREFERENCES | I1: ='Complete List_09252026'!L1 -> NEIGHBORHOOD OF INTEREST
A2: PHYSICAL NOTICES
A3: ='Complete List_09252026'!D129 -> HERE Local 2 | B3: ='Complete List_09252026'!C129 -> Ian Lewis | C3: ='Complete List_09252026'!E129 -> 209 Golden Gate Avenue | D3: ='Complete List_09252026'!F129 -> San Francisco | E3: ='Complete List_09252026'!G129 -> CA | F3: ='Complete List_09252026'!H129 -> 94102 | G3: ='Complete List_09252026'!J129 -> 0 | H3: ='Complete List_09252026'!K129 -> Physical | I3: ='Complete List_09252026'!L129 -> Chinatown, Downtown/Civic Center, Marina, Mission, Nob Hill, North Beach, Pacific Heights, Presidio, South of Market
A4: ='Complete List_09252026'!D166 -> Marina/Cow Hollow Neighbors & Merchants | B4: ='Complete List_09252026'!C166 -> Patricia Vaughey | C4: ='Complete List_09252026'!E166 -> 2269 Chestnut Street #990 | D4: ='Complete List_09252026'!F166 -> San Francisco | E4: ='Complete List_09252026'!G166 -> CA | F4: ='Complete List_09252026'!H166 -> 94123 | G4: ='Complete List_09252026'!J166 -> 0 | H4: ='Complete List_09252026'!K166 -> Physical | I4: ='Complete List_09252026'!L166 -> Marina, Pacific Heights, Western Addition
A5: ='Complete List_09252026'!D212 -> Oak Grove Group | B5: ='Complete List_09252026'!C212 -> Billy Lee | C5: ='Complete List_09252026'!E212 -> 2505 Oak Street | D5: ='Complete List_09252026'!F212 -> Napa | E5: ='Complete List_09252026'!G212 -> CA | F5: ='Complete List_09252026'!H212 -> 94559 | G5: ='Complete List_09252026'!J212 -> leeway_e@yahoo.com | H5: ='Complete List_09252026'!K212 -> Physical | I5: ='Complete List_09252026'!L212 -> Pacific Heights, Russian Hill, Marina, Nob Hill, Presidio, Presidio Heights, Sea Cliff, Noe Valley, Western Addition
A6: ='Complete List_09252026'!D74 -> Cow Hollow Association | B6: ='Complete List_09252026'!C74 -> Barbara Heffernan | C6: ='Complete List_09252026'!E74 -> 2423 Green Street | D6: ='Complete List_09252026'!F74 -> San Francisco | E6: ='Complete List_09252026'!G74 -> CA | F6: ='Complete List_09252026'!H74 -> 94123 | G6: ='Complete List_09252026'!J74 -> bjhassoc@comcast.net | H6: ='Complete List_09252026'!K74 -> Physical | I6: ='Complete List_09252026'!L74 -> Marina, Pacific Heights
A7: ='Complete List_09252026'!D75 -> Cow Hollow Association | B7: ='Complete List_09252026'!C75 -> Anne Bertrand | C7: ='Complete List_09252026'!E75 -> 1592 Union Street #500 | D7: ='Complete List_09252026'!F75 -> San Francisco | E7: ='Complete List_09252026'!G75 -> CA | F7: ='Complete List_09252026'!H75 -> 94123 | G7: ='Complete List_09252026'!J75 -> bossbien@aol.com | H7: ='Complete List_09252026'!K75 -> Physical | I7: ='Complete List_09252026'!L75 -> Marina, Pacific Heights
A8: ='Complete List_09252026'!D114 -> Golden Gate Valley Neighborhood Association | B8: ='Complete List_09252026'!C114 -> Robert Bardell | C8: ='Complete List_09252026'!E114 -> 1922 Filbert Street | D8: ='Complete List_09252026'!F114 -> San Francisco | E8: ='Complete List_09252026'!G114 -> CA | F8: ='Complete List_09252026'!H114 -> 94123 | G8: ='Complete List_09252026'!J114 -> bbardell@comcast.net | H8: ='Complete List_09252026'!K114 -> Physical | I8: ='Complete List_09252026'!L114 -> Marina, Pacific Heights
A9: ='Complete List_09252026'!D144 -> Jordan Park Improvement Assocation | B9: ='Complete List_09252026'!C144 -> Rose Hillson | C9: ='Complete List_09252026'!E144 -> 115 Parker Avenue | D9: ='Complete List_09252026'!F144 -> San Francisco | E9: ='Complete List_09252026'!G144 -> CA | F9: ='Complete List_09252026'!H144 -> 94118-2607 | G9: ='Complete List_09252026'!J144 -> 0 | H9: ='Complete List_09252026'!K144 -> Physical | I9: ='Complete List_09252026'!L144 -> Inner Richmond, Marina, Pacific Heights, Presidio Heights, Outer Richmond, Seacliff
A10: ='Complete List_09252026'!D245 -> Save the Marina's Heritage | B10: ='Complete List_09252026'!C245 -> Michael Hebel | C10: ='Complete List_09252026'!E245 -> 1555 Francisco Street | D10: ='Complete List_09252026'!F245 -> San Franicsco | E10: ='Complete List_09252026'!G245 -> CA | F10: ='Complete List_09252026'!H245 -> 94123 | G10: ='Complete List_09252026'!J245 -> savethemarinaheritage@gmail.com | H10: ='Complete List_09252026'!K245 -> Physical | I10: ='Complete List_09252026'!L245 -> Marina, Pacific Heights
A11: BOTH PHYSICAL & ELECTRONIC NOTICES
A12: ='Complete List_09252026'!D41 -> Board of Supervisors | B12: ='Complete List_09252026'!C41 -> Stephen Sherrill | C12: ='Complete List_09252026'!E41 -> 1 Dr. Carlton B Goodlett Place, Room #244 | D12: ='Complete List_09252026'!F41 -> San Francisco | E12: ='Complete List_09252026'!G41 -> CA | F12: ='Complete List_09252026'!H41 -> 94102-4689 | G12: ='Complete List_09252026'!J41 -> SherrillStaff@sfgov.org; Lorenzo.Rosas@sfgov.org | H12: ='Complete List_09252026'!K41 -> Both | I12: ='Complete List_09252026'!L41 -> Marina, Pacific Heights, Presidio, Presidio Heights, Russian Hill, Seacliff, Western Addition
A13: ELECTRONIC NOTICES
A14: ='Complete List_09252026'!D76 -> Cow Hollow Association | G14: ='Complete List_09252026'!J76 -> brookesampson@yahoo.com | H14: ='Complete List_09252026'!K76 -> Electronic | I14: ='Complete List_09252026'!L76 -> Marina, Pacific Heights
A15: ='Complete List_09252026'!D167 -> Marina Community Association | B15: ='Complete List_09252026'!C167 -> Neighborhood Planning Committee | C15: ='Complete List_09252026'!E167 -> 1517 North Point Street, #465 | D15: ='Complete List_09252026'!F167 -> San Francisco | E15: ='Complete List_09252026'!G167 -> CA | F15: ='Complete List_09252026'!H167 -> 94123 | G15: ='Complete List_09252026'!J167 -> cbeckman@sfmca.org | H15: ='Complete List_09252026'!K167 -> Electronic | I15: ='Complete List_09252026'!L167 -> Marina, Presidio
A16: ='Complete List_09252026'!D298 -> Union Street Association | B16: ='Complete List_09252026'!C298 -> Lesley Leonhardt | C16: ='Complete List_09252026'!E298 -> PO Box 470393 | D16: ='Complete List_09252026'!F298 -> San Francisco | E16: ='Complete List_09252026'!G298 -> CA | F16: ='Complete List_09252026'!H298 -> 94147 | G16: ='Complete List_09252026'!J298 -> LL@imagesnorth.com | H16: ='Complete List_09252026'!K298 -> Electronic | I16: ='Complete List_09252026'!L298 -> Marina, Pacific Heights
A17: ='Complete List_09252026'!D20 -> Avila Street Corridor | B17: ='Complete List_09252026'!C20 -> SatKartar Khalsa | C17: ='Complete List_09252026'!E20 -> 333 Avila Street | D17: ='Complete List_09252026'!F20 -> San Francisco | E17: ='Complete List_09252026'!G20 -> CA | F17: ='Complete List_09252026'!H20 -> 94123 | G17: ='Complete List_09252026'!J20 -> avilastreetcorridor@gmail.com | H17: ='Complete List_09252026'!K20 -> Electronic | I17: ='Complete List_09252026'!L20 -> Marina

Sheet Mission
A1: ORGANIZATION | B1: ='Complete List_09252026'!C1 -> NAME | C1: ='Complete List_09252026'!E1 -> ADDRESS | D1: ='Complete List_09252026'!F1 -> CITY | E1: ='Complete List_09252026'!G1 -> STATE | F1: ='Complete List_09252026'!H1 -> ZIP | G1: ='Complete List_09252026'!J1 -> EMAIL | H1: NOTIFICATION PREFERENCES | I1: ='Complete List_09252026'!L1 -> NEIGHBORHOOD OF INTEREST
A2: PHYSICAL NOTICES
A3: ='Complete List_09252026'!D69 -> Coleridge St. Neighbors | B3: ='Complete List_09252026'!C69 -> Buddy Choy | C3: ='Complete List_09252026'!E69 -> 157 Coleridge Street | D3: ='Complete List_09252026'!F69 -> San Francisco | E3: ='Complete List_09252026'!G69 -> CA | F3: ='Complete List_09252026'!H69 -> 94110 | G3: ='Complete List_09252026'!J69 -> choytate@gmail.com | H3: ='Complete List_09252026'!K69 -> Physical | I3: ='Complete List_09252026'!L69 -> Bernal Heights, Mission, Noe Valley
A4: ='Complete List_09252026'!D129 -> HERE Local 2 | B4: ='Complete List_09252026'!C129 -> Ian Lewis | C4: ='Complete List_09252026'!E129 -> 209 Golden Gate Avenue | D4: ='Complete List_09252026'!F129 -> San Francisco | E4: ='Complete List_09252026'!G129 -> CA | F4: ='Complete List_09252026'!H129 -> 94102 | G4: ='Complete List_09252026'!J129 -> 0 | H4: ='Complete List_09252026'!K129 -> Physical | I4: ='Complete List_09252026'!L129 -> Chinatown, Downtown/Civic Center, Marina, Mission, Nob Hill, North Beach, Pacific Heights, Presidio, South of Market
A5: ='Complete List_09252026'!D155 -> Liberty Hill Resident Association | B5: ='Complete List_09252026'!C155 -> John Barbey | C5: ='Complete List_09252026'!E155 -> 50 Liberty Street | D5: ='Complete List_09252026'!F155 -> San Francisco | E5: ='Complete List_09252026'!G155 -> CA | F5: ='Complete List_09252026'!H155 -> 94110 | G5: ='Complete List_09252026'!J155 -> villabarbei@earthlink.com | H5: ='Complete List_09252026'!K155 -> Physical | I5: ='Complete List_09252026'!L155 -> Mission
A6: ='Complete List_09252026'!D170 -> Market/Octavia Community Advisory Comm. | B6: ='Complete List_09252026'!C170 -> Ted Olsson | C6: ='Complete List_09252026'!E170 -> 30 Sharon Street | D6: ='Complete List_09252026'!F170 -> San Francisco | E6: ='Complete List_09252026'!G170 -> CA | F6: ='Complete List_09252026'!H170 -> 94114-1709 | G6: ='Complete List_09252026'!J170 -> olssonted@yahoo.com | H6: ='Complete List_09252026'!K170 -> Physical | I6: ='Complete List_09252026'!L170 -> Castro/Upper Market, Downtown/Civic Center, Mission
A7: ='Complete List_09252026'!D268 -> SoMaBend Neighborhood Association | B7: ='Complete List_09252026'!C268 -> Eric Lopez | C7: ='Complete List_09252026'!E268 -> P.O. Box 410805 | D7: ='Complete List_09252026'!F268 -> San Francisco | E7: ='Complete List_09252026'!G268 -> CA | F7: ='Complete List_09252026'!H268 -> 94141 | G7: ='Complete List_09252026'!J268 -> somabend.na@gmail.com | H7: ='Complete List_09252026'!K268 -> Physical | I7: ='Complete List_09252026'!L268 -> Downtown/Civic Center, Mission, South of Market
A8: ='Complete List_09252026'!D304 -> Valencia Corridor Merchant Association | B8: ='Complete List_09252026'!C304 -> Sean Quigley | C8: ='Complete List_09252026'!E304 -> 766 Valencia Street, 3rd Floor | D8: ='Complete List_09252026'!F304 -> San Francisco | E8: ='Complete List_09252026'!G304 -> CA | F8: ='Complete List_09252026'!H304 -> 94110 | G8: ='Complete List_09252026'!J304 -> seanq@paxtongate.com | H8: ='Complete List_09252026'!K304 -> Physical | I8: ='Complete List_09252026'!L304 -> Castro/Upper Market, Mission, Potrero Hill
A9: ='Complete List_09252026'!D315 -> Wild Equity Institute | B9: ='Complete List_09252026'!C315 -> Brent Plater | C9: ='Complete List_09252026'!E315 -> 474 Valencia Street Suite 295 | D9: ='Complete List_09252026'!F315 -> San Francisco | E9: ='Complete List_09252026'!G315 -> CA | F9: ='Complete List_09252026'!H315 -> 94103 | G9: ='Complete List_09252026'!J315 -> bplater@wildequity.org | H9: ='Complete List_09252026'!K315 -> Physical | I9: ='Complete List_09252026'!L315 -> Mission
A10: ='Complete List_09252026'!D50 -> Calle 24 Latino Cultural District | B10: ='Complete List_09252026'!C50 -> Erick Arguello | C10: ='Complete List_09252026'!E50 -> 1065 A Hampshire Street | D10: ='Complete List_09252026'!F50 -> San Francisco | E10: ='Complete List_09252026'!G50 -> CA | F10: ='Complete List_09252026'!H50 -> 94110 | G10: ='Complete List_09252026'!J50 -> eriq94110@aol.com | H10: ='Complete List_09252026'!K50 -> Physical | I10: ='Complete List_09252026'!L50 -> Mission
A11: ='Complete List_09252026'!D77 -> Cultural Action Network | B11: ='Complete List_09252026'!C77 -> Rick Hall | C11: ='Complete List_09252026'!E77 -> 2940 16th Street, #200-1 | D11: ='Complete List_09252026'!F77 -> San Francisco | E11: ='Complete List_09252026'!G77 -> CA | F11: ='Complete List_09252026'!H77 -> 94103 | G11: ='Complete List_09252026'!J77 -> rclistad@gmail.com | H11: ='Complete List_09252026'!K77 -> Physical | I11: ='Complete List_09252026'!L77 -> Mission
A12: ='Complete List_09252026'!D194 -> Native American Health Center | B12: ='Complete List_09252026'!C194 | C12: ='Complete List_09252026'!E194 -> 160 Capp Street | D12: ='Complete List_09252026'!F194 -> San Francisco | E12: ='Complete List_09252026'!G194 -> CA | F12: ='Complete List_09252026'!H194 -> 94110 | G12: ='Complete List_09252026'!J194 -> 0 | H12: ='Complete List_09252026'!K194 -> Physical | I12: ='Complete List_09252026'!L194 -> Mission
A13: ='Complete List_09252026'!D228 -> People Organizing to Demand Environmental and Economic Rights (PODER) | B13: ='Complete List_09252026'!C228 -> Antonio Diaz | C13: ='Complete List_09252026'!E228 -> 474 Valencia Street #125 | D13: ='Complete List_09252026'!F228 -> San Francisco | E13: ='Complete List_09252026'!G228 -> CA | F13: ='Complete List_09252026'!H228 -> 94103 | G13: ='Complete List_09252026'!J228 -> info@podersf.org | H13: ='Complete List_09252026'!K228 -> Physical | I13: ='Complete List_09252026'!L228 -> Crocker Amazon, Excelsior, Mission, Ocean View, Outer Mission, South of Market
A14: ='Complete List_09252026'!D14 -> Alliance for a Better District 6 | B14: ='Complete List_09252026'!C14 -> Michael Nulty | C14: ='Complete List_09252026'!E14 -> P.O. Box 420782 | D14: ='Complete List_09252026'!F14 -> San Francisco | E14: ='Complete List_09252026'!G14 -> CA | F14: ='Complete List_09252026'!H14 -> 94142 | G14: ='Complete List_09252026'!J14 -> sf_district6@yahoo.com | H14: ='Complete List_09252026'!K14 -> Physical | I14: ='Complete List_09252026'!L14 -> Downtown/Civic Center, Financial District, Mission, Nob Hill, South of Market, Treasure Island, Western Addition
A15: ='Complete List_09252026'!D156 -> Liberty Hill Neighborhood Association (LHNA) | B15: ='Complete List_09252026'!C156 -> Dr. Elizabeth Fromer | C15: ='Complete List_09252026'!E156 -> 338 Lexington Street | D15: ='Complete List_09252026'!F156 -> San Francisco | E15: ='Complete List_09252026'!G156 -> CA | F15: ='Complete List_09252026'!H156 -> 94110 | G15: ='Complete List_09252026'!J156 -> efromer3@gmail.com | H15: ='Complete List_09252026'!K156 -> Physical | I15: ='Complete List_09252026'!L156 -> Mission
A16: ='Complete List_09252026'!D220 -> Our Mission No Eviction | B16: ='Complete List_09252026'!C220 -> Roberto Hernandez | C16: ='Complete List_09252026'!E220 -> 1333 Florida Street | D16: ='Complete List_09252026'!F220 -> San Francisco | E16: ='Complete List_09252026'!G220 -> CA | F16: ='Complete List_09252026'!H220 -> 94110 | G16: ='Complete List_09252026'!J220 -> latinzoneprod@aol.com | H16: ='Complete List_09252026'!K220 -> Physical | I16: ='Complete List_09252026'!L220 -> Mission
A17: ='Complete List_09252026'!D264 -> SOMA Leadership Council | B17: ='Complete List_09252026'!C264 -> Jaime Whitaker | C17: ='Complete List_09252026'!E264 -> 201 Harrison Street Apt. 229 | D17: ='Complete List_09252026'!F264 -> San Francisco | E17: ='Complete List_09252026'!G264 -> CA | F17: ='Complete List_09252026'!H264 -> 94105 | G17: ='Complete List_09252026'!J264 -> rinconhill@gmail.com | H17: ='Complete List_09252026'!K264 -> Physical | I17: ='Complete List_09252026'!L264 -> Mission, South of Market
A18: BOTH PHYSICAL & ELECTRONIC NOTICES
A19: ='Complete List_09252026'!D44 -> Board of Supervisors | B19: ='Complete List_09252026'!C44 -> Jackie Fielder | C19: ='Complete List_09252026'!E44 -> 1 Dr. Carlton B Goodlett Place, Room #244 | D19: ='Complete List_09252026'!F44 -> San Francisco | E19: ='Complete List_09252026'!G44 -> CA | F19: ='Complete List_09252026'!H44 -> 94102-4689 | G19: ='Complete List_09252026'!J44 -> FielderStaff@sfgov.org; Ana.Herrera@sfgov.org; Preston.Kilgore@sfgov.org | H19: ='Complete List_09252026'!K44 -> Both | I19: ='Complete List_09252026'!L44 -> Bernal Heights, Excelsior, Mission, Visitacion Valley
A20: ELECTRONIC NOTICES
A21: ='Complete List_09252026'!D128 -> Hayes Valley Safe | B21: ='Complete List_09252026'!C128 -> Richard Johnson | C21: ='Complete List_09252026'!E128 -> 415 Buchanan St Apt C | D21: ='Complete List_09252026'!F128 -> San Francisco | E21: ='Complete List_09252026'!G128 -> CA | F21: ='Complete List_09252026'!H128 -> 94102 | G21: ='Complete List_09252026'!J128 -> info@hvsafe.com | H21: ='Complete List_09252026'!K128 -> Electronic | I21: ='Complete List_09252026'!L128 -> Castro/Upper Market, Downtown/Civic Center, Mission, South of Market, Western Addition
A22: ='Complete List_09252026'!D127 -> Hayes Valley Small Business Association | B22: ='Complete List_09252026'!C127 -> Ramiz Y | C22: ='Complete List_09252026'!E127 -> 559 Hayes Street | D22: ='Complete List_09252026'!F127 -> San Francisco | E22: ='Complete List_09252026'!G127 -> CA | F22: ='Complete List_09252026'!H127 -> 94102 | G22: ='Complete List_09252026'!J127 -> info@hvsba.org | H22: ='Complete List_09252026'!K127 -> Electronic | I22: ='Complete List_09252026'!L127 -> Castro/Upper Market, Downtown/Civic Center, Mission, South of Market, Western Addition
A23: ='Complete List_09252026'!D11 -> 19th Street/Oakwood Neighborhood Association | B23: ='Complete List_09252026'!C11 -> Marilyn Hersh | C23: ='Complete List_09252026'!E11 -> 3696 19th Street | D23: ='Complete List_09252026'!F11 -> San Francisco | E23: ='Complete List_09252026'!G11 -> CA | F23: ='Complete List_09252026'!H11 -> 94110 | G23: ='Complete List_09252026'!J11 -> hershmari@gmail.com | H23: ='Complete List_09252026'!K11 -> Electronic | I23: ='Complete List_09252026'!L11 -> Mission
A24: ='Complete List_09252026'!D12 -> 19th Street/Oakwood Neighborhood Association | B24: ='Complete List_09252026'!C12 -> Leslie Chin | C24: ='Complete List_09252026'!E12 -> 41 Oakwood | D24: ='Complete List_09252026'!F12 -> San Francisco | E24: ='Complete List_09252026'!G12 -> CA | F24: ='Complete List_09252026'!H12 -> 94110 | G24: ='Complete List_09252026'!J12 -> lchinflute@gmail.com | H24: ='Complete List_09252026'!K12 -> Electronic | I24: ='Complete List_09252026'!L12 -> Mission
A25: ='Complete List_09252026'!D8 -> 2887 Folsom Street Concerned Residents | B25: ='Complete List_09252026'!C8 -> Edward Stiel | C25: ='Complete List_09252026'!E8 -> 2887 Folsom Street | D25: ='Complete List_09252026'!F8 -> San Francisco | E25: ='Complete List_09252026'!G8 -> CA | F25: ='Complete List_09252026'!H8 -> 94110 | G25: ='Complete List_09252026'!J8 -> eddiestiel@yahoo.com | H25: ='Complete List_09252026'!K8 -> Electronic | I25: ='Complete List_09252026'!L8 -> Mission
A26: ='Complete List_09252026'!D58 -> Central 26th Street Neighborhood Coalition | B26: ='Complete List_09252026'!C58 -> Zoee Astrachan | C26: ='Complete List_09252026'!E58 -> 3441 26th Street | D26: ='Complete List_09252026'!F58 -> San Francisco | E26: ='Complete List_09252026'!G58 -> CA | F26: ='Complete List_09252026'!H58 -> 94114 | G26: ='Complete List_09252026'!J58 -> za@intersticearchitects.com | H26: ='Complete List_09252026'!K58 -> Electronic | I26: ='Complete List_09252026'!L58 -> Mission
A27: ='Complete List_09252026'!D86 -> Dolores Heights Improvement Club-DRC | B27: ='Complete List_09252026'!C86 -> Planning and Land Use Committee | C27: ='Complete List_09252026'!E86 -> 4016 20th Street | D27: ='Complete List_09252026'!F86 -> San Francisco | E27: ='Complete List_09252026'!G86 -> CA | F27: ='Complete List_09252026'!H86 -> 94114 | G27: ='Complete List_09252026'!J86 -> plu@doloresheights.org | H27: ='Complete List_09252026'!K86 -> Electronic | I27: ='Complete List_09252026'!L86 -> Castro/Upper Market, Mission, Noe Valley
A28: ='Complete List_09252026'!D88 -> East Mission Improvement Association (EMIA) | B28: ='Complete List_09252026'!C88 -> Judith Berkowitz | C28: ='Complete List_09252026'!E88 -> 2940 16th Street Room 200-1 (second floor) | D28: ='Complete List_09252026'!F88 -> San Francisco | E28: ='Complete List_09252026'!G88 -> CA | F28: ='Complete List_09252026'!H88 -> 94103 | G28: ='Complete List_09252026'!J88 -> zrants@gmail.com | H28: ='Complete List_09252026'!K88 -> Electronic | I28: ='Complete List_09252026'!L88 -> Mission
A29: ='Complete List_09252026'!D119 -> Greenaction for Health and Environmental Justice | B29: ='Complete List_09252026'!C119 -> Bradley Angel | C29: ='Complete List_09252026'!E119 -> 315 Sutter Street, 2nd Floor | D29: ='Complete List_09252026'!F119 -> San Francisco | E29: ='Complete List_09252026'!G119 -> CA | F29: ='Complete List_09252026'!H119 -> 94108 | G29: ='Complete List_09252026'!J119 -> greenaction@greenaction.org | H29: ='Complete List_09252026'!K119 -> Electronic | I29: ='Complete List_09252026'!L119 -> Bayview, Mission, Potrero Hill, Visitacion Valley
A30: ='Complete List_09252026'!D126 -> Hayes Valley Neighborhood Association | B30: ='Complete List_09252026'!C126 -> Jennifer Laska | C30: ='Complete List_09252026'!E126 -> 400 Grove Street, Suite 3 | D30: ='Complete List_09252026'!F126 -> San Francisco | E30: ='Complete List_09252026'!G126 -> CA | F30: ='Complete List_09252026'!H126 -> 94102 | G30: ='Complete List_09252026'!J126 -> president@hayesvalleysf.org | H30: ='Complete List_09252026'!K126 -> Electronic | I30: ='Complete List_09252026'!L126 -> Castro/Upper Market, Downtown/Civic Center, Mission, South of Market, Western Addition
A31: ='Complete List_09252026'!D184 -> Mission Dolores Neighborhood Association | B31: ='Complete List_09252026'!C184 -> Peter Lewis | C31: ='Complete List_09252026'!E184 -> 72 Landers Street | D31: ='Complete List_09252026'!F184 -> San Francisco | E31: ='Complete List_09252026'!G184 -> CA | F31: ='Complete List_09252026'!H184 -> 94110 | G31: ='Complete List_09252026'!J184 -> missiondna@earthlink.net | H31: ='Complete List_09252026'!K184 -> Electronic | I31: ='Complete List_09252026'!L184 -> Castro/Upper Market, Mission
A32: ='Complete List_09252026'!D185 -> Mission Economic Development Association | B32: ='Complete List_09252026'!C185 -> Jessica Rubio | C32: ='Complete List_09252026'!E185 -> 2301 Mission Street #301 | D32: ='Complete List_09252026'!F185 -> San Francisco | E32: ='Complete List_09252026'!G185 -> CA | F32: ='Complete List_09252026'!H185 -> 94110 | G32: ='Complete List_09252026'!J185 -> jrubio@medasf.org | H32: ='Complete List_09252026'!K185 -> Electronic | I32: ='Complete List_09252026'!L185 -> Excelsior, Mission, Outer Mission
A33: ='Complete List_09252026'!D186 -> Mission Local | B33: ='Complete List_09252026'!C186 -> Annika Hom | C33: ='Complete List_09252026'!E186 -> 2489 Mission Street #14 | D33: ='Complete List_09252026'!F186 -> San Francisco | E33: ='Complete List_09252026'!G186 -> CA | F33: ='Complete List_09252026'!H186 -> 94110 | G33: ='Complete List_09252026'!J186 -> joe.rivanobarros@missionlocal.com | H33: ='Complete List_09252026'!K186 -> Electronic | I33: ='Complete List_09252026'!L186 -> Bernal Heights, Mission
A34: ='Complete List_09252026'!D187 -> Mission Merchants Association | B34: ='Complete List_09252026'!C187 -> Philip Lesser | C34: ='Complete List_09252026'!E187 -> 555 Laurel Avenue #501 | D34: ='Complete List_09252026'!F187 -> San Mateo | E34: ='Complete List_09252026'!G187 -> CA | F34: ='Complete List_09252026'!H187 -> 94401 | G34: ='Complete List_09252026'!J187 -> pflesser555@outlook.com | H34: ='Complete List_09252026'!K187 -> Electronic | I34: ='Complete List_09252026'!L187 -> Mission
A35: ='Complete List_09252026'!D189 -> Mission Neighborhood Centers | B35: ='Complete List_09252026'!C189 -> Rafael Moreno | C35: ='Complete List_09252026'!E189 -> 362 Capp St | D35: ='Complete List_09252026'!F189 -> San Francisco | E35: ='Complete List_09252026'!G189 -> CA | F35: ='Complete List_09252026'!H189 -> 94110 | G35: ='Complete List_09252026'!J189 -> rafael.moreno@mncsf.org | H35: ='Complete List_09252026'!K189 -> Electronic | I35: ='Complete List_09252026'!L189 -> Mission
A36: ='Complete List_09252026'!D232 -> Potrero Boosters Neigborhood Association | B36: ='Complete List_09252026'!C232 -> J.R. Eppler | C36: ='Complete List_09252026'!E232 -> 1459 18th Street, Suite 133 | D36: ='Complete List_09252026'!F232 -> San Francisco | E36: ='Complete List_09252026'!G232 -> CA | F36: ='Complete List_09252026'!H232 -> 94107 | G36: ='Complete List_09252026'!J232 -> president@potreroboosters.org | H36: ='Complete List_09252026'!K232 -> Electronic | I36: ='Complete List_09252026'!L232 -> Mission, Potrero Hill, South of Market
A37: ='Complete List_09252026'!D253 -> San Francisco Christian Center | B37: ='Complete List_09252026'!C253 -> Cynthia Dillard | C37: ='Complete List_09252026'!E253 -> 5845 Mission Street | D37: ='Complete List_09252026'!F253 -> San Francisco | E37: ='Complete List_09252026'!G253 -> CA | F37: ='Complete List_09252026'!H253 -> 94112 | G37: ='Complete List_09252026'!J253 -> cdillard@sfchristiancenter.org | H37: ='Complete List_09252026'!K253 -> Electronic | I37: ='Complete List_09252026'!L253 -> Mission
A38: ='Complete List_09252026'!D255 -> San Francisco Land Use Coalition (SFLUC) | B38: ='Complete List_09252026'!C255 -> Gary Weiss | C38: ='Complete List_09252026'!E255 -> 78 Mars Street | D38: ='Complete List_09252026'!F255 -> San Francisco | E38: ='Complete List_09252026'!G255 -> CA | F38: ='Complete List_09252026'!H255 -> 94114 | G38: ='Complete List_09252026'!J255 -> garysfx@gmail.com | H38: ='Complete List_09252026'!K255 -> Electronic | I38: ='Complete List_09252026'!L255 -> Castro/Upper Market, Diamond Heights, Glen Park, Haight Ashbury, Mission, Noe Valley, South of Market, Twin Peaks, Upper Market, Western Addition
A39: ='Complete List_09252026'!D300 -> United to Save the Mission | B39: ='Complete List_09252026'!C300 -> Larisa Pedroncelli | C39: ='Complete List_09252026'!E300 -> 2940 16th Street, Suite 216 | D39: ='Complete List_09252026'!F300 -> San Francisco | E39: ='Complete List_09252026'!G300 -> CA | F39: ='Complete List_09252026'!H300 -> 94103 | G39: ='Complete List_09252026'!J300 -> circus@factory1.com | H39: ='Complete List_09252026'!K300 -> Electronic | I39: ='Complete List_09252026'!L300 -> Mission
A40: ='Complete List_09252026'!D53 -> Castro LGBTQ Cultural District | B40: ='Complete List_09252026'!C53 -> Jesse Sanford & Stephen Torres | C40: ='Complete List_09252026'!E53 -> 1800 Market Street | D40: ='Complete List_09252026'!F53 -> San Francisco | E40: ='Complete List_09252026'!G53 -> CA | F40: ='Complete List_09252026'!H53 -> 94102 | G40: ='Complete List_09252026'!J53 -> landuse@castrolgbtq.org | H40: ='Complete List_09252026'!K53 -> Electronic | I40: ='Complete List_09252026'!L53 -> Bernal Heights, Castro/Upper Market, Downtown/Civic Center, Mission, Noe Valley, South of Market
